Workbook

Sheet Instruções
A1: Catálogo de mitigações (C2): planilha de trabalho
A3: Objetivo | B3: Selecionar 40 mitigações da base de Saeri et al. (MIT AI Risk Initiative) aplicáveis a organizações que implantam ou operam sistemas de IA, e completar os campos de contribuição do grupo. Decisão 0024.
A4: Fonte | B4: AI Risk Mitigation Database, MIT AI Risk Initiative (airisk.mit.edu), versão pública de 2025-07-23 (arquivo _PUBLIC__Mitigation_Database_2025-07-23.csv). As 831 entradas já estão carregadas na folha Triagem, ordenadas pelos grupos de documentos. Dados sob licença CC BY 4.0: dar o crédito e indicar as alterações (tradução e adaptação).
A5: Passo 1. Triagem | B5: As entradas da base já estão na folha Triagem. O critério Classificada já vem preenchido, por ser objetivo (as 16 sem subcategoria, com código terminado em X, ficam com Não). Cada membro analisa o seu bloco e marca os outros três critérios. A coluna Elegível é calculada.
A6: Passo 2. Seleção | B6: Entre as elegíveis, escolha 40, 10 por membro, respeitando a cobertura da folha Acompanhamento: as subcategorias aplicáveis representadas e cada domínio de risco do MIT com 3 mitigações ou mais. Marque Incluir nelas e Excluir, com motivo, nas demais.
A7: Passo 3. Catálogo | B7: Para cada entrada incluída, preencha a folha Catálogo. Os campos de Saeri (ID, nome original, documento, subcategoria) são copiados da triagem; os demais são contribuição do grupo.
A8: Passo 4. Anotação dupla | B8: Cada mitigação tem dois anotadores, de membros diferentes, para os subdomínios de risco. O anotador B preenche sem ver a coluna do anotador A (oculte-a antes de começar). Depois, os dois discutem as divergências e registram o consenso. Essa anotação dupla é a base da medida de concordância do OE1.
A9: Passo 5. Estimativas | B9: Custo, evidência e concordância seguem a folha Rubrica. A incerteza é calculada. Registre na Fonte da estimativa de onde veio cada avaliação.
A10: Critérios de inclusão | B10: Ator: aplicável a quem implanta ou opera sistemas de IA. Acionável: ação concreta, não condição organizacional. Verificável: há evidência que comprove a aplicação. Classificada: tem subcategoria (não é X.X). As quatro condições são obrigatórias.
A11: Redundância | B11: Quando várias entradas descrevem a mesma ação, escolha uma representativa e registre o ID dela na coluna 'Redundante com' das demais. Não funda entradas: a rastreabilidade até a base depende do ID.
A12: Formato dos subdomínios | B12: Códigos do MIT separados por vírgula e espaço, em ordem crescente: 1.1, 7.3. A ordem importa para o cálculo de concordância exata.
A13: Fonte da estimativa | B13: Modelo de preenchimento [Fontes consultadas], [o que cada uma sustenta]. [O que é julgamento do grupo]. Regras: - Cite só fontes que você abriu e conferiu. Se usar IA para achar fontes, confira cada uma: a IA inventa referências com facilidade. - A fonte original da mitigação (o documento de Saeri) sustenta o que a mitigação é, mas raramente sustenta custo. - Quando não houver fonte externa para alguma estimativa, usaremos esta resposta como padrão: "Custo estimado pelo grupo, pela rubrica." Isso é legítimo; o que não pode é esconder. - Coerência com a rubrica: se a única base for o julgamento do grupo, a evidência é Limitada. Se houver mais de uma fonte, ou uma norma ou guia reconhecido, sem dado empírico, é Média. Robusta exige várias fontes independentes com estudo empírico ou avaliação publicada.
A14: Uso de IA | B14: Permitido como apoio, com validação humana integral de cada entrada, e registrado na coluna Assistência de IA. Saeri et al. relatam que assistentes de IA omitiram, fundiram e inventaram mitigações durante a extração.
... A29: Classificada | B29: Sim
A30: Redundante com (ID)
A31: Elegível | B31: Sim (calculado)
A32: Decisão | B32: Incluir
A33: Motivo da exclusão
A34: Assistência de IA | B34: Não
A35: Observações | B35: Representativa de outras duas entradas equivalentes.
A37: Exemplo ilustrativo de linha do Catálogo | B37: Valores fictícios, só para mostrar o formato.
A38: Nº | B38: 1
A39: Responsável | B39: Renato Pestana de Gouveia
A40: ID na base | B40: (ID da base)
A41: Nome original | B41: Incident response plan
A42: Nome em português | B42: Plano de resposta a incidentes
A43: Documento de origem | B43: NIST AI RMF: Generative AI Profile (NIST, 2024)
A44: Subcategoria (Saeri) | B44: 3.6 Resposta a incidentes e recuperação
A45: Descrição em português | B45: Estabelecer um plano de resposta a incidentes de IA, com papéis, escalonamento e etapas de recuperação.
A46: Subdomínios: anotador A | B46: 3.1, 7.3
... A59: Situação | B59: Concluída
A60: Observações
A61: Chave do documento | B61: nist-2024 (calculado)
A62: Código da subcategoria | B62: 3.6 (calculado)

Sheet Triagem
A1: ID na base | B1: Nome original | C1: Descrição original | D1: Documento de origem | E1: Subcategoria (Saeri) | F1: Responsável | G1: Ator | H1: Acionável | I1: Verificável | J1: Classificada | K1: Redundante com (ID) | L1: Elegível | M1: Decisão | N1: Motivo da exclusão | O1: Assistência de IA | P1: Observações | Q1: IA: Ator | R1: IA: Acionável | S1: IA: Verificável | T1: IA: Classificada | U1: IA: Elegível | V1: IA: Justificativa | W1: IA: Possíveis redundâncias
A2: A0388_NIST2024 | B2: Legal Compliance Alignment | C2: Align GAI development and use with applicable laws and regulations, including those related to data privacy, copyright and intellectual property law. | D2: NIST AI RMF: Generative AI Profile (NIST, 2024) | E2: 4.1 Documentação do sistema | F2: Angelo Andrioli Netho | G2: Sim | H2: Não | I2: Não | J2: Sim | L2: =IF(COUNTA(G2:J2)<4,"",IF(AND(G2="Sim",H2="Sim",I2="Sim",J2="Sim",K2=""),"Sim","Não")) -> Não | O2: Sim | Q2: Sim | R2: Não | S2: Não | T2: Sim | U2: Não | V2: Diretriz genérica, princípio ou condição organizacional, sem ação concreta definida.
A3: A0389_NIST2024 | B3: Training Data Transparency | C3: Establish transparency policies and processes for documenting the origin and history of training data and generated data for GAI applications to advance digital content transparency, while balancing the proprietary nature of training approaches. | D3: NIST AI RMF: Generative AI Profile (NIST, 2024) | E3: 3.2 Governança de dados | F3: Angelo Andrioli Netho | G3: Sim | H3: Sim | I3: Sim | J3: Sim | K3: A0460; A0527 | L3: =IF(COUNTA(G3:J3)<4,"",IF(AND(G3="Sim",H3="Sim",I3="Sim",J3="Sim",K3=""),"Sim","Não")) -> Não | O3: Sim | Q3: Sim | R3: Sim | S3: Sim | T3: Sim | U3: Sim | V3: Aplicável a quem implanta ou opera sistemas de IA; ação concreta e comprovável. | W3: A0460_NIST2024 Transparency Training Adaptation (0,24); A0527_NIST2024 Digital Content Transparency (0,18)
A4: A0390_NIST2024 | B4: Risk Capability Evaluation | C4: Establish policies to evaluate risk-relevant capabilities of GAI and robustness of safety measures, both prior to deployment and on an ongoing basis, through internal and external evaluations. | D4: NIST AI RMF: Generative AI Profile (NIST, 2024) | E4: 3.1 Testes e auditoria | F4: Angelo Andrioli Netho | G4: Sim | H4: Sim | I4: Sim | J4: Sim | L4: =IF(COUNTA(G4:J4)<4,"",IF(AND(G4="Sim",H4="Sim",I4="Sim",J4="Sim",K4=""),"Sim","Não")) -> Sim | O4: Sim | Q4: Sim | R4: Sim | S4: Sim | T4: Sim | U4: Sim | V4: Aplicável a quem implanta ou opera sistemas de IA; ação concreta e comprovável.
A5: A0391_NIST2024 | B5: Risk Tier Definition | C5: Consider the following factors when updating or defining risk tiers for GAI: Abuses and impacts to information integrity; Dependencies between GAI and other IT or data systems; Harm to fundamental rights or public safety; Presentation of obscene, objectionable, offensive, discriminatory, invalid or untruthful output; Psychological impacts to humans (e.g., anthropomorphization, algorithmic aversion, emotional entanglement); Possibility for malicious use; Whether the system introduces significant new security vulnerabilities; Anticipated system impact on some groups compared to others; Unreliable decision making capabilities, validity, adaptability, and variability of GAI system performance over time. | D5: NIST AI RMF: Generative AI Profile (NIST, 2024) | E5: 1.2 Gestão de riscos | F5: Angelo Andrioli Netho | G5: Sim | H5: Sim | I5: Sim | J5: Sim | L5: =IF(COUNTA(G5:J5)<4,"",IF(AND(G5="Sim",H5="Sim",I5="Sim",J5="Sim",K5=""),"Sim","Não")) -> Sim | O5: Sim | Q5: Sim | R5: Sim | S5: Sim | T5: Sim | U5: Sim | V5: Redigida como consideração ou pergunta; a ação subjacente é concreta e aplicável, mas a descrição precisa ser reescrita como ação.
A6: A0392_NIST2024 | B6: Performance Threshold Standards | C6: Establish minimum thresholds for performance or assurance criteria and review as part of deployment approval ("go/"no-go") policies, procedures, and processes, with reviewed processes and approval thresholds reflecting measurement of GAI capabilities and risks. | D6: NIST AI RMF: Generative AI Profile (NIST, 2024) | E6: 1.5 Estruturas de decisão de segurança | F6: Angelo Andrioli Netho | G6: Sim | H6: Sim | I6: Sim | J6: Sim | L6: =IF(COUNTA(G6:J6)<4,"",IF(AND(G6="Sim",H6="Sim",I6="Sim",J6="Sim",K6=""),"Sim","Não")) -> Sim | O6: Sim | Q6: Sim | R6: Sim | S6: Sim | T6: Sim | U6: Sim | V6: Aplicável a quem implanta ou opera sistemas de IA; ação concreta e comprovável.
A7: A0393_NIST2024 | B7: CBRN Testing Protocol | C7: Establish a test plan and response policy, before developing highly capable models, to periodically evaluate whether the model may misuse CBRN information or capabilities and/or offensive cyber capabilities. | D7: NIST AI RMF: Generative AI Profile (NIST, 2024) | E7: 3.1 Testes e auditoria | F7: Angelo Andrioli Netho | G7: Não | H7: Sim | I7: Sim | J7: Sim | L7: =IF(COUNTA(G7:J7)<4,"",IF(AND(G7="Sim",H7="Sim",I7="Sim",J7="Sim",K7=""),"Sim","Não")) -> Não | O7: Sim | Q7: Não | R7: Sim | S7: Sim | T7: Sim | U7: Não | V7: Voltada a quem desenvolve ou treina modelos de fronteira (capacidades perigosas, treinamento em larga escala, pesos, escalonamento); pouco aplicável a quem implanta ou opera.
A8: A0394_NIST2024 | B8: Stakeholder Input Collection | C8: Obtain input from stakeholder communities to identify unacceptable use, in accordance with activities in the AI RMF Map function. | D8: NIST AI RMF: Generative AI Profile (NIST, 2024) | E8: 1.7 Avaliação de impacto social | F8: Angelo Andrioli Netho | G8: Sim | H8: Sim | I8: Sim | J8: Sim | L8: =IF(COUNTA(G8:J8)<4,"",IF(AND(G8="Sim",H8="Sim",I8="Sim",J8="Sim",K8=""),"Sim","Não")) -> Sim | O8: Sim | Q8: Sim | R8: Sim | S8: Sim | T8: Sim | U8: Sim | V8: Aplicável a quem implanta ou opera sistemas de IA; ação concreta e comprovável.
A9: A0395_NIST2024 | B9: Risk Hierarchy Maintenance | C9: Maintain an updated hierarchy of identified and expected GAI risks connected to contexts of GAI model advancement and use, potentially including specialized risk levels for GAI systems that address issues such as model collapse and algorithmic monoculture. | D9: NIST AI RMF: Generative AI Profile (NIST, 2024) | E9: 1.2 Gestão de riscos | F9: Angelo Andrioli Netho | G9: Sim | H9: Sim | I9: Sim | J9: Sim | L9: =IF(COUNTA(G9:J9)<4,"",IF(AND(G9="Sim",H9="Sim",I9="Sim",J9="Sim",K9=""),"Sim","Não")) -> Sim | O9: Sim | Q9: Sim | R9: Sim | S9: Sim | T9: Sim | U9: Sim | V9: Aplicável a quem implanta ou opera sistemas de IA; ação concreta e comprovável.
A10: A0396_NIST2024 | B10: Risk Tolerance Reassessment | C10: Reevaluate organizational risk tolerances to account for unacceptable negative risk (such as where significant negative impacts are imminent, severe harms are actually occurring, or large-scale risks could occur); and broad GAI negative risks, including: Immature safety or risk cultures related to AI and GAI design, development and deployment, public information integrity risks, including impacts on democratic processes, unknown long-term performance characteristics of GAI. | D10: NIST AI RMF: Generative AI Profile (NIST, 2024) | E10: 1.2 Gestão de riscos | F10: Angelo Andrioli Netho | G10: Sim | H10: Sim | I10: Sim | J10: Sim | K10: A0656 | L10: =IF(COUNTA(G10:J10)<4,"",IF(AND(G10="Sim",H10="Sim",I10="Sim",J10="Sim",K10=""),"Sim","Não")) -> Não | O10: Sim | Q10: Sim | R10: Sim | S10: Sim | T10: Sim | U10: Sim | V10: Aplicável a quem implanta ou opera sistemas de IA; ação concreta e comprovável. | W10: A0656_Barrett2024 Risk Tolerance Thresholds (0,16)
A11: A0397_NIST2024 | B11: Development Halt Plan | C11: Devise a plan to halt development or deployment of a GAI system that poses unacceptable negative risk. | D11: NIST AI RMF: Generative AI Profile (NIST, 2024) | E11: 1.5 Estruturas de decisão de segurança | F11: Angelo Andrioli Netho | G11: Sim | H11: Sim | I11: Sim | J11: Sim | L11: =IF(COUNTA(G11:J11)<4,"",IF(AND(G11="Sim",H11="Sim",I11="Sim",J11="Sim",K11=""),"Sim","Não")) -> Sim | M11: Incluir | O11: Sim | Q11: Sim | R11: Sim | S11: Sim | T11: Sim | U11: Sim | V11: Aplicável a quem implanta ou opera sistemas de IA; ação concreta e comprovável.
A12: A0398_NIST2024 | B12: Harmful Content Prevention | C12: Establish policies and mechanisms to prevent GAI systems from generating CSAM, NCII or content that violates the law. | D12: NIST AI RMF: Generative AI Profile (NIST, 2024) | E12: 2.4 Controles de segurança de conteúdo | F12: Angelo Andrioli Netho | G12: Sim | H12: Sim | I12: Sim | J12: Sim | L12: =IF(COUNTA(G12:J12)<4,"",IF(AND(G12="Sim",H12="Sim",I12="Sim",J12="Sim",K12=""),"Sim","Não")) -> Sim | M12: Incluir | O12: Sim | Q12: Sim | R12: Sim | S12: Sim | T12: Sim | U12: Sim | V12: Aplicável a quem implanta ou opera sistemas de IA; ação concreta e comprovável.
A13: A0399_NIST2024 | B13: Acceptable Use Policy | C13: Establish transparent acceptable use policies for GAI that address illegal use or applications of GAI. | D13: NIST AI RMF: Generative AI Profile (NIST, 2024) | E13: 3.3 Gestão de acesso | F13: Angelo Andrioli Netho | G13: Sim | H13: Sim | I13: Sim | J13: Sim | K13: A0415; A0436; A0447 | L13: =IF(COUNTA(G13:J13)<4,"",IF(AND(G13="Sim",H13="Sim",I13="Sim",J13="Sim",K13=""),"Sim","Não")) -> Não | O13: Sim | Q13: Sim | R13: Sim | S13: Sim | T13: Sim | U13: Sim | V13: Aplicável a quem implanta ou opera sistemas de IA; ação concreta e comprovável. | W13: A0415_NIST2024 Interface Use Policy (0,31); A0436_NIST2024 Third-Party Use Policy Update (0,30); A0447_NIST2024 Illegal Use Identification (0,21)
A14: A0400_NIST2024 | B14: Content Provenance Review | C14: Define organizational responsibilities for periodic review of content provenance and incident monitoring for GAI systems. | D14: NIST AI RMF: Generative AI Profile (NIST, 2024) | E14: 3.5 Monitoramento pós-implantação | F14: Angelo Andrioli Netho | G14: Sim | H14: Sim | I14: Sim | J14: Sim | K14: A0637 | L14: =IF(COUNTA(G14:J14)<4,"",IF(AND(G14="Sim",H14="Sim",I14="Sim",J14="Sim",K14=""),"Sim","Não")) -> Não | O14: Sim | Q14: Sim | R14: Sim | S14: Sim | T14: Sim | U14: Sim | V14: Aplicável a quem implanta ou opera sistemas de IA; ação concreta e comprovável. | W14: A0637_Barrett2024 Monitoring of RM policies (0,19)
A15: A0401_NIST2024 | B15: Incident Response Process | C15: Establish organizational policies and procedures for after action reviews of GAI system incident response and incident disclosures, to identify gaps; Update incident response and incident disclosure processes as required. | D15: NIST AI RMF: Generative AI Profile (NIST, 2024) | E15: 3.6 Resposta a incidentes e recuperação | F15: Angelo Andrioli Netho | G15: Sim | H15: Sim | I15: Sim | J15: Sim | K15: A0409; A0439; A0209; | L15: =IF(COUNTA(G15:J15)<4,"",IF(AND(G15="Sim",H15="Sim",I15="Sim",J15="Sim",K15=""),"Sim","Não")) -> Não | O15: Sim | Q15: Sim | R15: Sim | S15: Sim | T15: Sim | U15: Sim | V15: Aplicável a quem implanta ou opera sistemas de IA; ação concreta e comprovável. | W15: A0409_NIST2024 Incident Response Teams (0,24); A0439_NIST2024 Third-Party Response Plans (0,20); A0209_Schuett2023 Security incident response plan (0,19)
A16: A0402_NIST2024 | B16: Documentation Retention Policy | C16: Maintain a document retention policy to keep history for test, evaluation, validation, and verification (TEVV), and digital content transparency methods for GAI. | D16: NIST AI RMF: Generative AI Profile (NIST, 2024) | E16: 4.1 Documentação do sistema | F16: Angelo Andrioli Netho | G16: Sim | H16: Sim | I16: Sim | J16: Sim | K16: A0527 | L16: =IF(COUNTA(G16:J16)<4,"",IF(AND(G16="Sim",H16="Sim",I16="Sim",J16="Sim",K16=""),"Sim","Não")) -> Não | O16: Sim | Q16: Sim | R16: Sim | S16: Sim | T16: Sim | U16: Sim | V16: Aplicável a quem implanta ou opera sistemas de IA; ação concreta e comprovável. | W16: A0527_NIST2024 Digital Content Transparency (0,16)
A17: A0403_NIST2024 | B17: System Inventory Enumeration | C17: Enumerate organizational GAI systems for incorporation into AI system inventory and adjust AI system inventory requirements to account for GAI risks. | D17: NIST AI RMF: Generative AI Profile (NIST, 2024) | E17: 1.2 Gestão de riscos | F17: Angelo Andrioli Netho | G17: Sim | H17: Sim | I17: Sim | J17: Sim | K17: A0638; A0404; | L17: =IF(COUNTA(G17:J17)<4,"",IF(AND(G17="Sim",H17="Sim",I17="Sim",J17="Sim",K17=""),"Sim","Não")) -> Não | O17: Sim | Q17: Sim | R17: Sim | S17: Sim | T17: Sim | U17: Sim | V17: Aplicável a quem implanta ou opera sistemas de IA; ação concreta e comprovável. | W17: A0638_Barrett2024 Inventory AI Systems (0,18); A0404_NIST2024 Inventory Exemption Definition (0,16)
A18: A0404_NIST2024 | B18: Inventory Exemption Definition | C18: Define any inventory exemptions in organizational policies for GAI systems embedded into application software. | D18: NIST AI RMF: Generative AI Profile (NIST, 2024) | E18: 1.2 Gestão de riscos | F18: Angelo Andrioli Netho | G18: Sim | H18: Sim | I18: Sim | J18: Sim | K18: A0403; A0638; | L18: =IF(COUNTA(G18:J18)<4,"",IF(AND(G18="Sim",H18="Sim",I18="Sim",J18="Sim",K18=""),"Sim","Não")) -> Não | O18: Sim | Q18: Sim | R18: Sim | S18: Sim | T18: Sim | U18: Sim | V18: Aplicável a quem implanta ou opera sistemas de IA; ação concreta e comprovável. | W18: A0403_NIST2024 System Inventory Enumeration (0,16); A0638_Barrett2024 Inventory AI Systems (0,15)
A19: A0405_NIST2024 | B19: Comprehensive Inventory Details | C19: In addition to general model, governance, and risk information, consider the following items in GAI system inventory entries: Data provenance information (e.g., source, signatures, versioning, watermarks); Known issues reported from internal bug tracking or external information sharing resources (e.g., AI incident database, AVID, CVE, NVD, or OECD AI incident monitor); Human oversight roles and responsibilities; Special rights and considerations for intellectual property, licensed works, or personal, privileged, proprietary or sensitive data; Underlying foundation models, versions of underlying models, and access modes. | D19: NIST AI RMF: Generative AI Profile (NIST, 2024) | E19: 4.1 Documentação do sistema | F19: Angelo Andrioli Netho | G19: Sim | H19: Sim | I19: Sim | J19: Sim | K19: A0408 | L19: =IF(COUNTA(G19:J19)<4,"",IF(AND(G19="Sim",H19="Sim",I19="Sim",J19="Sim",K19=""),"Sim","Não")) -> Não | O19: Sim | Q19: Sim | R19: Sim | S19: Sim | T19: Sim | U19: Sim | V19: Aplicável a quem implanta ou opera sistemas de IA; ação concreta e comprovável. | W19: A0408_NIST2024 Incident Communication Framework (0,23)
A20: A0406_NIST2024 | B20: Deactivation Protocol | C20: Protocols are put in place to ensure GAI systems are able to be deactivated when necessary. | D20: NIST AI RMF: Generative AI Profile (NIST, 2024) | E20: 3.6 Resposta a incidentes e recuperação | F20: Angelo Andrioli Netho | G20: Sim | H20: Sim | I20: Sim | J20: Sim | L20: =IF(COUNTA(G20:J20)<4,"",IF(AND(G20="Sim",H20="Sim",I20="Sim",J20="Sim",K20=""),"Sim","Não")) -> Sim | O20: Sim | Q20: Sim | R20: Sim | S20: Sim | T20: Sim | U20: Sim | V20: Aplicável a quem implanta ou opera sistemas de IA; ação concreta e comprovável.
A21: A0407_NIST2024 | B21: Decommissioning Considerations | C21: Consider the following factors when decommissioning GAI systems: Data retention requirements; Data security, e.g., containment, protocols, Data leakage after decommissioning; Dependencies between upstream, downstream, or other data, internet of things (IOT) or AI systems; Use of open-source data or models; Users' emotional entanglement with GAI functions. | D21: NIST AI RMF: Generative AI Profile (NIST, 2024) | E21: 3.2 Governança de dados | F21: Angelo Andrioli Netho | G21: Sim | H21: Sim | I21: Sim | J21: Sim | L21: =IF(COUNTA(G21:J21)<4,"",IF(AND(G21="Sim",H21="Sim",I21="Sim",J21="Sim",K21=""),"Sim","Não")) -> Sim | O21: Sim | Q21: Sim | R21: Sim | S21: Sim | T21: Sim | U21: Sim | V21: Redigida como consideração ou pergunta; a ação subjacente é concreta e aplicável, mas a descrição precisa ser reescrita como ação.
A22: A0408_NIST2024 | B22: Incident Communication Framework | C22: Establish organizational roles, policies, and procedures for communicating GAI incidents and performance to AI Actors and downstream stakeholders (including those potentially impacted), via community or official resources (e.g., AI incident database, AVID, CVE, NVD, or OECD AI incident monitor). | D22: NIST AI RMF: Generative AI Profile (NIST, 2024) | E22: 4.3 Relato de incidentes | F22: Angelo Andrioli Netho | G22: Sim | H22: Sim | I22: Sim | J22: Sim | K22: A0405 | L22: =IF(COUNTA(G22:J22)<4,"",IF(AND(G22="Sim",H22="Sim",I22="Sim",J22="Sim",K22=""),"Sim","Não")) -> Não | O22: Sim | Q22: Sim | R22: Sim | S22: Sim | T22: Sim | U22: Sim | V22: Aplicável a quem implanta ou opera sistemas de IA; ação concreta e comprovável. | W22: A0405_NIST2024 Comprehensive Inventory Details (0,23)
A23: A0409_NIST2024 | B23: Incident Response Teams | C23: Establish procedures to engage teams for GAI system incident response with diverse composition and responsibilities based on the particular incident type. | D23: NIST AI RMF: Generative AI Profile (NIST, 2024) | E23: 3.6 Resposta a incidentes e recuperação | F23: Angelo Andrioli Netho | G23: Sim | H23: Sim | I23: Sim | J23: Sim | K23: A0401; A0439; A0209; | L23: =IF(COUNTA(G23:J23)<4,"",IF(AND(G23="Sim",H23="Sim",I23="Sim",J23="Sim",K23=""),"Sim","Não")) -> Não | O23: Sim | Q23: Sim | R23: Sim | S23: Sim | T23: Sim | U23: Sim | V23: Aplicável a quem implanta ou opera sistemas de IA; ação concreta e comprovável. | W23: A0401_NIST2024 Incident Response Process (0,24); A0439_NIST2024 Third-Party Response Plans (0,20); A0209_Schuett2023 Security incident response plan (0,18)
A24: A0410_NIST2024 | B24: Response Team Verification | C24: Establish processes to verify the AI Actors conducting GAI incident response tasks demonstrate and maintain the appropriate skills and training. | D24: NIST AI RMF: Generative AI Profile (NIST, 2024) | E24: 3.6 Resposta a incidentes e recuperação | F24: Angelo Andrioli Netho | G24: Sim | H24: Sim | I24: Sim | J24: Sim | K24: A0401; A0409; | L24: =IF(COUNTA(G24:J24)<4,"",IF(AND(G24="Sim",H24="Sim",I24="Sim",J24="Sim",K24=""),"Sim","Não")) -> Não | O24: Sim | Q24: Sim | R24: Sim | S24: Sim | T24: Sim | U24: Sim | V24: Aplicável a quem implanta ou opera sistemas de IA; ação concreta e comprovável. | W24: A0401_NIST2024 Incident Response Process (0,16); A0409_NIST2024 Incident Response Teams (0,15)
A25: A0411_NIST2024 | B25: National Security Involvement | C25: When systems may raise national security risks, involve national security professionals in mapping, measuring, and managing those risks. | D25: NIST AI RMF: Generative AI Profile (NIST, 2024) | E25: 4.2 Divulgação de riscos | F25: Angelo Andrioli Netho | G25: Sim | H25: Sim | I25: Sim | J25: Sim | L25: =IF(COUNTA(G25:J25)<4,"",IF(AND(G25="Sim",H25="Sim",I25="Sim",J25="Sim",K25=""),"Sim","Não")) -> Sim | O25: Sim | Q25: Não | R25: Sim | S25: Sim | T25: Sim | U25: Não | V25: Voltada a quem desenvolve ou treina modelos de fronteira (capacidades perigosas, treinamento em larga escala, pesos, escalonamento); pouco aplicável a quem implanta ou opera.
A26: A0412_NIST2024 | B26: Whistleblower Protection | C26: Create mechanisms to provide protections for whistleblowers who report, based on reasonable belief, when the organization violates relevant laws or poses a specific and empirically well-substantiated negative risk to public safety (or has already caused harm). | D26: NIST AI RMF: Generative AI Profile (NIST, 2024) | E26: 1.4 Canal de denúncia e proteção ao denunciante | F26: Angelo Andrioli Netho | G26: Sim | H26: Sim | I26: Sim | J26: Sim | K26: A0022; A1044; A0104; | L26: =IF(COUNTA(G26:J26)<4,"",IF(AND(G26="Sim",H26="Sim",I26="Sim",J26="Sim",K26=""),"Sim","Não")) -> Não | O26: Sim | Q26: Sim | R26: Sim | S26: Sim | T26: Sim | U26: Sim | V26: Aplicável a quem implanta ou opera sistemas de IA; ação concreta e comprovável. | W26: A0022_Bengio2025 Whistleblower protection (0,23); A1044_Uuk2024 Whistleblower protections (0,18); A0104_Future of Life Institute2024 Comprehensive whistleblower protection policy (0,18)
A27: A0413_NIST2024 | B27: Independent Evaluation Policy | C27: Policies are in place to bolster oversight of GAI systems with independent evaluations or assessments of GAI models or systems where the type and robustness of evaluations are proportional to the identified risks. | D27: NIST AI RMF: Generative AI Profile (NIST, 2024) | E27: 3.1 Testes e auditoria | F27: Angelo Andrioli Netho | G27: Sim | H27: Sim | I27: Sim | J27: Sim | L27: =IF(COUNTA(G27:J27)<4,"",IF(AND(G27="Sim",H27="Sim",I27="Sim",J27="Sim",K27=""),"Sim","Não")) -> Sim | O27: Sim | Q27: Sim | R27: Sim | S27: Sim | T27: Sim | U27: Sim | V27: Aplicável a quem implanta ou opera sistemas de IA; ação concreta e comprovável.
A28: A0414_NIST2024 | B28: Organizational Role Adjustment | C28: Consider adjustment of organizational roles and components across lifecycle stages of large or complex GAI systems, including: Test and evaluation, validation, and red-teaming of GAI systems; GAI content moderation; GAI system development and engineering; Increased accessibility of GAI tools, interfaces, and systems, Incident response and containment. | D28: NIST AI RMF: Generative AI Profile (NIST, 2024) | E28: 1.1 Estrutura de conselho e supervisão | F28: Angelo Andrioli Netho | G28: Sim | H28: Não | I28: Não | J28: Sim | L28: =IF(COUNTA(G28:J28)<4,"",IF(AND(G28="Sim",H28="Sim",I28="Sim",J28="Sim",K28=""),"Sim","Não")) -> Não | O28: Sim | Q28: Sim | R28: Não | S28: Não | T28: Sim | U28: Não | V28: Diretriz genérica, princípio ou condição organizacional, sem ação concreta definida.
A29: A0415_NIST2024 | B29: Interface Use Policy | C29: Define acceptable use policies for GAI interfaces, modalities, and human-AI configurations (i.e., for chatbots and decision-making tasks), including criteria for the kinds of queries GAI applications should refuse to respond to. | D29: NIST AI RMF: Generative AI Profile (NIST, 2024) | E29: 3.3 Gestão de acesso | F29: Angelo Andrioli Netho | G29: Sim | H29: Sim | I29: Sim | J29: Sim | K29: A0399; A0436; | L29: =IF(COUNTA(G29:J29)<4,"",IF(AND(G29="Sim",H29="Sim",I29="Sim",J29="Sim",K29=""),"Sim","Não")) -> Não | O29: Sim | Q29: Sim | R29: Sim | S29: Sim | T29: Sim | U29: Sim | V29: Aplicável a quem implanta ou opera sistemas de IA; ação concreta e comprovável. | W29: A0399_NIST2024 Acceptable Use Policy (0,31); A0436_NIST2024 Third-Party Use Policy Update (0,18)
A30: A0416_NIST2024 | B30: User Feedback Mechanism | C30: Establish policies for user feedback mechanisms for GAI systems which include thorough instructions and any mechanisms for recourse. | D30: NIST AI RMF: Generative AI Profile (NIST, 2024) | E30: 4.6 Direitos e recursos dos usuários | F30: Angelo Andrioli Netho | G30: Sim | H30: Sim | I30: Sim | J30: Sim | K30: A0687 | L30: =IF(COUNTA(G30:J30)<4,"",IF(AND(G30="Sim",H30="Sim",I30="Sim",J30="Sim",K30=""),"Sim","Não")) -> Não | O30: Sim | Q30: Sim | R30: Sim | S30: Sim | T30: Sim | U30: Sim | V30: Aplicável a quem implanta ou opera sistemas de IA; ação concreta e comprovável. | W30: A0687_Barrett2024 Enable User Feedback & Appeals (0,16)
A31: A0417_NIST2024 | B31: Threat Modeling Process | C31: Engage in threat modeling to anticipate potential risks from GAI systems | D31: NIST AI RMF: Generative AI Profile (NIST, 2024) | E31: 2.3 Engenharia de segurança do modelo | F31: Angelo Andrioli Netho | G31: Sim | H31: Sim | I31: Sim | J31: Sim | L31: =IF(COUNTA(G31:J31)<4,"",IF(AND(G31="Sim",H31="Sim",I31="Sim",J31="Sim",K31=""),"Sim","Não")) -> Sim | O31: Sim | Q31: Sim | R31: Sim | S31: Sim | T31: Sim | U31: Sim | V31: Aplicável a quem implanta ou opera sistemas de IA; ação concreta e comprovável.
A32: A0418_NIST2024 | B32: Risk Measurement Improvement | C32: Establish policies and procedures that address continual improvement processes for GAI risk measurement. Address general risks associated with a lack of explainability and transparency in GAI systems by using ample documentation and techniques such as: application of gradient-based attributions, occlusion/term reduction, counterfactual prompts and prompt engineering, and analysis of embeddings; Assess and update risk measurement approaches at regular cadences | D32: NIST AI RMF: Generative AI Profile (NIST, 2024) | E32: 1.2 Gestão de riscos | F32: Angelo Andrioli Netho | G32: Sim | H32: Sim | I32: Sim | J32: Sim | K32: A0529 | L32: =IF(COUNTA(G32:J32)<4,"",IF(AND(G32="Sim",H32="Sim",I32="Sim",J32="Sim",K32=""),"Sim","Não")) -> Não | O32: Sim | Q32: Sim | R32: Sim | S32: Sim | T32: Sim | U32: Sim | V32: Aplicável a quem implanta ou opera sistemas de IA; ação concreta e comprovável. | W32: A0529_NIST2024 ML Explanation Application (0,23)
A33: A0419_NIST2024 | B33: Standardized Measurement Protocols | C33: Establish policies, procedures, and processes detailing risk measurement in context of use with standardized measurement protocols and structured public feedback exercises such as AI red-teaming or independent external evaluations. | D33: NIST AI RMF: Generative AI Profile (NIST, 2024) | E33: 3.1 Testes e auditoria | F33: Angelo Andrioli Netho | G33: Sim | H33: Sim | I33: Sim | J33: Sim | K33: A0490; A0493; | L33: =IF(COUNTA(G33:J33)<4,"",IF(AND(G33="Sim",H33="Sim",I33="Sim",J33="Sim",K33=""),"Sim","Não")) -> Não | O33: Sim | Q33: Sim | R33: Sim | S33: Sim | T33: Sim | U33: Sim | V33: Aplicável a quem implanta ou opera sistemas de IA; ação concreta e comprovável. | W33: A0490_NIST2024 Feedback Exercise Use Cases (0,16); A0493_NIST2024 External Evaluation Engagement (0,16)
A34: A0420_NIST2024 | B34: Lifecycle Oversight Functions | C34: Establish policies, procedures, and processes for oversight functions (e.g., senior leadership, legal, compliance, including internal evaluation) across the GAI lifecycle, from problem formulation and supply chains to system decommission. | D34: NIST AI RMF: Generative AI Profile (NIST, 2024) | E34: 1.1 Estrutura de conselho e supervisão | F34: Angelo Andrioli Netho | G34: Sim | H34: Sim | I34: Sim | J34: Sim | L34: =IF(COUNTA(G34:J34)<4,"",IF(AND(G34="Sim",H34="Sim",I34="Sim",J34="Sim",K34=""),"Sim","Não")) -> Sim | O34: Sim | Q34: Sim | R34: Sim | S34: Sim | T34: Sim | U34: Sim | V34: Aplicável a quem implanta ou opera sistemas de IA; ação concreta e comprovável.
A35: A0421_NIST2024 | B35: Terms of Service Establishment | C35: Establish terms of use and terms of service for GAI systems. | D35: NIST AI RMF: Generative AI Profile (NIST, 2024) | E35: 3.3 Gestão de acesso | F35: Angelo Andrioli Netho | G35: Sim | H35: Sim | I35: Sim | J35: Sim | K35: A0817 | L35: =IF(COUNTA(G35:J35)<4,"",IF(AND(G35="Sim",H35="Sim",I35="Sim",J35="Sim",K35=""),"Sim","Não")) -> Não | O35: Sim | Q35: Sim | R35: Sim | S35: Sim | T35: Sim | U35: Sim | V35: Aplicável a quem implanta ou opera sistemas de IA; ação concreta e comprovável. | W35: A0817_UK Government2023 Information Sharing with Downstream Users (0,17)
A36: A0422_NIST2024 | B36: Actor Inclusion in Risk ID | C36: Include relevant AI Actors in the GAI system risk identification process. | D36: NIST AI RMF: Generative AI Profile (NIST, 2024) | E36: 1.7 Avaliação de impacto social | F36: Angelo Andrioli Netho | G36: Sim | H36: Sim | I36: Sim | J36: Sim | L36: =IF(COUNTA(G36:J36)<4,"",IF(AND(G36="Sim",H36="Sim",I36="Sim",J36="Sim",K36=""),"Sim","Não")) -> Sim | O36: Sim | Q36: Sim | R36: Sim | S36: Sim | T36: Sim | U36: Sim | V36: Aplicável a quem implanta ou opera sistemas de IA; ação concreta e comprovável.
A37: A0423_NIST2024 | B37: Downstream Impact Verification | C37: Verify that downstream GAI system impacts (such as the use of third-party plugins) are included in the impact documentation process. | D37: NIST AI RMF: Generative AI Profile (NIST, 2024) | E37: 4.1 Documentação do sistema | F37: Angelo Andrioli Netho | G37: Sim | H37: Sim | I37: Sim | J37: Sim | L37: =IF(COUNTA(G37:J37)<4,"",IF(AND(G37="Sim",H37="Sim",I37="Sim",J37="Sim",K37=""),"Sim","Não")) -> Sim | O37: Sim | Q37: Sim | R37: Sim | S37: Sim | T37: Sim | U37: Sim | V37: Aplicável a quem implanta ou opera sistemas de IA; ação concreta e comprovável.
A38: A0424_NIST2024 | B38: Provenance Method Measurement | C38: Establish policies for measuring the effectiveness of employed content provenance methodologies (e.g., cryptography, watermarking, steganography, etc.) | D38: NIST AI RMF: Generative AI Profile (NIST, 2024) | E38: 2.4 Controles de segurança de conteúdo | F38: Angelo Andrioli Netho | G38: Sim | H38: Sim | I38: Sim | J38: Sim | L38: =IF(COUNTA(G38:J38)<4,"",IF(AND(G38="Sim",H38="Sim",I38="Sim",J38="Sim",K38=""),"Sim","Não")) -> Sim | O38: Sim | Q38: Sim | R38: Sim | S38: Sim | T38: Sim | U38: Sim | V38: Aplicável a quem implanta ou opera sistemas de IA; ação concreta e comprovável.
A39: A0425_NIST2024 | B39: Feedback Resource Allocation | C39: Allocate time and resources for outreach, feedback, and recourse processes in GAI system development. | D39: NIST AI RMF: Generative AI Profile (NIST, 2024) | E39: 4.3 Relato de incidentes | F39: Angelo Andrioli Netho | G39: Sim | H39: Não | I39: Sim | J39: Sim | L39: =IF(COUNTA(G39:J39)<4,"",IF(AND(G39="Sim",H39="Sim",I39="Sim",J39="Sim",K39=""),"Sim","Não")) -> Não | O39: Sim | Q39: Sim | R39: Sim | S39: Sim | T39: Sim | U39: Sim | V39: Aplicável a quem implanta ou opera sistemas de IA; ação concreta e comprovável.
A40: A0426_NIST2024 | B40: User Interaction Documentation | C40: Document interactions with GAI systems to users prior to interactive activities, particularly in contexts involving more significant risks. | D40: NIST AI RMF: Generative AI Profile (NIST, 2024) | E40: 4.6 Direitos e recursos dos usuários | F40: Angelo Andrioli Netho | G40: Sim | H40: Sim | I40: Sim | J40: Sim | K40: A0160 | L40: =IF(COUNTA(G40:J40)<4,"",IF(AND(G40="Sim",H40="Sim",I40="Sim",J40="Sim",K40=""),"Sim","Não")) -> Não | O40: Sim | Q40: Sim | R40: Sim | S40: Sim | T40: Sim | U40: Sim | V40: Aplicável a quem implanta ou opera sistemas de IA; ação concreta e comprovável. | W40: A0160_Future of Life Institute2024 User Interaction Monitoring & Response Restri (0,19)
A41: A0427_NIST2024 | B41: Content Rights Categorization | C41: Categorize different types of GAI content with associated third-party rights (e.g., copyright, intellectual property, data privacy). | D41: NIST AI RMF: Generative AI Profile (NIST, 2024) | E41: 3.2 Governança de dados | F41: Angelo Andrioli Netho | G41: Sim | H41: Sim | I41: Sim | J41: Sim | K41: A0650 | L41: =IF(COUNTA(G41:J41)<4,"",IF(AND(G41="Sim",H41="Sim",I41="Sim",J41="Sim",K41=""),"Sim","Não")) -> Não | O41: Sim | Q41: Sim | R41: Sim | S41: Sim | T41: Sim | U41: Sim | V41: Aplicável a quem implanta ou opera sistemas de IA; ação concreta e comprovável. | W41: A0650_Barrett2024 Third-Party Risk (0,18)
A42: A0428_NIST2024 | B42: Joint Educational Activities | C42: Conduct joint educational activities and events in collaboration with third parties to promote best practices for managing GAI risks. | D42: NIST AI RMF: Generative AI Profile (NIST, 2024) | E42: 1.7 Avaliação de impacto social | F42: Angelo Andrioli Netho | G42: Sim | H42: Sim | I42: Sim | J42: Sim | L42: =IF(COUNTA(G42:J42)<4,"",IF(AND(G42="Sim",H42="Sim",I42="Sim",J42="Sim",K42=""),"Sim","Não")) -> Sim | O42: Sim | Q42: Sim | R42: Sim | S42: Sim | T42: Sim | U42: Sim | V42: Aplicável a quem implanta ou opera sistemas de IA; ação concreta e comprovável.
A43: A0429_NIST2024 | B43: Provenance Success Metrics | C43: Develop and validate approaches for measuring the success of content provenance management efforts with third parties (e.g., incidents detected and response times). | D43: NIST AI RMF: Generative AI Profile (NIST, 2024) | E43: 3.5 Monitoramento pós-implantação | F43: Angelo Andrioli Netho | G43: Sim | H43: Sim | I43: Sim | J43: Sim | L43: =IF(COUNTA(G43:J43)<4,"",IF(AND(G43="Sim",H43="Sim",I43="Sim",J43="Sim",K43=""),"Sim","Não")) -> Sim | O43: Sim | Q43: Sim | R43: Sim | S43: Sim | T43: Sim | U43: Sim | V43: Aplicável a quem implanta ou opera sistemas de IA; ação concreta e comprovável.
A44: A0430_NIST2024 | B44: Contract and SLA Standards | C44: Draft and maintain well-defined contracts and service level agreements (SLAs) that specify content ownership, usage rights, quality standards, security requirements, and content provenance expectations for GAI systems. | D44: NIST AI RMF: Generative AI Profile (NIST, 2024) | E44: 3.2 Governança de dados | F44: Angelo Andrioli Netho | G44: Sim | H44: Sim | I44: Sim | J44: Sim | L44: =IF(COUNTA(G44:J44)<4,"",IF(AND(G44="Sim",H44="Sim",I44="Sim",J44="Sim",K44=""),"Sim","Não")) -> Sim | O44: Sim | Q44: Sim | R44: Sim | S44: Sim | T44: Sim | U44: Sim | V44: Aplicável a quem implanta ou opera sistemas de IA; ação concreta e comprovável.
A45: A0431_NIST2024 | B45: Supplier Risk Assessment | C45: Implement a use-cased based supplier risk assessment framework to evaluate and monitor third-party entities' performance and adherence to content provenance standards and technologies to detect anomalies and unauthorized changes; services acquisition and value chain risk management; and legal compliance. | D45: NIST AI RMF: Generative AI Profile (NIST, 2024) | E45: 1.2 Gestão de riscos | F45: Angelo Andrioli Netho | G45: Sim | H45: Sim | I45: Sim | J45: Sim | L45: =IF(COUNTA(G45:J45)<4,"",IF(AND(G45="Sim",H45="Sim",I45="Sim",J45="Sim",K45=""),"Sim","Não")) -> Sim | O45: Sim | Q45: Sim | R45: Sim | S45: Sim | T45: Sim | U45: Sim | V45: Aplicável a quem implanta ou opera sistemas de IA; ação concreta e comprovável.
A46: A0432_NIST2024 | B46: Contract Evaluation Clauses | C46: Include clauses in contracts which allow an organization to evaluate third-party GAI processes and standards. | D46: NIST AI RMF: Generative AI Profile (NIST, 2024) | E46: 3.1 Testes e auditoria | F46: Angelo Andrioli Netho | G46: Sim | H46: Sim | I46: Sim | J46: Sim | L46: =IF(COUNTA(G46:J46)<4,"",IF(AND(G46="Sim",H46="Sim",I46="Sim",J46="Sim",K46=""),"Sim","Não")) -> Sim | O46: Sim | Q46: Sim | R46: Sim | S46: Sim | T46: Sim | U46: Sim | V46: Aplicável a quem implanta ou opera sistemas de IA; ação concreta e comprovável.
A47: A0433_NIST2024 | B47: Third-Party Entity Inventory | C47: Inventory all third-party entities with access to organizational content and establish approved GAI technology and service provider lists. | D47: NIST AI RMF: Generative AI Profile (NIST, 2024) | E47: 3.3 Gestão de acesso | F47: Angelo Andrioli Netho | G47: Sim | H47: Sim | I47: Sim | J47: Sim | L47: =IF(COUNTA(G47:J47)<4,"",IF(AND(G47="Sim",H47="Sim",I47="Sim",J47="Sim",K47=""),"Sim","Não")) -> Sim | M47: Incluir | O47: Sim | Q47: Sim | R47: Sim | S47: Sim | T47: Sim | U47: Sim | V47: Aplicável a quem implanta ou opera sistemas de IA; ação concreta e comprovável.
A48: A0434_NIST2024 | B48: Third-Party Change Records | C48: Maintain records of changes to content made by third parties to promote content provenance, including sources, timestamps, metadata. | D48: NIST AI RMF: Generative AI Profile (NIST, 2024) | E48: 4.1 Documentação do sistema | F48: Angelo Andrioli Netho | G48: Sim | H48: Sim | I48: Sim | J48: Sim | L48: =IF(COUNTA(G48:J48)<4,"",IF(AND(G48="Sim",H48="Sim",I48="Sim",J48="Sim",K48=""),"Sim","Não")) -> Sim | O48: Sim | Q48: Sim | R48: Sim | S48: Sim | T48: Sim | U48: Sim | V48: Aplicável a quem implanta ou opera sistemas de IA; ação concreta e comprovável.
A49: A0435_NIST2024 | B49: Due Diligence Process Update | C49: Update and integrate due diligence processes for GAI acquisition and procurement vendor assessments to include intellectual property, data privacy, security, and other risks. For example, update processes to: Address solutions that may rely on embedded GAI technologies; Address ongoing monitoring, assessments, and alerting, dynamic risk assessments, and real-time reporting tools for monitoring third-party GAI risks; Consider policy adjustments across GAI modeling libraries, tools and APIs, fine-tuned models, and embedded tools; Assess GAI vendors, open-source or proprietary GAI tools, or GAI service providers against incident or vulnerability databases. | D49: NIST AI RMF: Generative AI Profile (NIST, 2024) | E49: 1.2 Gestão de riscos | F49: Angelo Andrioli Netho | G49: Sim | H49: Sim | I49: Sim | J49: Sim | K49: A0436 | L49: =IF(COUNTA(G49:J49)<4,"",IF(AND(G49="Sim",H49="Sim",I49="Sim",J49="Sim",K49=""),"Sim","Não")) -> Não | O49: Sim | Q49: Sim | R49: Sim | S49: Sim | T49: Sim | U49: Sim | V49: Aplicável a quem implanta ou opera sistemas de IA; ação concreta e comprovável. | W49: A0436_NIST2024 Third-Party Use Policy Update (0,16)
A50: A0436_NIST2024 | B50: Third-Party Use Policy Update | C50: Update GAI acceptable use policies to address proprietary and open-source GAI technologies and data, and contractors, consultants, and other third-party personnel. | D50: NIST AI RMF: Generative AI Profile (NIST, 2024) | E50: 3.3 Gestão de acesso | F50: Angelo Andrioli Netho | G50: Sim | H50: Sim | I50: Sim | J50: Sim | K50: A0399; A0415; A0435; | L50: =IF(COUNTA(G50:J50)<4,"",IF(AND(G50="Sim",H50="Sim",I50="Sim",J50="Sim",K50=""),"Sim","Não")) -> Não | O50: Sim | Q50: Sim | R50: Sim | S50: Sim | T50: Sim | U50: Sim | V50: Aplicável a quem implanta ou opera sistemas de IA; ação concreta e comprovável. | W50: A0399_NIST2024 Acceptable Use Policy (0,30); A0415_NIST2024 Interface Use Policy (0,18); A0435_NIST2024 Due Diligence Process Update (0,16)
A51: A0437_NIST2024 | B51: Value Chain Risk Documentation | C51: Document GAI risks associated with system value chain to identify over-reliance on third-party data and to identify fallbacks. | D51: NIST AI RMF: Generative AI Profile (NIST, 2024) | E51: 4.1 Documentação do sistema | F51: Angelo Andrioli Netho | G51: Sim | H51: Sim | I51: Sim | J51: Sim | K51: A0509; A0744; A0746; | L51: =IF(COUNTA(G51:J51)<4,"",IF(AND(G51="Sim",H51="Sim",I51="Sim",J51="Sim",K51=""),"Sim","Não")) -> Não | O51: Sim | Q51: Sim | R51: Sim | S51: Sim | T51: Sim | U51: Sim | V51: Aplicável a quem implanta ou opera sistemas de IA; ação concreta e comprovável. | W51: A0509_NIST2024 Value Chain Wellbeing Assessment (0,19); A0744_NIST2024 Value Chain and Component Integration (0,19); A0746_NIST2024 Information Integrity; Information Security; (0,18)
A52: A0438_NIST2024 | B52: Third-Party Incident Documentation | C52: Document incidents involving third-party GAI data and systems, including open-source data and open-source software | D52: NIST AI RMF: Generative AI Profile (NIST, 2024) | E52: 4.3 Relato de incidentes | F52: Angelo Andrioli Netho | G52: Sim | H52: Sim | I52: Sim | J52: Sim | K52: A0436 | L52: =IF(COUNTA(G52:J52)<4,"",IF(AND(G52="Sim",H52="Sim",I52="Sim",J52="Sim",K52=""),"Sim","Não")) -> Não | O52: Sim | Q52: Sim | R52: Sim | S52: Sim | T52: Sim | U52: Sim | V52: Aplicável a quem implanta ou opera sistemas de IA; ação concreta e comprovável. | W52: A0436_NIST2024 Third-Party Use Policy Update (0,15)
A53: A0439_NIST2024 | B53: Third-Party Response Plans | C53: Establish incident response plans for third-party GAI technologies: Align incident response plans with impacts enumerated in MAP 5.1; Communicate third-party GAI incident response plans to all relevant AI Actors; Define ownership of GAI incident response functions; Rehearse third-party GAI incident response plans at a regular cadence; Improve incident response plans based on retrospective learning; Review incident response plans for alignment with relevant breach reporting, data protection, data privacy, or other laws. | D53: NIST AI RMF: Generative AI Profile (NIST, 2024) | E53: 3.6 Resposta a incidentes e recuperação | F53: Angelo Andrioli Netho | G53: Sim | H53: Sim | I53: Sim | J53: Sim | K53: A0409; A0401; A0830; | L53: =IF(COUNTA(G53:J53)<4,"",IF(AND(G53="Sim",H53="Sim",I53="Sim",J53="Sim",K53=""),"Sim","Não")) -> Não | O53: Sim | Q53: Sim | R53: Sim | S53: Sim | T53: Sim | U53: Sim | V53: Aplicável a quem implanta ou opera sistemas de IA; ação concreta e comprovável. | W53: A0409_NIST2024 Incident Response Teams (0,20); A0401_NIST2024 Incident Response Process (0,20); A0830_UK Government2023 Incident Response, Escalation, and Remeditati (0,16)
A54: A0440_NIST2024 | B54: Third-Party Monitoring Policy | C54: Establish policies and procedures for continuous monitoring of third-party GAI systems in deployment. | D54: NIST AI RMF: Generative AI Profile (NIST, 2024) | E54: 3.5 Monitoramento pós-implantação | F54: Angelo Andrioli Netho | G54: Sim | H54: Sim | I54: Sim | J54: Sim | K54: A0077; A0441; | L54: =IF(COUNTA(G54:J54)<4,"",IF(AND(G54="Sim",H54="Sim",I54="Sim",J54="Sim",K54=""),"Sim","Não")) -> Não | O54: Sim | Q54: Sim | R54: Sim | S54: Sim | T54: Sim | U54: Sim | V54: Aplicável a quem implanta ou opera sistemas de IA; ação concreta e comprovável. | W54: A0077_Eisenberg2025 Establish responsible development and deploym (0,18); A0441_NIST2024 Data Redundancy Policy (0,18)
A55: A0441_NIST2024 | B55: Data Redundancy Policy | C55: Establish policies and procedures that address GAI data redundancy, including model weights and other system artifacts. | D55: NIST AI RMF: Generative AI Profile (NIST, 2024) | E55: 3.2 Governança de dados | F55: Angelo Andrioli Netho | G55: Sim | H55: Sim | I55: Sim | J55: Sim | K55: A0440 | L55: =IF(COUNTA(G55:J55)<4,"",IF(AND(G55="Sim",H55="Sim",I55="Sim",J55="Sim",K55=""),"Sim","Não")) -> Não | O55: Sim | Q55: Sim | R55: Sim | S55: Sim | T55: Sim | U55: Sim | V55: Aplicável a quem implanta ou opera sistemas de IA; ação concreta e comprovável. | W55: A0440_NIST2024 Third-Party Monitoring Policy (0,18)
A56: A0442_NIST2024 | B56: Rollover and Fallback Management | C56: Establish policies and procedures to test and manage risks related to rollover and fallback technologies for GAI systems, acknowledging that rollover and fallback may include manual processing. | D56: NIST AI RMF: Generative AI Profile (NIST, 2024) | E56: 3.6 Resposta a incidentes e recuperação | F56: Angelo Andrioli Netho | G56: Sim | H56: Sim | I56: Sim | J56: Sim | L56: =IF(COUNTA(G56:J56)<4,"",IF(AND(G56="Sim",H56="Sim",I56="Sim",J56="Sim",K56=""),"Sim","Não")) -> Sim | O56: Sim | Q56: Sim | R56: Sim | S56: Sim | T56: Sim | U56: Sim | V56: Aplicável a quem implanta ou opera sistemas de IA; ação concreta e comprovável.
A57: A0443_NIST2024 | B57: Vendor Contract Review | C57: Review vendor contracts and avoid arbitrary or capricious termination of critical GAI technologies or vendor services and non-standard terms that may amplify or defer liability in unexpected ways and/or contribute to unauthorized data collection by vendors or third-parties (e.g., secondary data use). Consider: Clear assignment of liability and responsibility for incidents, GAI system changes over time (e.g., fine-tuning, drift, decay); Request: Notification and disclosure for serious incidents arising from third-party data and systems; Service Level Agreements (SLAs) in vendor contracts that address incident response, response times, and availability of critical support. | D57: NIST AI RMF: Generative AI Profile (NIST, 2024) | E57: 3.2 Governança de dados | F57: Angelo Andrioli Netho | G57: Sim | H57: Sim | I57: Sim | J57: Sim | L57: =IF(COUNTA(G57:J57)<4,"",IF(AND(G57="Sim",H57="Sim",I57="Sim",J57="Sim",K57=""),"Sim","Não")) -> Sim | O57: Sim | Q57: Sim | R57: Sim | S57: Sim | T57: Sim | U57: Sim | V57: Aplicável a quem implanta ou opera sistemas de IA; ação concreta e comprovável.
A58: A0444_NIST2024 | B58: Purpose Identification Factors | C58: When identifying intended purposes, consider factors such as internal vs. external use, narrow vs. broad application scope, fine-tuning, and varieties of data sources (e.g., grounding, retrieval-augmented generation). | D58: NIST AI RMF: Generative AI Profile (NIST, 2024) | E58: 1.7 Avaliação de impacto social | F58: Angelo Andrioli Netho | G58: Sim | H58: Sim | I58: Sim | J58: Sim | L58: =IF(COUNTA(G58:J58)<4,"",IF(AND(G58="Sim",H58="Sim",I58="Sim",J58="Sim",K58=""),"Sim","Não")) -> Sim | O58: Sim | Q58: Sim | R58: Sim | S58: Sim | T58: Sim | U58: Sim | V58: Redigida como consideração ou pergunta; a ação subjacente é concreta e aplicável, mas a descrição precisa ser reescrita como ação.
A59: A0445_NIST2024 | B59: Context of Use Documentation | C59: Determine and document the expected and acceptable GAI system context of use in collaboration with socio-cultural and other domain experts, by assessing: Assumptions and limitations; Direct value to the organization; Intended operational environment and observed usage patterns; Potential positive and negative impacts to individuals, public safety, groups, communities, organizations, democratic institutions, and the physical environment; Social norms and expectations. | D59: NIST AI RMF: Generative AI Profile (NIST, 2024) | E59: 1.7 Avaliação de impacto social | F59: Angelo Andrioli Netho | G59: Sim | H59: Sim | I59: Sim | J59: Sim | L59: =IF(COUNTA(G59:J59)<4,"",IF(AND(G59="Sim",H59="Sim",I59="Sim",J59="Sim",K59=""),"Sim","Não")) -> Sim | O59: Sim | Q59: Sim | R59: Sim | S59: Sim | T59: Sim | U59: Sim | V59: Aplicável a quem implanta ou opera sistemas de IA; ação concreta e comprovável.
A60: A0446_NIST2024 | B60: Risk Measurement Planning | C60: Document risk measurement plans to address identified risks. Plans may include, as applicable: Individual and group cognitive biases (e.g., confirmation bias, funding bias, groupthink) for AI Actors involved in the design, implementation, and use of GAI systems; Known past GAI system incidents and failure modes; In-context use and foreseeable misuse, abuse, and off-label use; Over reliance on quantitative metrics and methodologies without sufficient awareness of their limitations in the context(s) of use; Standard measurement and structured human feedback approaches; Anticipated human-AI configurations. | D60: NIST AI RMF: Generative AI Profile (NIST, 2024) | E60: 1.2 Gestão de riscos | F60: Angelo Andrioli Netho | G60: Sim | H60: Sim | I60: Sim | J60: Sim | L60: =IF(COUNTA(G60:J60)<4,"",IF(AND(G60="Sim",H60="Sim",I60="Sim",J60="Sim",K60=""),"Sim","Não")) -> Sim | O60: Sim | Q60: Sim | R60: Sim | S60: Sim | T60: Sim | U60: Sim | V60: Aplicável a quem implanta ou opera sistemas de IA; ação concreta e comprovável.
A61: A0447_NIST2024 | B61: Illegal Use Identification | C61: Identify and document foreseeable illegal uses or applications of the GAI system that surpass organizational risk tolerances. | D61: NIST AI RMF: Generative AI Profile (NIST, 2024) | E61: 3.3 Gestão de acesso | F61: Angelo Andrioli Netho | G61: Sim | H61: Sim | I61: Sim | J61: Sim | K61: A0399; A0726; | L61: =IF(COUNTA(G61:J61)<4,"",IF(AND(G61="Sim",H61="Sim",I61="Sim",J61="Sim",K61=""),"Sim","Não")) -> Não | O61: Sim | Q61: Sim | R61: Sim | S61: Sim | T61: Sim | U61: Sim | V61: Aplicável a quem implanta ou opera sistemas de IA; ação concreta e comprovável. | W61: A0399_NIST2024 Acceptable Use Policy (0,21); A0726_NIST2024 Information Security (0,15)
A62: A0448_NIST2024 | B62: Interdisciplinary Team Formation | C62: Establish and empower interdisciplinary teams that reflect a wide range of capabilities, competencies, demographic groups, domain expertise, educational backgrounds, lived experiences, professions, and skills across the enterprise to inform and conduct risk measurement and management functions. | D62: NIST AI RMF: Generative AI Profile (NIST, 2024) | E62: 1.1 Estrutura de conselho e supervisão | F62: Angelo Andrioli Netho | G62: Sim | H62: Sim | I62: Sim | J62: Sim | L62: =IF(COUNTA(G62:J62)<4,"",IF(AND(G62="Sim",H62="Sim",I62="Sim",J62="Sim",K62=""),"Sim","Não")) -> Sim | O62: Sim | Q62: Sim | R62: Sim | S62: Sim | T62: Sim | U62: Sim | V62: Aplicável a quem implanta ou opera sistemas de IA; ação concreta e comprovável.
A63: A0449_NIST2024 | B63: Representative Data Verification | C63: Verify that data or benchmarks used in risk measurement, and users, participants, or subjects involved in structured GAI public feedback exercises are representative of diverse in-context user populations. | D63: NIST AI RMF: Generative AI Profile (NIST, 2024) | E63: 3.2 Governança de dados | F63: Angelo Andrioli Netho | G63: Sim | H63: Sim | I63: Sim | J63: Sim | K63: A0494; A0486; | L63: =IF(COUNTA(G63:J63)<4,"",IF(AND(G63="Sim",H63="Sim",I63="Sim",J63="Sim",K63=""),"Sim","Não")) -> Não | O63: Sim | Q63: Sim | R63: Sim | S63: Sim | T63: Sim | U63: Sim | V63: Aplicável a quem implanta ou opera sistemas de IA; ação concreta e comprovável. | W63: A0494_NIST2024 Feedback Independence Verification (0,16); A0486_NIST2024 Feedback Exercise Metrics (0,15)
A64: A0450_NIST2024 | B64: Data Origin Practices | C64: Establish known assumptions and practices for determining data origin and content lineage, for documentation and evaluation purposes. | D64: NIST AI RMF: Generative AI Profile (NIST, 2024) | E64: 3.2 Governança de dados | F64: Angelo Andrioli Netho | G64: Sim | H64: Sim | I64: Sim | J64: Sim | K64: A0459 | L64: =IF(COUNTA(G64:J64)<4,"",IF(AND(G64="Sim",H64="Sim",I64="Sim",J64="Sim",K64=""),"Sim","Não")) -> Não | O64: Sim | Q64: Sim | R64: Sim | S64: Sim | T64: Sim | U64: Sim | V64: Aplicável a quem implanta ou opera sistemas de IA; ação concreta e comprovável. | W64: A0459_NIST2024 Lineage Understanding Evaluation (0,17)
A65: A0451_NIST2024 | B65: Content Flow Testing | C65: Institute test and evaluation for data and content flows within the GAI system, including but not limited to, original data sources, data transformations, and decision-making criteria. | D65: NIST AI RMF: Generative AI Profile (NIST, 2024) | E65: 3.1 Testes e auditoria | F65: Angelo Andrioli Netho | G65: Sim | H65: Sim | I65: Sim | J65: Sim | L65: =IF(COUNTA(G65:J65)<4,"",IF(AND(G65="Sim",H65="Sim",I65="Sim",J65="Sim",K65=""),"Sim","Não")) -> Sim | O65: Sim | Q65: Sim | R65: Sim | S65: Sim | T65: Sim | U65: Sim | V65: Aplicável a quem implanta ou opera sistemas de IA; ação concreta e comprovável.
A66: A0452_NIST2024 | B66: Upstream Dependency Documentation | C66: Identify and document how the system relies on upstream data sources, including for content provenance, and if it serves as an upstream dependency for other systems. | D66: NIST AI RMF: Generative AI Profile (NIST, 2024) | E66: 4.1 Documentação do sistema | F66: Angelo Andrioli Netho | G66: Sim | H66: Sim | I66: Sim | J66: Sim | L66: =IF(COUNTA(G66:J66)<4,"",IF(AND(G66="Sim",H66="Sim",I66="Sim",J66="Sim",K66=""),"Sim","Não")) -> Sim | O66: Sim | Q66: Sim | R66: Sim | S66: Sim | T66: Sim | U66: Sim | V66: Aplicável a quem implanta ou opera sistemas de IA; ação concreta e comprovável.
A67: A0453_NIST2024 | B67: External Network Analysis | C67: Observe and analyze how the GAI system interacts with external networks, and identify any potential for negative externalities, particularly where content provenance might be compromised. | D67: NIST AI RMF: Generative AI Profile (NIST, 2024) | E67: 3.5 Monitoramento pós-implantação | F67: Angelo Andrioli Netho | G67: Sim | H67: Sim | I67: Sim | J67: Sim | L67: =IF(COUNTA(G67:J67)<4,"",IF(AND(G67="Sim",H67="Sim",I67="Sim",J67="Sim",K67=""),"Sim","Não")) -> Sim | O67: Sim | Q67: Sim | R67: Sim | S67: Sim | T67: Sim | U67: Sim | V67: Aplicável a quem implanta ou opera sistemas de IA; ação concreta e comprovável.
A68: A0454_NIST2024 | B68: Output Accuracy Assessment | C68: Assess the accuracy, quality, reliability, and authenticity of GAI output by comparing it to a set of known ground truth data and by using a variety of evaluation methods (e.g., human oversight and automated evaluation, proven cryptographic techniques, review of content inputs). | D68: NIST AI RMF: Generative AI Profile (NIST, 2024) | E68: 3.1 Testes e auditoria | F68: Angelo Andrioli Netho | G68: Sim | H68: Sim | I68: Sim | J68: Sim | L68: =IF(COUNTA(G68:J68)<4,"",IF(AND(G68="Sim",H68="Sim",I68="Sim",J68="Sim",K68=""),"Sim","Não")) -> Sim | O68: Sim | Q68: Sim | R68: Sim | S68: Sim | T68: Sim | U68: Sim | V68: Aplicável a quem implanta ou opera sistemas de IA; ação concreta e comprovável.
A69: A0455_NIST2024 | B69: Data Quality Review | C69: Review and document accuracy, representativeness, relevance, suitability of data used at different stages of AI life cycle. | D69: NIST AI RMF: Generative AI Profile (NIST, 2024) | E69: 3.2 Governança de dados | F69: Angelo Andrioli Netho | G69: Sim | H69: Sim | I69: Sim | J69: Sim | K69: A0489 | L69: =IF(COUNTA(G69:J69)<4,"",IF(AND(G69="Sim",H69="Sim",I69="Sim",J69="Sim",K69=""),"Sim","Não")) -> Não | O69: Sim | Q69: Sim | R69: Sim | S69: Sim | T69: Sim | U69: Sim | V69: Aplicável a quem implanta ou opera sistemas de IA; ação concreta e comprovável. | W69: A0489_NIST2024 Data Quality Evaluation (0,17)
A70: A0456_NIST2024 | B70: Fact-Checking Deployment | C70: Deploy and document fact-checking techniques to verify the accuracy and veracity of information generated by GAI systems, especially when the information comes from multiple (or unknown) sources. | D70: NIST AI RMF: Generative AI Profile (NIST, 2024) | E70: 2.4 Controles de segurança de conteúdo | F70: Angelo Andrioli Netho | G70: Sim | H70: Sim | I70: Sim | J70: Sim | K70: A0061 | L70: =IF(COUNTA(G70:J70)<4,"",IF(AND(G70="Sim",H70="Sim",I70="Sim",J70="Sim",K70=""),"Sim","Não")) -> Não | O70: Sim | Q70: Sim | R70: Sim | S70: Sim | T70: Sim | U70: Sim | V70: Aplicável a quem implanta ou opera sistemas de IA; ação concreta e comprovável. | W70: A0061_Eisenberg2025 Establish information quality assurance frame (0,17)
A71: A0457_NIST2024 | B71: Synthetic Content Detection | C71: Develop and implement testing techniques to identify GAI produced content (e.g., synthetic media) that might be indistinguishable from human-generated content. | D71: NIST AI RMF: Generative AI Profile (NIST, 2024) | E71: 2.4 Controles de segurança de conteúdo | F71: Angelo Andrioli Netho | G71: Sim | H71: Sim | I71: Sim | J71: Sim | L71: =IF(COUNTA(G71:J71)<4,"",IF(AND(G71="Sim",H71="Sim",I71="Sim",J71="Sim",K71=""),"Sim","Não")) -> Sim | O71: Sim | Q71: Sim | R71: Sim | S71: Sim | T71: Sim | U71: Sim | V71: Aplicável a quem implanta ou opera sistemas de IA; ação concreta e comprovável.
A72: A0458_NIST2024 | B72: Adversarial Testing Plans | C72: Implement plans for GAI systems to undergo regular adversarial testing to identify vulnerabilities and potential manipulation or misuse. | D72: NIST AI RMF: Generative AI Profile (NIST, 2024) | E72: 3.1 Testes e auditoria | F72: Angelo Andrioli Netho | G72: Sim | H72: Sim | I72: Sim | J72: Sim | K72: A0063; A0721; | L72: =IF(COUNTA(G72:J72)<4,"",IF(AND(G72="Sim",H72="Sim",I72="Sim",J72="Sim",K72=""),"Sim","Não")) -> Não | O72: Sim | Q72: Sim | R72: Sim | S72: Sim | T72: Sim | U72: Sim | V72: Aplicável a quem implanta ou opera sistemas de IA; ação concreta e comprovável. | W72: A0063_Eisenberg2025 Implement adversarial testing and red team pr (0,17); A0721_NIST2024 Information Integrity; Information Security (0,16)
A73: A0459_NIST2024 | B73: Lineage Understanding Evaluation | C73: Evaluate whether GAI operators and end-users can accurately understand content lineage and origin. | D73: NIST AI RMF: Generative AI Profile (NIST, 2024) | E73: 3.1 Testes e auditoria | F73: Angelo Andrioli Netho | G73: Sim | H73: Sim | I73: Sim | J73: Sim | K73: A0450 | L73: =IF(COUNTA(G73:J73)<4,"",IF(AND(G73="Sim",H73="Sim",I73="Sim",J73="Sim",K73=""),"Sim","Não")) -> Não | O73: Sim | Q73: Sim | R73: Sim | S73: Sim | T73: Sim | U73: Sim | V73: Aplicável a quem implanta ou opera sistemas de IA; ação concreta e comprovável. | W73: A0450_NIST2024 Data Origin Practices (0,17)
A74: A0460_NIST2024 | B74: Transparency Training Adaptation | C74: Adapt existing training programs to include modules on digital content transparency | D74: NIST AI RMF: Generative AI Profile (NIST, 2024) | E74: 1.1 Estrutura de conselho e supervisão | F74: Angelo Andrioli Netho | G74: Sim | H74: Sim | I74: Sim | J74: Sim | K74: A0389; A0527; | L74: =IF(COUNTA(G74:J74)<4,"",IF(AND(G74="Sim",H74="Sim",I74="Sim",J74="Sim",K74=""),"Sim","Não")) -> Não | O74: Sim | Q74: Sim | R74: Sim | S74: Sim | T74: Sim | U74: Sim | V74: Aplicável a quem implanta ou opera sistemas de IA; ação concreta e comprovável. | W74: A0389_NIST2024 Training Data Transparency (0,24); A0527_NIST2024 Digital Content Transparency (0,19)
A75: A0461_NIST2024 | B75: Risk Management Certification | C75: Develop certification programs that test proficiency in managing GAI risks and interpreting content provenance, relevant to specific industry and context. | D75: NIST AI RMF: Generative AI Profile (NIST, 2024) | E75: 1.1 Estrutura de conselho e supervisão | F75: Angelo Andrioli Netho | G75: Não | H75: Sim | I75: Sim | J75: Sim | L75: =IF(COUNTA(G75:J75)<4,"",IF(AND(G75="Sim",H75="Sim",I75="Sim",J75="Sim",K75=""),"Sim","Não")) -> Não | O75: Sim | Q75: Não | R75: Sim | S75: Sim | T75: Sim | U75: Não | V75: Dirigida a governo, regulador ou ao ecossistema do setor, e não a uma organização que implanta ou opera um sistema.
A76: A0462_NIST2024 | B76: Proficiency Test Delineation | C76: Delineate human proficiency tests from tests of GAI capabilities. | D76: NIST AI RMF: Generative AI Profile (NIST, 2024) | E76: 3.1 Testes e auditoria | F76: Angelo Andrioli Netho | G76: Sim | H76: Sim | I76: Sim | J76: Sim | L76: =IF(COUNTA(G76:J76)<4,"",IF(AND(G76="Sim",H76="Sim",I76="Sim",J76="Sim",K76=""),"Sim","Não")) -> Sim | O76: Sim | Q76: Sim | R76: Não | S76: Não | T76: Sim | U76: Não | V76: Diretriz genérica, princípio ou condição organizacional, sem ação concreta definida.
A77: A0463_NIST2024 | B77: Configuration Outcome Monitoring | C77: Implement systems to continually monitor and track the outcomes of human-GAI configurations for future refinement and improvements. | D77: NIST AI RMF: Generative AI Profile (NIST, 2024) | E77: 3.5 Monitoramento pós-implantação | F77: Angelo Andrioli Netho | G77: Sim | H77: Sim | I77: Sim | J77: Sim | L77: =IF(COUNTA(G77:J77)<4,"",IF(AND(G77="Sim",H77="Sim",I77="Sim",J77="Sim",K77=""),"Sim","Não")) -> Sim | O77: Sim | Q77: Sim | R77: Sim | S77: Sim | T77: Sim | U77: Sim | V77: Aplicável a quem implanta ou opera sistemas de IA; ação concreta e comprovável.
A78: A0464_NIST2024 | B78: Stakeholder Testing Involvement | C78: Involve the end-users, practitioners, and operators in GAI system in prototyping and testing activities. Make sure these tests cover various scenarios, such as crisis situations or ethically sensitive contexts. | D78: NIST AI RMF: Generative AI Profile (NIST, 2024) | E78: 3.1 Testes e auditoria | F78: Angelo Andrioli Netho | G78: Sim | H78: Sim | I78: Sim | J78: Sim | L78: =IF(COUNTA(G78:J78)<4,"",IF(AND(G78="Sim",H78="Sim",I78="Sim",J78="Sim",K78=""),"Sim","Não")) -> Sim | O78: Sim | Q78: Sim | R78: Sim | S78: Sim | T78: Sim | U78: Sim | V78: Aplicável a quem implanta ou opera sistemas de IA; ação concreta e comprovável.
A79: A0465_NIST2024 | B79: Privacy Risk Monitoring | C79: Conduct periodic monitoring of AI-generated content for privacy risks; address any possible instances of PII or sensitive data exposure. | D79: NIST AI RMF: Generative AI Profile (NIST, 2024) | E79: 3.5 Monitoramento pós-implantação | F79: Angelo Andrioli Netho | G79: Sim | H79: Sim | I79: Sim | J79: Sim | K79: A0681 | L79: =IF(COUNTA(G79:J79)<4,"",IF(AND(G79="Sim",H79="Sim",I79="Sim",J79="Sim",K79=""),"Sim","Não")) -> Não | O79: Sim | Q79: Sim | R79: Sim | S79: Sim | T79: Sim | U79: Sim | V79: Aplicável a quem implanta ou opera sistemas de IA; ação concreta e comprovável. | W79: A0681_Barrett2024 Examine & Document Privacy Risk (0,20)
A80: A0466_NIST2024 | B80: IP Infringement Response | C80: Implement processes for responding to potential intellectual property infringement claims or other rights. | D80: NIST AI RMF: Generative AI Profile (NIST, 2024) | E80: 3.6 Resposta a incidentes e recuperação | F80: Angelo Andrioli Netho | G80: Sim | H80: Sim | I80: Sim | J80: Sim | K80: A0470 | L80: =IF(COUNTA(G80:J80)<4,"",IF(AND(G80="Sim",H80="Sim",I80="Sim",J80="Sim",K80=""),"Sim","Não")) -> Não | O80: Sim | Q80: Sim | R80: Sim | S80: Sim | T80: Sim | U80: Sim | V80: Aplicável a quem implanta ou opera sistemas de IA; ação concreta e comprovável. | W80: A0470_NIST2024 Third-Party IP Protection (0,16)
A81: A0467_NIST2024 | B81: Governance Connection | C81: Connect new GAI policies, procedures, and processes to existing model, data, software development, and IT governance and to legal, compliance, and risk management activities. | D81: NIST AI RMF: Generative AI Profile (NIST, 2024) | E81: 1.2 Gestão de riscos | F81: Angelo Andrioli Netho | G81: Sim | H81: Sim | I81: Sim | J81: Sim | L81: =IF(COUNTA(G81:J81)<4,"",IF(AND(G81="Sim",H81="Sim",I81="Sim",J81="Sim",K81=""),"Sim","Não")) -> Sim | O81: Sim | Q81: Sim | R81: Sim | S81: Sim | T81: Sim | U81: Sim | V81: Aplicável a quem implanta ou opera sistemas de IA; ação concreta e comprovável.
A82: A0468_NIST2024 | B82: Training Data Curation | C82: Document training data curation policies, to the extent possible and according to applicable laws and policies. | D82: NIST AI RMF: Generative AI Profile (NIST, 2024) | E82: 3.2 Governança de dados | F82: Angelo Andrioli Netho | G82: Sim | H82: Sim | I82: Sim | J82: Sim | K82: A1022; A0474; | L82: =IF(COUNTA(G82:J82)<4,"",IF(AND(G82="Sim",H82="Sim",I82="Sim",J82="Sim",K82=""),"Sim","Não")) -> Não | O82: Sim | Q82: Sim | R82: Sim | S82: Sim | T82: Sim | U82: Sim | V82: Aplicável a quem implanta ou opera sistemas de IA; ação concreta e comprovável. | W82: A1022_Uuk2024 Data curation (0,32); A0474_NIST2024 Training Data Diligence (0,19)
A83: A0469_NIST2024 | B83: Data Quality Standards | C83: Establish policies for collection, retention, and minimum quality of data, in consideration of the following risks: Disclosure of inappropriate CBRN information; Use of Illegal or dangerous content; Offensive cyber capabilities; Training data imbalances that could give rise to harmful biases; Leak of personally identifiable information, including facial likenesses of individuals. | D83: NIST AI RMF: Generative AI Profile (NIST, 2024) | E83: 3.2 Governança de dados | F83: Angelo Andrioli Netho | G83: Sim | H83: Sim | I83: Sim | J83: Sim | L83: =IF(COUNTA(G83:J83)<4,"",IF(AND(G83="Sim",H83="Sim",I83="Sim",J83="Sim",K83=""),"Sim","Não")) -> Sim | O83: Sim | Q83: Sim | R83: Sim | S83: Sim | T83: Sim | U83: Sim | V83: Aplicável a quem implanta ou opera sistemas de IA; ação concreta e comprovável.
A84: A0470_NIST2024 | B84: Third-Party IP Protection | C84: Implement policies and practices defining how third-party intellectual property and training data will be used, stored, and protected. | D84: NIST AI RMF: Generative AI Profile (NIST, 2024) | E84: 3.2 Governança de dados | F84: Angelo Andrioli Netho | G84: Sim | H84: Sim | I84: Sim | J84: Sim | K84: A0466; A0650; | L84: =IF(COUNTA(G84:J84)<4,"",IF(AND(G84="Sim",H84="Sim",I84="Sim",J84="Sim",K84=""),"Sim","Não")) -> Não | O84: Sim | Q84: Sim | R84: Sim | S84: Sim | T84: Sim | U84: Sim | V84: Aplicável a quem implanta ou opera sistemas de IA; ação concreta e comprovável. | W84: A0466_NIST2024 IP Infringement Response (0,16); A0650_Barrett2024 Third-Party Risk (0,16)
A85: A0471_NIST2024 | B85: Fine-Tuned Model Re-evaluation | C85: Re-evaluate models that were fine-tuned or enhanced on top of third-party models. | D85: NIST AI RMF: Generative AI Profile (NIST, 2024) | E85: 3.1 Testes e auditoria | F85: Angelo Andrioli Netho | G85: Sim | H85: Sim | I85: Sim | J85: Sim | K85: A0511; A0789; | L85: =IF(COUNTA(G85:J85)<4,"",IF(AND(G85="Sim",H85="Sim",I85="Sim",J85="Sim",K85=""),"Sim","Não")) -> Não | O85: Sim | Q85: Sim | R85: Sim | S85: Sim | T85: Sim | U85: Sim | V85: Aplicável a quem implanta ou opera sistemas de IA; ação concreta e comprovável. | W85: A0511_NIST2024 Fine-Tuned Safety Re-evaluation (0,44); A0789_UK Government2023 Model Evaluation of System Security (0,30)
A86: A0472_NIST2024 | B86: Domain Adaptation Risk Assessment | C86: Re-evaluate risks when adapting GAI models to new domains. Additionally, establish warning systems to determine if a GAI system is being used in a new domain where previous assumptions (relating to context of use or mapped risks such as security, and safety) may no longer hold. | D86: NIST AI RMF: Generative AI Profile (NIST, 2024) | E86: 3.5 Monitoramento pós-implantação | F86: Angelo Andrioli Netho | G86: Sim | H86: Sim | I86: Sim | J86: Sim | L86: =IF(COUNTA(G86:J86)<4,"",IF(AND(G86="Sim",H86="Sim",I86="Sim",J86="Sim",K86=""),"Sim","Não")) -> Sim | O86: Sim | Q86: Sim | R86: Sim | S86: Sim | T86: Sim | U86: Sim | V86: Aplicável a quem implanta ou opera sistemas de IA; ação concreta e comprovável.
A87: A0473_NIST2024 | B87: PII Detection Methods | C87: Leverage approaches to detect the presence of PII or sensitive data in generated output text, image, video, or audio. | D87: NIST AI RMF: Generative AI Profile (NIST, 2024) | E87: 2.4 Controles de segurança de conteúdo | F87: Angelo Andrioli Netho | G87: Sim | H87: Sim | I87: Sim | J87: Sim | L87: =IF(COUNTA(G87:J87)<4,"",IF(AND(G87="Sim",H87="Sim",I87="Sim",J87="Sim",K87=""),"Sim","Não")) -> Sim | M87: Incluir | O87: Sim | Q87: Sim | R87: Sim | S87: Sim | T87: Sim | U87: Sim | V87: Aplicável a quem implanta ou opera sistemas de IA; ação concreta e comprovável.
A88: A0474_NIST2024 | B88: Training Data Diligence | C88: Conduct appropriate diligence on training data use to assess intellectual property, and privacy, risks, including to examine whether use of proprietary or sensitive training data is consistent with applicable laws. | D88: NIST AI RMF: Generative AI Profile (NIST, 2024) | E88: 3.2 Governança de dados | F88: Angelo Andrioli Netho | G88: Sim | H88: Sim | I88: Sim | J88: Sim | K88: A0468; A0510; | L88: =IF(COUNTA(G88:J88)<4,"",IF(AND(G88="Sim",H88="Sim",I88="Sim",J88="Sim",K88=""),"Sim","Não")) -> Não | O88: Sim | Q88: Sim | R88: Sim | S88: Sim | T88: Sim | U88: Sim | V88: Aplicável a quem implanta ou opera sistemas de IA; ação concreta e comprovável. | W88: A0468_NIST2024 Training Data Curation (0,19); A0510_NIST2024 Training Data Harm Assessment (0,16)
A89: A0475_NIST2024 | B89: Provenance Testing Practices | C89: Apply TEVV practices for content provenance (e.g., probing a system's synthetic data generation capabilities for potential misuse or vulnerabilities. | D89: NIST AI RMF: Generative AI Profile (NIST, 2024) | E89: 3.1 Testes e auditoria | F89: Angelo Andrioli Netho | G89: Sim | H89: Sim | I89: Sim | J89: Sim | L89: =IF(COUNTA(G89:J89)<4,"",IF(AND(G89="Sim",H89="Sim",I89="Sim",J89="Sim",K89=""),"Sim","Não")) -> Sim | O89: Sim | Q89: Sim | R89: Sim | S89: Sim | T89: Sim | U89: Sim | V89: Aplicável a quem implanta ou opera sistemas de IA; ação concreta e comprovável.
A90: A0476_NIST2024 | B90: Provenance Harm Identification | C90: Identify potential content provenance harms of GAI, such as misinformation or disinformation, deepfakes, including NCII, or tampered content. Enumerate and rank risks based on their likelihood and potential impact, and determine how well provenance solutions address specific risks and/or harms. | D90: NIST AI RMF: Generative AI Profile (NIST, 2024) | E90: 2.4 Controles de segurança de conteúdo | F90: Angelo Andrioli Netho | G90: Sim | H90: Sim | I90: Sim | J90: Sim | L90: =IF(COUNTA(G90:J90)<4,"",IF(AND(G90="Sim",H90="Sim",I90="Sim",J90="Sim",K90=""),"Sim","Não")) -> Sim | O90: Sim | Q90: Sim | R90: Sim | S90: Sim | T90: Sim | U90: Sim | V90: Aplicável a quem implanta ou opera sistemas de IA; ação concreta e comprovável.
A91: A0477_NIST2024 | B91: Use Disclosure Consideration | C91: Consider disclosing use of GAI to end users in relevant contexts, while considering the objective of disclosure, the context of use, the likelihood and magnitude of the risk posed, the audience of the disclosure, as well as the frequency of the disclosures. | D91: NIST AI RMF: Generative AI Profile (NIST, 2024) | E91: 4.6 Direitos e recursos dos usuários | F91: Angelo Andrioli Netho | G91: Sim | H91: Sim | I91: Sim | J91: Sim | L91: =IF(COUNTA(G91:J91)<4,"",IF(AND(G91="Sim",H91="Sim",I91="Sim",J91="Sim",K91=""),"Sim","Não")) -> Sim | O91: Sim | Q91: Sim | R91: Sim | S91: Sim | T91: Sim | U91: Sim | V91: Redigida como consideração ou pergunta; a ação subjacente é concreta e aplicável, mas a descrição precisa ser reescrita como ação.
A92: A0478_NIST2024 | B92: Risk-Based Feedback Prioritization | C92: Prioritize GAI structured public feedback processes based on risk assessment estimates. | D92: NIST AI RMF: Generative AI Profile (NIST, 2024) | E92: 1.2 Gestão de riscos | F92: Angelo Andrioli Netho | G92: Sim | H92: Sim | I92: Sim | J92: Sim | L92: =IF(COUNTA(G92:J92)<4,"",IF(AND(G92="Sim",H92="Sim",I92="Sim",J92="Sim",K92=""),"Sim","Não")) -> Sim | O92: Sim | Q92: Sim | R92: Sim | S92: Sim | T92: Sim | U92: Sim | V92: Aplicável a quem implanta ou opera sistemas de IA; ação concreta e comprovável.
A93: A0479_NIST2024 | B93: Adversarial Role-Playing | C93: Conduct adversarial role-playing exercises, GAI red-teaming, or chaos testing to identify anomalous or unforeseen failure modes. | D93: NIST AI RMF: Generative AI Profile (NIST, 2024) | E93: 3.1 Testes e auditoria | F93: Angelo Andrioli Netho | G93: Sim | H93: Sim | I93: Sim | J93: Sim | L93: =IF(COUNTA(G93:J93)<4,"",IF(AND(G93="Sim",H93="Sim",I93="Sim",J93="Sim",K93=""),"Sim","Não")) -> Sim | O93: Sim | Q93: Sim | R93: Sim | S93: Sim | T93: Sim | U93: Sim | V93: Aplicável a quem implanta ou opera sistemas de IA; ação concreta e comprovável.
A94: A0480_NIST2024 | B94: Threat Profiling | C94: Profile threats and negative impacts arising from GAI systems interacting with, manipulating, or generating content, and outlining known and potential vulnerabilities and the likelihood of their occurrence. | D94: NIST AI RMF: Generative AI Profile (NIST, 2024) | E94: 2.3 Engenharia de segurança do modelo | F94: Angelo Andrioli Netho | G94: Sim | H94: Sim | I94: Sim | J94: Sim | L94: =IF(COUNTA(G94:J94)<4,"",IF(AND(G94="Sim",H94="Sim",I94="Sim",J94="Sim",K94=""),"Sim","Não")) -> Sim | O94: Sim | Q94: Sim | R94: Sim | S94: Sim | T94: Sim | U94: Sim | V94: Aplicável a quem implanta ou opera sistemas de IA; ação concreta e comprovável.
A95: A0481_NIST2024 | B95: Context-Based Impact Measures | C95: Determine context-based measures to identify if new impacts are present due to the GAI system, including regular engagements with downstream AI Actors to identify and quantify new contexts of unanticipated impacts of GAI systems. | D95: NIST AI RMF: Generative AI Profile (NIST, 2024) | E95: 3.5 Monitoramento pós-implantação | F95: Angelo Andrioli Netho | G95: Sim | H95: Sim | I95: Sim | J95: Sim | K95: A0482 | L95: =IF(COUNTA(G95:J95)<4,"",IF(AND(G95="Sim",H95="Sim",I95="Sim",J95="Sim",K95=""),"Sim","Não")) -> Não | O95: Sim | Q95: Sim | R95: Sim | S95: Sim | T95: Sim | U95: Sim | V95: Aplicável a quem implanta ou opera sistemas de IA; ação concreta e comprovável. | W95: A0482_NIST2024 Input Actor Engagement (0,15)
A96: A0482_NIST2024 | B96: Input Actor Engagement | C96: Plan regular engagements with AI Actors responsible for inputs to GAI systems, including third-party data and algorithms, to review and evaluate unanticipated impacts. | D96: NIST AI RMF: Generative AI Profile (NIST, 2024) | E96: 3.5 Monitoramento pós-implantação | F96: Angelo Andrioli Netho | G96: Sim | H96: Sim | I96: Sim | J96: Sim | K96: A0481 | L96: =IF(COUNTA(G96:J96)<4,"",IF(AND(G96="Sim",H96="Sim",I96="Sim",J96="Sim",K96=""),"Sim","Não")) -> Não | O96: Sim | Q96: Sim | R96: Sim | S96: Sim | T96: Sim | U96: Sim | V96: Aplicável a quem implanta ou opera sistemas de IA; ação concreta e comprovável. | W96: A0481_NIST2024 Context-Based Impact Measures (0,15)
A97: A0483_NIST2024 | B97: Origin Tracing Methods | C97: Employ methods to trace the origin and modifications of digital content. | D97: NIST AI RMF: Generative AI Profile (NIST, 2024) | E97: 2.4 Controles de segurança de conteúdo | F97: Angelo Andrioli Netho | G97: Sim | H97: Sim | I97: Sim | J97: Sim | L97: =IF(COUNTA(G97:J97)<4,"",IF(AND(G97="Sim",H97="Sim",I97="Sim",J97="Sim",K97=""),"Sim","Não")) -> Sim | O97: Sim | Q97: Sim | R97: Sim | S97: Sim | T97: Sim | U97: Sim | V97: Aplicável a quem implanta ou opera sistemas de IA; ação concreta e comprovável.
A98: A0484_NIST2024 | B98: Provenance Analysis Tools | C98: Integrate tools designed to analyze content provenance and detect data anomalies, verify the authenticity of digital signatures, and identify patterns associated with misinformation or manipulation. | D98: NIST AI RMF: Generative AI Profile (NIST, 2024) | E98: 2.4 Controles de segurança de conteúdo | F98: Angelo Andrioli Netho | G98: Sim | H98: Sim | I98: Sim | J98: Sim | L98: =IF(COUNTA(G98:J98)<4,"",IF(AND(G98="Sim",H98="Sim",I98="Sim",J98="Sim",K98=""),"Sim","Não")) -> Sim | O98: Sim | Q98: Sim | R98: Sim | S98: Sim | T98: Sim | U98: Sim | V98: Aplicável a quem implanta ou opera sistemas de IA; ação concreta e comprovável.
A99: A0485_NIST2024 | B99: Demographic Metric Disaggregation | C99: Disaggregate evaluation metrics by demographic factors to identify any discrepancies in how content provenance mechanisms work across diverse populations. | D99: NIST AI RMF: Generative AI Profile (NIST, 2024) | E99: 3.1 Testes e auditoria | F99: Angelo Andrioli Netho | G99: Sim | H99: Sim | I99: Sim | J99: Sim | L99: =IF(COUNTA(G99:J99)<4,"",IF(AND(G99="Sim",H99="Sim",I99="Sim",J99="Sim",K99=""),"Sim","Não")) -> Sim | O99: Sim | Q99: Sim | R99: Sim | S99: Sim | T99: Sim | U99: Sim | V99: Aplicável a quem implanta ou opera sistemas de IA; ação concreta e comprovável.
A100: A0486_NIST2024 | B100: Feedback Exercise Metrics | C100: Develop a suite of metrics to evaluate structured public feedback exercises informed by representative AI Actors. | D100: NIST AI RMF: Generative AI Profile (NIST, 2024) | E100: 3.1 Testes e auditoria | F100: Angelo Andrioli Netho | G100: Sim | H100: Sim | I100: Sim | J100: Sim | K100: A0490; A0449; | L100: =IF(COUNTA(G100:J100)<4,"",IF(AND(G100="Sim",H100="Sim",I100="Sim",J100="Sim",K100=""),"Sim","Não")) -> Não | O100: Sim | Q100: Sim | R100: Sim | S100: Sim | T100: Sim | U100: Sim | V100: Aplicável a quem implanta ou opera sistemas de IA; ação concreta e comprovável. | W100: A0490_NIST2024 Feedback Exercise Use Cases (0,23); A0449_NIST2024 Representative Data Verification (0,15)
...

Sheet Catálogo
A1: Nº | B1: Responsável | C1: ID na base | D1: Nome original | E1: Nome em português | F1: Documento de origem | G1: Subcategoria (Saeri) | H1: Descrição em português | I1: Subdomínios: anotador A | J1: Anotador A | K1: Subdomínios: anotador B | L1: Anotador B | M1: Concordância exata | N1: Subdomínios: consenso | O1: Risco-alvo sugerido | P1: Evidência esperada | Q1: Custo sugerido | R1: Evidência da estimativa | S1: Concordância das fontes | T1: Incerteza | U1: Fonte da estimativa | V1: Situação | W1: Observações | X1: Chave do documento | Y1: Código da subcategoria
A2: 1 | B2: Renato Pestana de Gouveia | C2: A0657_Barrett2024 | D2: Elicit Requirements & Assess Impacts | E2: Levantar requisitos e avaliar impactos | F2: AI Risk Management Standards Profile for GPAIS (Barrett et al., 2024) | G2: 1.2 Gestão de riscos | H2: Os requisitos do sistema (por exemplo, “o sistema deve respeitar a privacidade de seus usuários”) são levantados junto aos atores relevantes no contexto de IA e compreendidos por eles. As decisões de projeto levam em consideração as implicações sociotécnicas, visando tratar os riscos associados à IA. | I2: 1.1, 2.1, 6.5, 7.3, 7.4 | J2: Renato Pestana de Gouveia | K2: 1.1, 2.1, 4.1, 6.5, 7.3, 7.4 | L2: Fernando Alonso Piroga da Silva | M2: =IF(OR(I2="",K2=""),"",IF(TRIM(I2)=TRIM(K2),"Sim","Não")) -> Não | N2: 1.1, 2.1, 4.1, 6.5, 7.3, 7.4 | O2: Implementação de IA com decisões de projeto desalinhadas do contexto sociotécnico, gerando violações de direitos e falhas não previstas de governança. | P2: Documento de requisitos sociotécnicos aprovado pelas partes interessadas e matriz de rastreabilidade comprovando a incorporação desses requisitos na arquitetura/projeto do sistema. | Q2: Médio | R2: Média | S2: Alta | T2: =IF(OR(R2="",S2=""),"",CHOOSE(MATCH(R2,Listas!$X$5:$X$7,0)+MATCH(S2,Listas!$Z$5:$Z$7,0)-1,"Alta","Alta","Média","Baixa","Baixa")) -> Baixa | U2: Barrett et al. (2024, p. 33), perfil construído sobre o NIST AI RMF 1.0 (subcategoria MAP 1.6), descreve a ação e lista itens de ação e de documentação do Playbook do NIST, como avaliar impactos ao longo do ciclo de vida com especialistas e comunidades afetadas. De forma independente, a ISO/IEC 42001:2023 exige especificar e documentar os requisitos dos sistemas de IA (controle A.6.2.2) e avaliar e documentar os impactos sobre indivíduos, grupos e a sociedade (cláusulas 6.1.4 e 8.4; controles A.5). Custo estimado pelo grupo, pela rubrica. | V2: Concluída | X2: {=IFERROR(INDEX(Listas!$D$5:$D$17,MATCH(F2,Listas!$C$5:$C$17,0)),"")} -> barrett-2024 | Y2: =IFERROR(LEFT(G2,FIND(" ",G2)-1),"") -> 1.2
A3: 2 | B3: Renato Pestana de Gouveia | C3: A0675_Barrett2024 | D3: Measure & Document Deployment Performance | E3: Medir e documentar o desempenho da implantação | F3: AI Risk Management Standards Profile for GPAIS (Barrett et al., 2024) | G3: 4.1 Documentação do sistema | H3: Os critérios de desempenho ou de garantia de sistemas de IA são medidos de forma qualitativa ou quantitativa e demonstrados para condições semelhantes às do(s) ambiente(s) de implantação. As medições são documentadas. | I3: 6.5, 7.3, 7.4 | J3: Renato Pestana de Gouveia | K3: 4.1, 6.5, 7.3, 7.4 | L3: Fernando Alonso Piroga da Silva | M3: =IF(OR(I3="",K3=""),"",IF(TRIM(I3)=TRIM(K3),"Sim","Não")) -> Não | N3: 4.1, 6.5, 7.3, 7.4 | O3: Implantação de IA sem validação técnica prévia sob condições realistas de produção, resultando em falhas, comportamento impreciso e falta de rastreabilidade do desempenho | P3: Relatórios formais de testes de validação e garantia de qualidade (benchmarks/métricas quantitativas e qualificações qualitativas) documentando o comportamento do sistema em ambiente simulado ou pré-produtivo idêntico ao de implantação, contendo a aprovação da equipe técnica responsável. | Q3: Médio | R3: Média | S3: Alta | T3: =IF(OR(R3="",S3=""),"",CHOOSE(MATCH(R3,Listas!$X$5:$X$7,0)+MATCH(S3,Listas!$Z$5:$Z$7,0)-1,"Alta","Alta","Média","Baixa","Baixa")) -> Baixa | U3: Barrett et al. (2023, p. 46), perfil construído sobre o NIST AI RMF 1.0 (subcategoria MEASURE 2.5: "The AI system to be deployed is demonstrated to be valid and reliable. Limitations of the generalizability beyond the conditions under which the technology was developed are documented"), orienta a medição formal das formas de validade (incluindo validade externa/generalizabilidade), confiabilidade e robustez, além de documentar as limitações operacionais fora da distribuição de treino. De forma complementar e independente, a norma ISO/IEC 42001:2023 exige definir e documentar medidas de verificação e validação do sistema de IA (controle A.6.2.4 e seção B.6.2.4), incluindo critérios de aceitação, avaliação de robustez e tratamento das limitações de desempenho. Custo estimado pelo grupo, pela rubrica. | V3: Concluída | X3: {=IFERROR(INDEX(Listas!$D$5:$D$17,MATCH(F3,Listas!$C$5:$C$17,0)),"")} -> barrett-2024 | Y3: =IFERROR(LEFT(G3,FIND(" ",G3)-1),"") -> 4.1
A4: 3 | B4: Renato Pestana de Gouveia | C4: A0677_Barrett2024 | D4: Demonstrate Validity & Generalization Limits | E4: Demonstrar a validade e os limites de generalização | F4: AI Risk Management Standards Profile for GPAIS (Barrett et al., 2024) | G4: 3.1 Testes e auditoria | H4: O sistema de IA a ser implementado demonstra ser válido e confiável. As limitações quanto à sua generalizabilidade para além das condições em que a tecnologia foi desenvolvida estão documentadas. | I4: 6.5, 7.3, 7.4 | J4: Renato Pestana de Gouveia | K4: 4.1, 6.5, 7.3, 7.4 | L4: Fernando Alonso Piroga da Silva | M4: =IF(OR(I4="",K4=""),"",IF(TRIM(I4)=TRIM(K4),"Sim","Não")) -> Não | N4: 4.1, 6.5, 7.3, 7.4 | O4: Falhas imprevisíveis, alucinações ou perda severa de desempenho e confiabilidade ao operar fora das condições específicas de treinamento/desenvolvimento, resultando em tomada de decisão incorreta em cenários reais decorrente da falta de mapeamento formal dos limites de generalização e validade do modelo. | P4: Relatórios formais de avaliação e documentação de limites operacionais, contendo resultados de testes de validade (construto, interna e externa/generalizabilidade), métricas de robustez e confiabilidade sob diferentes condições de entrada, e especificação clara de casos de uso/domínios não recomendados no System Card ou Model Card. | Q4: Médio | R4: Média | S4: Alta | T4: =IF(OR(R4="",S4=""),"",CHOOSE(MATCH(R4,Listas!$X$5:$X$7,0)+MATCH(S4,Listas!$Z$5:$Z$7,0)-1,"Alta","Alta","Média","Baixa","Baixa")) -> Baixa | U4: Barrett et al. (2023, p. 46), perfil construído sobre o NIST AI RMF 1.0 (subcategoria MEASURE 2.5: "The AI system to be deployed is demonstrated to be valid and reliable. Limitations of the generalizability beyond the conditions under which the technology was developed are documented"), orienta a medição formal das formas de validade (incluindo validade externa/generalizabilidade), confiabilidade e robustez, além de documentar as limitações operacionais fora da distribuição de treino. De forma complementar e independente, a norma ISO/IEC 42001:2023 exige definir e documentar medidas de verificação e validação do sistema de IA (controle A.6.2.4 e seção B.6.2.4), incluindo critérios de aceitação, avaliação de robustez e tratamento das limitações de desempenho. Custo estimado pelo grupo, pela rubrica. | V4: Concluída | X4: {=IFERROR(INDEX(Listas!$D$5:$D$17,MATCH(F4,Listas!$C$5:$C$17,0)),"")} -> barrett-2024 | Y4: =IFERROR(LEFT(G4,FIND(" ",G4)-1),"") -> 3.1
A5: 4 | B5: Renato Pestana de Gouveia | C5: A0698_Barrett2024 | D5: Deactivate Misaligned Systems | E5: Desativar sistemas desalinhados | F5: AI Risk Management Standards Profile for GPAIS (Barrett et al., 2024) | G5: 3.6 Resposta a incidentes e recuperação | H5: Existem mecanismos implementados e em uso, bem como responsabilidades atribuídas e compreendidas, para substituir, desativar ou interromper sistemas de IA que apresentem desempenho ou resultados incompatíveis com o uso pretendido. | I5: 6.5, 7.3 | J5: Renato Pestana de Gouveia | K5: 6.5, 7.3 | L5: Fernando Alonso Piroga da Silva | M5: =IF(OR(I5="",K5=""),"",IF(TRIM(I5)=TRIM(K5),"Sim","Não")) -> Sim | N5: 6.5, 7.3 | O5: Uso continuado ou descontrole de sistemas de IA que apresentem comportamento desalinhado, indesejado ou de alto risco, resultando em falhas operacionais, ampliação de danos socioambientais, violação de diretrizes de governança ou incapacidade de interrupção emergencial (falta de mecanismos de kill switch / desligamento seguro). | P5: Procedimentos operacionais padronizados (SOPs) e protocolos técnicos documentados que estabeleçam limiares de acionamento para bypass, interrupção ou desativação emergencial de modelos (kill switches ou desligamento físico em centros de dados), acompanhados por matriz de responsabilidades e relatórios formais de testes do mecanismo de desativação executados em ambiente controlado. | Q5: Médio | R5: Média | S5: Alta | T5: =IF(OR(R5="",S5=""),"",CHOOSE(MATCH(R5,Listas!$X$5:$X$7,0)+MATCH(S5,Listas!$Z$5:$Z$7,0)-1,"Alta","Alta","Média","Baixa","Baixa")) -> Baixa | U5: Barrett et al. (2023, p. 59), perfil construído sobre o NIST AI RMF 1.0 (subcategoria MANAGE 2.4: "Mechanisms are in place and applied, and responsibilities are assigned and understood, to supersede, disengage, or deactivate AI systems that demonstrate performance or outcomes inconsistent with intended use"), orienta o planejamento de procedimentos de desligamento emergencial (emergency power off / kill switches), liberação gradual (staged-release) e acesso estruturado via API para garantir a capacidade de desativação. De forma independente e complementar, a norma ISO/IEC 42001:2023 prevê controles para tratamento e resposta a incidentes e interrupção operacional de sistemas de IA (cláusula 8.4 e anexos de controle A.8 e B.8). Custo estimado pelo grupo, pela rubrica. | V5: Concluída | X5: {=IFERROR(INDEX(Listas!$D$5:$D$17,MATCH(F5,Listas!$C$5:$C$17,0)),"")} -> barrett-2024 | Y5: =IFERROR(LEFT(G5,FIND(" ",G5)-1),"") -> 3.6
A6: 5 | B6: Renato Pestana de Gouveia | C6: A0699_Barrett2024 | D6: Monitor Third-Party Risks | E6: Monitorar riscos de terceiros | F6: AI Risk Management Standards Profile for GPAIS (Barrett et al., 2024) | G6: 1.2 Gestão de riscos | H6: Os riscos e benefícios da IA ​​provenientes de recursos de terceiros são monitorados regularmente, e controles de risco são aplicados e documentados. | I6: 2.2, 6.5, 7.3, 7.4 | J6: Renato Pestana de Gouveia | K6: 2.2, 6.5, 7.3, 7.4 | L6: Fernando Alonso Piroga da Silva | M6: =IF(OR(I6="",K6=""),"",IF(TRIM(I6)=TRIM(K6),"Sim","Não")) -> Sim | N6: 2.2, 6.5, 7.3, 7.4 | O6: Propagação de falhas, vulnerabilidades de segurança, viés ou violação de direitos oriundos de componentes de terceiros (datasets não curados, software/APIs, modelos pré-treinados ou infraestrutura em nuvem), resultando em contaminação de dados (data poisoning), perda de conformidade legal/IP ou dependência crítica de fornecedores sem controles adequados de governança. | P6: Política formal de gestão de riscos de fornecedores e cadeia de suprimentos de IA, contendo registros de due diligence, relatórios de auditoria/testes de segurança de componentes adquiridos, logs de monitoramento contínuo do desempenho e da confiabilidade das soluções de terceiros, e inventário atualizado de ativos externos com seus respectivos termos contratuais e planos de contingência. | Q6: Médio | R6: Média | S6: Alta | T6: =IF(OR(R6="",S6=""),"",CHOOSE(MATCH(R6,Listas!$X$5:$X$7,0)+MATCH(S6,Listas!$Z$5:$Z$7,0)-1,"Alta","Alta","Média","Baixa","Baixa")) -> Baixa | U6: Barrett et al. (2023, p. 28, 60), perfil construído sobre o NIST AI RMF 1.0 (subcategorias GOVERN 6.1/6.2 e MANAGE 3.1/3.2: "AI risks and benefits from third-party entities are managed"), orienta o monitoramento contínuo, verificação de transparência sobre dados de treino, avaliações contratuais e planos de contingência/desativação para fornecedores de software, dados ou modelos. De forma independente e complementar, a norma ISO/IEC 42001:2023 aborda a gestão de fornecedores e recursos externos de IA no controle A.9.3 (Management of third-party resources) e cláusulas de controle de cadeia de suprimentos. Custo estimado pelo grupo, pela rubrica. | V6: Concluída | X6: {=IFERROR(INDEX(Listas!$D$5:$D$17,MATCH(F6,Listas!$C$5:$C$17,0)),"")} -> barrett-2024 | Y6: =IFERROR(LEFT(G6,FIND(" ",G6)-1),"") -> 1.2
A7: 6 | B7: Renato Pestana de Gouveia | C7: A0701_Barrett2024 | D7: Implement Post-deployment Monitoring Plan | E7: Implementar plano de monitoramento pós-implantação | F7: AI Risk Management Standards Profile for GPAIS (Barrett et al., 2024) | G7: 3.5 Monitoramento pós-implantação | H7: São implementados planos de monitoramento de sistemas de IA após a sua implantação, incluindo mecanismos para a coleta e avaliação de contribuições de usuários e outros atores relevantes no contexto da IA, bem como procedimentos para recursos e reversão de decisões, desativação, resposta a incidentes, recuperação e gestão de mudanças. | I7: 5.2, 6.5, 7.3, 7.4 | J7: Renato Pestana de Gouveia | K7: 5.2, 6.5, 7.3, 7.4 | L7: Fernando Alonso Piroga da Silva | M7: =IF(OR(I7="",K7=""),"",IF(TRIM(I7)=TRIM(K7),"Sim","Não")) -> Sim | N7: 5.2, 6.5, 7.3, 7.4 | O7: Degradação não detectada do desempenho, surgimento de desvios (concept drift / data drift), comportamentos emergentes nocivos ou falhas de segurança pós-implantação, resultando em decisões incorretas do sistema, impactos não mitigados sobre usuários/comunidades afetadas e ausência de resposta tempestiva a incidentes ou canal de contestação. | P7: Plano formal de monitoramento pós-implantação operacionalizado, contendo painéis (dashboards) de métricas contínuas de desempenho/confiabilidade, registros de testes TEVV pós-implantação, histórico de relatórios de incidentes e near-misses integrados a bases de incidentes, bem como fluxos documentados de canais de feedback, contestação e gestão de mudanças (versioning). | Q7: Médio | R7: Média | S7: Alta | T7: =IF(OR(R7="",S7=""),"",CHOOSE(MATCH(R7,Listas!$X$5:$X$7,0)+MATCH(S7,Listas!$Z$5:$Z$7,0)-1,"Alta","Alta","Média","Baixa","Baixa")) -> Baixa | U7: Barrett et al. (2023, p. 61), perfil construído sobre o NIST AI RMF 1.0 (subcategoria MANAGE 4.1: "Post-deployment AI system monitoring plans are implemented, including mechanisms for capturing and evaluating input from users and other relevant AI actors, appeal and override, system decommissioning, incident response, recovery, and change management"), orienta a realização de testes TEVV pós-implantação, rodadas periódicas de red-teaming, canais de feedback/recurso e compartilhamento de informações sobre erros/incidentes. De forma independente e complementar, a norma ISO/IEC 42001:2023 exige o monitoramento contínuo e a avaliação do sistema de IA em produção na cláusula 9.2/9.3 e no controle A.8.4 (AI system monitoring). Custo estimado pelo grupo, pela rubrica. | V7: Concluída | X7: {=IFERROR(INDEX(Listas!$D$5:$D$17,MATCH(F7,Listas!$C$5:$C$17,0)),"")} -> barrett-2024 | Y7: =IFERROR(LEFT(G7,FIND(" ",G7)-1),"") -> 3.5
A8: 7 | B8: Renato Pestana de Gouveia | C8: A0703_Barrett2024 | D8: Report & Respond to Incidents | E8: Relatar e responder a incidentes | F8: AI Risk Management Standards Profile for GPAIS (Barrett et al., 2024) | G8: 4.3 Relato de incidentes | H8: Incidentes e erros são comunicados aos atores de IA pertinentes, incluindo as comunidades afetadas. Processos para o acompanhamento, a resposta e a recuperação diante de incidentes e erros são seguidos e documentados. | I8: 1.1, 3.1, 6.5, 7.4 | J8: Renato Pestana de Gouveia | K8: 3.1, 6.5, 7.4 | L8: Fernando Alonso Piroga da Silva | M8: =IF(OR(I8="",K8=""),"",IF(TRIM(I8)=TRIM(K8),"Sim","Não")) -> Não | N8: 3.1, 6.5, 7.4 | O8: Atraso na identificação, falha na comunicação ou resposta inadequada a erros, violações ou incidentes causados pelo sistema de IA, resultando no agravamento de danos aos afetados, perda de rastreabilidade, descumprimento de obrigações regulatórias de notificação e reincidência de falhas evitáveis. | P8: Plano de resposta e recuperação a incidentes de IA documentado, acompanhado de um banco de dados/registro ativo de incidentes e near-misses (contendo data, severidade, impacto e ações corretivas), relatórios formais de notificação enviados às partes interessadas e comunidades afetadas, e comprovação de submissão a repositórios públicos de incidentes (como o AI Incident Database - AIID). | Q8: Médio | R8: Média | S8: Alta | T8: =IF(OR(R8="",S8=""),"",CHOOSE(MATCH(R8,Listas!$X$5:$X$7,0)+MATCH(S8,Listas!$Z$5:$Z$7,0)-1,"Alta","Alta","Média","Baixa","Baixa")) -> Baixa | U8: Barrett et al. (2023, p. 62), perfil construído sobre o NIST AI RMF 1.0 (subcategoria MANAGE 4.3: "Incidents and errors are communicated to relevant AI actors, including affected communities. Processes for tracking, responding to, and recovering from incidents and errors are followed and documented"), orienta a manutenção de banco de dados de erros/incidentes, procedimentos de notificação contínua e compartilhamento público de dados de falhas. De forma independente e complementar, a norma ISO/IEC 42001:2023 exige a gestão, tratamento e relato de incidentes de sistemas de IA (cláusula 10.1/10.2 e controles de resposta a incidentes A.8.5). Custo estimado pelo grupo, pela rubrica. | V8: Concluída | X8: {=IFERROR(INDEX(Listas!$D$5:$D$17,MATCH(F8,Listas!$C$5:$C$17,0)),"")} -> barrett-2024 | Y8: =IFERROR(LEFT(G8,FIND(" ",G8)-1),"") -> 4.3
A9: 8 | B9: Renato Pestana de Gouveia | C9: A0069_Eisenberg2025 | D9: Establish user rights and recourse framework | E9: Estabelecer direitos dos usuários e um mecanismo de recurso | F9: The Unified Control Framework (Eisenberg et al., 2025) | G9: 4.6 Direitos e recursos dos usuários | H9: Implemente mecanismos abrangentes para o relato por parte dos usuários, coleta de feedback, investigação de incidentes e disponibilização de recursos, incluindo procedimentos claros para que os usuários possam relatar problemas, solicitar explicações ou correções, recorrer de decisões e obter a devida reparação. O sistema deve ser capaz de lidar com diversos tipos de preocupações dos usuários, incluindo erros no sistema, tratamento injusto, violações de privacidade e questões de segurança. | I9: 1.1, 2.1, 2.2, 5.2, 6.5, 7.3, 7.4 | J9: Renato Pestana de Gouveia | K9: 1.1, 2.1, 2.2, 5.2, 6.5, 7.3, 7.4 | L9: Fernando Alonso Piroga da Silva | M9: =IF(OR(I9="",K9=""),"",IF(TRIM(I9)=TRIM(K9),"Sim","Não")) -> Sim | N9: 1.1, 2.1, 2.2, 5.2, 6.5, 7.3, 7.4 | O9: Incapacidade de contestação ou contestação de decisões automatizadas adversas ou de alto impacto impostas aos usuários, culminando na violação de direitos individuais (privacidade, equidade e devido processo), perpetuação de discriminação algorítmica/tratamento injusto e ocorrência de danos morais ou materiais sem mecanismo de recurso (recourse), correção ou reparação adequada. | P9: Mecanismo operacional de direitos e recurso dos usuários documentado e funcional, composto por procedimentos formais de triagem e investigação de incidentes, canal público/acessível para solicitação de explicações e contestação de decisões, protocolo de revisão humana de decisões contestadas e registros de auditoria (logs de solicitações, tempo de resposta e reparações/correções efetuadas). | Q9: Médio | R9: Média | S9: Alta | T9: =IF(OR(R9="",S9=""),"",CHOOSE(MATCH(R9,Listas!$X$5:$X$7,0)+MATCH(S9,Listas!$Z$5:$Z$7,0)-1,"Alta","Alta","Média","Baixa","Baixa")) -> Baixa | U9: Eisenberg et al. (2025, p. 29, 31), no The Unified Control Framework (UCF), define o Control-028 (Establish user rights and recourse framework), exigindo rotinas para coleta de feedback, investigação de incidentes, explicação e contestação de decisões adversas em conformidade com o Colorado AI Act (Seção 6-1-1703.4). De forma independente e complementar, a ISO/IEC 42001:2023 prevê mecanismos de gestão de reclamações de partes interessadas, transparência e avaliação de impactos no controle A.5.4 (Stakeholder feedback and reporting mechanisms). Custo estimado pelo grupo, pela rubrica. | V9: Concluída | X9: {=IFERROR(INDEX(Listas!$D$5:$D$17,MATCH(F9,Listas!$C$5:$C$17,0)),"")} -> eisenberg-2025 | Y9: =IFERROR(LEFT(G9,FIND(" ",G9)-1),"") -> 4.6
A10: 9 | B10: Renato Pestana de Gouveia | C10: A0074_Eisenberg2025 | D10: Establish third-party assessment and management framework | E10: Estabelecer uma estrutura de avaliação e gestão de terceiros | F10: The Unified Control Framework (Eisenberg et al., 2025) | G10: 4.5 Acesso de terceiros ao sistema | H10: Estabeleça procedimentos abrangentes para documentar, avaliar e gerenciar fornecedores e dependências a montante na cadeia de valor de sistemas de IA, incluindo requisitos de transparência, verificação de conformidade, rastreamento de dependências e planejamento de contingência. | I10: 2.2, 6.5, 7.3, 7.4 | J10: Renato Pestana de Gouveia | K10: 2.2, 6.5, 7.3, 7.4 | L10: Fernando Alonso Piroga da Silva | M10: =IF(OR(I10="",K10=""),"",IF(TRIM(I10)=TRIM(K10),"Sim","Não")) -> Sim | N10: 2.2, 6.5, 7.3, 7.4 | O10: Propagação de falhas, vulnerabilidades de segurança, opacidade técnica ou descumprimento regulatório originados de componentes, fornecedores ou modelos a montante (upstream) na cadeia de valor de IA, resultando em dependência não gerenciada de terceiros (vendor lock-in), interrupções operacionais e perda de controle sobre a conformidade e integridade do sistema. | P10: Estrutura formal de avaliação e gestão de riscos de fornecedores/terceiros implementada, contendo relatórios de due diligence e auditoria de fornecedores, inventário atualizado de dependências a montante (software, modelos pré-treinados, APIs e dados), requisitos contratuais de transparência/conformidade documentados e planos de contingência/alternativas operacionais para falhas de terceiros. | Q10: Médio | R10: Média | S10: Alta | T10: =IF(OR(R10="",S10=""),"",CHOOSE(MATCH(R10,Listas!$X$5:$X$7,0)+MATCH(S10,Listas!$Z$5:$Z$7,0)-1,"Alta","Alta","Média","Baixa","Baixa")) -> Baixa | U10: Eisenberg et al. (2025, p. 30), no The Unified Control Framework (UCF), define o Control-033 (Establish third-party assessment and management framework), estabelecendo procedimentos para documentação, avaliação de conformidade, rastreamento de dependências e plano de contingência para fornecedores na cadeia de valor de IA. De forma independente e complementar, a norma ISO/IEC 42001:2023 aborda a gestão de recursos de terceiros e cadeia de suprimentos de IA nos controles A.9.3 (Management of third-party resources) e cláusulas associadas. Custo estimado pelo grupo, pela rubrica. | V10: Concluída | X10: {=IFERROR(INDEX(Listas!$D$5:$D$17,MATCH(F10,Listas!$C$5:$C$17,0)),"")} -> eisenberg-2025 | Y10: =IFERROR(LEFT(G10,FIND(" ",G10)-1),"") -> 4.5
A11: 10 | B11: Renato Pestana de Gouveia | C11: A0080_Eisenberg2025 | D11: Establish data governance and management practices | E11: Estabelecer práticas de governança e gestão de dados | F11: The Unified Control Framework (Eisenberg et al., 2025) | G11: 3.2 Governança de dados | H11: Implementar medidas de governança de dados utilizadas para o treinamento, o que inclui estabelecer uma política de direitos autorais, bem como identificar e documentar as fontes de dados, os possíveis vieses e as medidas de mitigação adotadas. | I11: 1.1, 6.3, 6.5, 7.4 | J11: Renato Pestana de Gouveia | K11: 1.1, 3.1, 4.1, 6.3, 6.5, 7.4 | L11: Fernando Alonso Piroga da Silva | M11: =IF(OR(I11="",K11=""),"",IF(TRIM(I11)=TRIM(K11),"Sim","Não")) -> Não | N11: 1.1, 3.1, 4.1, 6.3, 6.5, 7.4 | O11: Uso de dados de treinamento com problemas de qualidade, vieses não identificados, violação de direitos autorais (copyright) ou proveniência desconhecida, resultando em degradação de desempenho do modelo, saídas discriminatórias, disputas judiciais de propriedade intelectual e não conformidade regulatória. | P11: Estrutura e política de governança de dados para IA documentada, contendo inventário detalhado de fontes e proveniência dos dados de treino (data lineage), política formal de conformidade com direitos autorais/propriedade intelectual, relatórios de avaliação de viés e representatividade na amostragem, e registros de auditoria das técnicas de mitigação e limpeza aplicadas ao conjunto de dados. | Q11: Médio | R11: Média | S11: Alta | T11: =IF(OR(R11="",S11=""),"",CHOOSE(MATCH(R11,Listas!$X$5:$X$7,0)+MATCH(S11,Listas!$Z$5:$Z$7,0)-1,"Alta","Alta","Média","Baixa","Baixa")) -> Baixa | U11: Eisenberg et al. (2025, p. 30), no The Unified Control Framework (UCF), define o Control-039 (Establish data governance and management practices), exigindo medidas formais de governança sobre dados de treinamento, incluindo política de direitos autorais, documentação de fontes, identificação de vieses e mitigação aplicadas. De forma independente e complementar, a norma ISO/IEC 42001:2023 detalha a gestão e qualidade de dados para IA no controle A.6.2 (Data for AI systems) e cláusula 8.3. Custo estimado pelo grupo, pela rubrica. | V11: Concluída | X11: {=IFERROR(INDEX(Listas!$D$5:$D$17,MATCH(F11,Listas!$C$5:$C$17,0)),"")} -> eisenberg-2025 | Y11: =IFERROR(LEFT(G11,FIND(" ",G11)-1),"") -> 3.2
A12: 11 | B12: Hugo Fagundes Faria Santos | C12: A0147_Future of Life Institute2024 | D12: Regular third-party penetration testing | E12: Testes regulares de penetração realizados por terceiros | F12: FLI AI Safety Index 2024 (Future of Life Institute) | G12: 3.1 Testes e auditoria | H12: Realizar periodicamente testes de penetração conduzidos por especialistas externos em segurança cibernética, com o objetivo de identificar vulnerabilidades na infraestrutura utilizada para desenvolver e implantar modelos de inteligência artificial. Esses testes devem abranger a segurança digital e, quando aplicável, a segurança física, permitindo identificar e corrigir falhas antes que sejam exploradas. | I12: 2.1, 2.2, 3.2 , 4.2 , 7.3 | J12: Hugo Fagundes Faria Santos | K12: 2.1, 2.2, 5.1, 6.5, 7.2, 7.3 | L12: Angelo Andrioli Netho | M12: =IF(OR(I12="",K12=""),"",IF(TRIM(I12)=TRIM(K12),"Sim","Não")) -> Não | N12: 2.1, 2.2, 3.2, 4.2, 5.1, 7.2, 7.3 | O12: Exploração de vulnerabilidades de segurança na infraestrutura de desenvolvimento e implantação de sistemas de IA, permitindo acessos não autorizados, vazamento de dados ou comprometimento do sistema. | P12: Relatórios de testes de penetração realizados por terceiros, contendo vulnerabilidades identificadas, nível de criticidade, recomendações e registros das correções implementadas. | Q12: Alto | R12: Limitada | S12: Alta | T12: =IF(OR(R12="",S12=""),"",CHOOSE(MATCH(R12,Listas!$X$5:$X$7,0)+MATCH(S12,Listas!$Z$5:$Z$7,0)-1,"Alta","Alta","Média","Baixa","Baixa")) -> Média | U12: Future of Life Institute (2024) Recomendação de testes independentes de segurança para identificar vulnerabilidades em sistemas de IA. | V12: Concluída | X12: {=IFERROR(INDEX(Listas!$D$5:$D$17,MATCH(F12,Listas!$C$5:$C$17,0)),"")} -> fli-2024 | Y12: =IFERROR(LEFT(G12,FIND(" ",G12)-1),"") -> 3.1
A13: 12 | B13: Hugo Fagundes Faria Santos | C13: A0942_Gipiškis2024 | D13: Scope red-teaming activities based on deploy- ment context | E13: Adequação das atividades de Red Teaming ao contexto de implantação | F13: Risk Sources and Risk Management Measures (Gipiškis et al., 2024) | G13: 3.1 Testes e auditoria | H13: Adaptar as atividades de Red Teaming de acordo com o contexto de implantação do sistema de inteligência artificial, considerando sua finalidade, os riscos envolvidos e o ambiente operacional. A avaliação deve considerar a diversidade de usuários, os possíveis casos de uso, a sensibilidade do domínio de aplicação, a escala de implantação e as vulnerabilidades conhecidas do modelo ou de sistemas semelhantes. | I13: 2.1, 5.2, 6.5, 7.4 | J13: Hugo Fagundes Faria Santos | K13: 3.1, 3.2, 5.1, 6.5, 7.2, 7.3, 7.4 | L13: Angelo Andrioli Netho | M13: =IF(OR(I13="",K13=""),"",IF(TRIM(I13)=TRIM(K13),"Sim","Não")) -> Não | N13: 2.1 ,3.1 ,3.2 ,5.1 ,6.5 ,7.2 ,7.3 ,7.4 | O13: Falhas de segurança e comportamentos prejudiciais não identificados devido à realização de testes que não consideram o contexto real de utilização do sistema de IA. | P13: Plano de Red Teaming contextualizado, cenários de ataque testados, relatórios de vulnerabilidades encontradas e registros das medidas corretivas adotadas. | Q13: Alto | R13: Limitada | S13: Alta | T13: =IF(OR(R13="",S13=""),"",CHOOSE(MATCH(R13,Listas!$X$5:$X$7,0)+MATCH(S13,Listas!$Z$5:$Z$7,0)-1,"Alta","Alta","Média","Baixa","Baixa")) -> Média | U13: Gipiškis (2024) Orientações sobre a adaptação de testes adversariais ao contexto de utilização e aos riscos do sistema. | V13: Concluída | X13: {=IFERROR(INDEX(Listas!$D$5:$D$17,MATCH(F13,Listas!$C$5:$C$17,0)),"")} -> gipiskis-2024 | Y13: =IFERROR(LEFT(G13,FIND(" ",G13)-1),"") -> 3.1
... A21: 20 | B21: Hugo Fagundes Faria Santos | C21: A0987_Gipiškis2024 | D21: Sandboxing of AI Systems | E21: Desenvolvimento e testes de sistemas de IA em ambientes isolados | F21: Risk Sources and Risk Management Measures (Gipiškis et al., 2024) | G21: 3.1 Testes e auditoria | H21: Desenvolver e testar sistemas de inteligência artificial em ambientes isolados e controlados, conhecidos como Sandbox, para limitar a interação com recursos externos e impedir que comportamentos potencialmente perigosos afetem outros sistemas. Nesse ambiente, o acesso à rede, ao armazenamento, à memória e a outros recursos pode ser bloqueado ou restringido. Essa abordagem permite avaliar o comportamento da IA de forma mais segura, reduzindo os riscos associados à execução de ações ou à geração de resultados prejudiciais durante os testes. | I21: 2.1, 2.2, 4.2, 7.3 | J21: Hugo Fagundes Faria Santos | K21: 2.1, 2.2, 4.2, 7.3 | L21: Angelo Andrioli Netho | M21: =IF(OR(I21="",K21=""),"",IF(TRIM(I21)=TRIM(K21),"Sim","Não")) -> Sim | N21: 2.1, 2.2, 4.2, 7.3 | O21: Comprometimento de sistemas externos, exposição de informações sensíveis ou execução de ações perigosas durante o desenvolvimento e os testes de sistemas de IA. | P21: Documentação da configuração do ambiente Sandbox, políticas de isolamento, registros de restrições de rede e recursos, relatórios de testes de segurança e evidências da eficácia do isolamento. | Q21: Alto | R21: Limitada | S21: Alta | T21: =IF(OR(R21="",S21=""),"",CHOOSE(MATCH(R21,Listas!$X$5:$X$7,0)+MATCH(S21,Listas!$Z$5:$Z$7,0)-1,"Alta","Alta","Média","Baixa","Baixa")) -> Média | U21: Gipiškis (2024) Recomendação de isolamento de ambientes para limitar impactos de comportamentos perigosos. | V21: Concluída | X21: {=IFERROR(INDEX(Listas!$D$5:$D$17,MATCH(F21,Listas!$C$5:$C$17,0)),"")} -> gipiskis-2024 | Y21: =IFERROR(LEFT(G21,FIND(" ",G21)-1),"") -> 3.1
A22: 21 | B22: Angelo Andrioli Netho | C22: A0397_NIST2024 | D22: Development Halt Plan | E22: Planejar a interrupção de sistemas com risco inaceitável | F22: NIST AI RMF: Generative AI Profile (NIST, 2024) | G22: 1.5 Estruturas de decisão de segurança | H22: Elaborar um plano para interromper o desenvolvimento ou a implantação de um sistema de IA generativa que apresente risco negativo inaceitável. | I22: 7.1, 7.2 | J22: Angelo Andrioli Netho | K22: 6.5, 7.3 | L22: Renato Pestana de Gouveia | M22: =IF(OR(I22="",K22=""),"",IF(TRIM(I22)=TRIM(K22),"Sim","Não")) -> Não | N22: 6.5, 7.3 | O22: Sistema de IA que continua em operação mesmo depois de apresentar riscos acima da tolerância da organização, por falta de critérios e de um procedimento definido para interrompê-lo, ampliando os danos antes da contenção. | P22: Plano de interrupção formalmente aprovado pela direção, contendo critérios de acionamento ligados à tolerância a riscos, responsáveis nomeados, etapas de interrupção e de comunicação, e registro de ao menos um teste ou simulação do plano. | Q22: Médio | R22: Média | S22: Alta | T22: =IF(OR(R22="",S22=""),"",CHOOSE(MATCH(R22,Listas!$X$5:$X$7,0)+MATCH(S22,Listas!$Z$5:$Z$7,0)-1,"Alta","Alta","Média","Baixa","Baixa")) -> Baixa | U22: NIST AI 600-1 (2024), ação GV-1.3-007, ligada à subcategoria GOVERN 1.3 do NIST AI RMF 1.0 ("Processes, procedures, and practices are in place to determine the needed level of risk management activities based on the organization’s risk tolerance"), recomenda planejar a interrupção do desenvolvimento ou da implantação de sistemas com risco negativo inaceitável. O NIST AI RMF 1.0 reforça a ação em MANAGE 2.4 ("Mechanisms are in place and applied, and responsibilities are assigned and understood, to supersede, disengage, or deactivate AI systems that demonstrate performance or outcomes inconsistent with intended use") e em GOVERN 1.7 (desativação segura de sistemas). De forma independente, a ISO/IEC 42001:2023 prevê supervisão humana com autoridade para anular decisões do sistema (B.9.3) e processos de resposta a falhas durante a operação (B.6.2.6). Custo estimado pelo grupo, pela rubrica. | V22: Concluída | W22: A0406 (protocolo de desativação) descreve ação muito parecida. | X22: {=IFERROR(INDEX(Listas!$D$5:$D$17,MATCH(F22,Listas!$C$5:$C$17,0)),"")} -> nist-2024 | Y22: =IFERROR(LEFT(G22,FIND(" ",G22)-1),"") -> 1.5
A23: 22 | B23: Angelo Andrioli Netho | C23: A0398_NIST2024 | D23: Harmful Content Prevention | E23: Prevenir a geração de conteúdo ilegal e abusivo | F23: NIST AI RMF: Generative AI Profile (NIST, 2024) | G23: 2.4 Controles de segurança de conteúdo | H23: Estabelecer políticas e mecanismos que impeçam o sistema de IA generativa de gerar material de abuso sexual infantil (CSAM), imagens íntimas não consentidas (NCII) ou outros conteúdos que violem a lei. | I23: 7.1, 7.2 | J23: Angelo Andrioli Netho | K23: 1.2, 2.1, 6.5, 7.2, 7.3 | L23: Renato Pestana de Gouveia | M23: =IF(OR(I23="",K23=""),"",IF(TRIM(I23)=TRIM(K23),"Sim","Não")) -> Não | N23: 1.2, 2.1, 6.5, 7.2, 7.3 | O23: Geração de conteúdo ilegal ou abusivo pelo sistema (CSAM, imagens íntimas não consentidas, conteúdo violento ou de ódio), com dano direto às pessoas retratadas e responsabilização legal e reputacional da organização. | P23: Política de conteúdo aprovada e publicada; filtros ou classificadores ativos na entrada e na saída do sistema; registros de bloqueio; e relatório de testes periódicos com pedidos proibidos, mostrando a taxa de bloqueio obtida. | Q23: Médio | R23: Média | S23: Média | T23: =IF(OR(R23="",S23=""),"",CHOOSE(MATCH(R23,Listas!$X$5:$X$7,0)+MATCH(S23,Listas!$Z$5:$Z$7,0)-1,"Alta","Alta","Média","Baixa","Baixa")) -> Média | U23: NIST AI 600-1 (2024), ação GV-1.4-001, ligada à subcategoria GOVERN 1.4 do NIST AI RMF 1.0 ("The risk management process and its outcomes are established through transparent policies, procedures, and other controls based on organizational risk priorities"), recomenda políticas e mecanismos para impedir a geração de CSAM, NCII e conteúdo ilegal, associando a ação aos riscos de conteúdo obsceno, degradante ou abusivo e de conteúdo perigoso, violento ou de ódio. O NIST AI RMF 1.0 também exige a avaliação regular dos riscos de segurança (MEASURE 2.6). A ISO/IEC 42001:2023 trata o tema apenas de forma indireta, pela política de IA (A.2.2) e pelo uso conforme o uso pretendido (A.9.4), sem mencionar conteúdo nocivo; por isso a concordância foi considerada média. Custo estimado pelo grupo, pela rubrica. | V23: Concluída | X23: {=IFERROR(INDEX(Listas!$D$5:$D$17,MATCH(F23,Listas!$C$5:$C$17,0)),"")} -> nist-2024 | Y23: =IFERROR(LEFT(G23,FIND(" ",G23)-1),"") -> 2.4
A24: 23 | B24: Angelo Andrioli Netho | C24: A0433_NIST2024 | D24: Third-Party Entity Inventory | E24: Inventariar terceiros com acesso a conteúdo | F24: NIST AI RMF: Generative AI Profile (NIST, 2024) | G24: 3.3 Gestão de acesso | H24: Inventariar todas as entidades terceiras com acesso ao conteúdo da organização e estabelecer listas de tecnologias e fornecedores de IA generativa aprovados. | I24: 2.1, 6.5 | J24: Angelo Andrioli Netho | K24: 2.1, 6.5 | L24: Renato Pestana de Gouveia | M24: =IF(OR(I24="",K24=""),"",IF(TRIM(I24)=TRIM(K24),"Sim","Não")) -> Sim | N24: 2.1, 6.5 | O24: Exposição de dados e conteúdo da organização a terceiros não controlados e uso de ferramentas ou serviços de IA não avaliados, gerando vazamentos, violações contratuais e riscos de segurança na cadeia de fornecimento. | P24: Inventário atualizado de terceiros, com o tipo de acesso e o conteúdo envolvido em cada caso; lista de tecnologias e fornecedores de IA aprovados, com responsável, critérios de aprovação e data da última revisão. | Q24: Médio | R24: Média | S24: Alta | T24: =IF(OR(R24="",S24=""),"",CHOOSE(MATCH(R24,Listas!$X$5:$X$7,0)+MATCH(S24,Listas!$Z$5:$Z$7,0)-1,"Alta","Alta","Média","Baixa","Baixa")) -> Baixa | U24: NIST AI 600-1 (2024), ação GV-6.1-007, ligada à subcategoria GOVERN 6.1 do NIST AI RMF 1.0 ("Policies and procedures are in place that address AI risks associated with third-party entities, including risks of infringement of a third-party’s intellectual property or other rights"), recomenda inventariar os terceiros com acesso ao conteúdo e manter listas de fornecedores aprovados; o AI RMF complementa com o mapeamento de riscos de componentes de terceiros (MAP 4.1). De forma independente, a ISO/IEC 42001:2023 exige documentar todas as partes envolvidas no ciclo de vida do sistema e seus papéis (A.10.2 e B.10.2) e estabelecer um processo para que o uso de fornecedores se alinhe à abordagem responsável da organização (A.10.3). Custo estimado pelo grupo, pela rubrica. | V24: Concluída | X24: {=IFERROR(INDEX(Listas!$D$5:$D$17,MATCH(F24,Listas!$C$5:$C$17,0)),"")} -> nist-2024 | Y24: =IFERROR(LEFT(G24,FIND(" ",G24)-1),"") -> 3.3
A25: 24 | B25: Angelo Andrioli Netho | C25: A0473_NIST2024 | D25: PII Detection Methods | E25: Detectar dados pessoais nas saídas | F25: NIST AI RMF: Generative AI Profile (NIST, 2024) | G25: 2.4 Controles de segurança de conteúdo | H25: Aplicar métodos para detectar a presença de dados pessoais (PII) ou dados sensíveis nas saídas geradas em texto, imagem, vídeo ou áudio. | I25: 2.1, 7.4 | J25: Angelo Andrioli Netho | K25: 2.1, 7.4 | L25: Renato Pestana de Gouveia | M25: =IF(OR(I25="",K25=""),"",IF(TRIM(I25)=TRIM(K25),"Sim","Não")) -> Sim | N25: 2.1, 7.4 | O25: Vazamento de dados pessoais ou sensíveis nas respostas do sistema, vindos de dados memorizados no treinamento, de documentos consultados ou das próprias entradas dos usuários, com violação de privacidade e da legislação de proteção de dados. | P25: Detector de dados pessoais integrado ao fluxo de saída do sistema; registros das detecções e das ações tomadas (bloqueio ou mascaramento); e relatório de teste com casos conhecidos, informando as taxas de acerto e de falha. | Q25: Médio | R25: Média | S25: Média | T25: =IF(OR(R25="",S25=""),"",CHOOSE(MATCH(R25,Listas!$X$5:$X$7,0)+MATCH(S25,Listas!$Z$5:$Z$7,0)-1,"Alta","Alta","Média","Baixa","Baixa")) -> Média | U25: NIST AI 600-1 (2024), ação MP-4.1-009, ligada à subcategoria MAP 4.1 do NIST AI RMF 1.0, recomenda detectar dados pessoais ou sensíveis nas saídas em texto, imagem, vídeo ou áudio, associando a ação ao risco de privacidade de dados. O NIST AI RMF 1.0 exige examinar e documentar o risco de privacidade do sistema (MEASURE 2.10: "Privacy risk of the AI system – as identified in the MAP function – is examined and documented"). A ISO/IEC 42001:2023 trata a privacidade como objetivo organizacional (C.2.7) e remete à ISO/IEC 27701 para o tratamento de dados pessoais (B.10.2), mas não descreve a detecção nas saídas; por isso a concordância foi considerada média. Custo estimado pelo grupo, pela rubrica. | V25: Concluída | X25: {=IFERROR(INDEX(Listas!$D$5:$D$17,MATCH(F25,Listas!$C$5:$C$17,0)),"")} -> nist-2024 | Y25: =IFERROR(LEFT(G25,FIND(" ",G25)-1),"") -> 2.4
A26: 25 | B26: Angelo Andrioli Netho | C26: A0505_NIST2024 | D26: Source and Citation Review | E26: Verificar fontes e citações nas saídas | F26: NIST AI RMF: Generative AI Profile (NIST, 2024) | G26: 3.5 Monitoramento pós-implantação | H26: Revisar e verificar as fontes e citações presentes nas saídas do sistema, durante a medição de riscos antes da implantação e no monitoramento contínuo. | I26: 3.2, 4.1, 7.3 | J26: Angelo Andrioli Netho | K26: 3.2, 4.1, 7.3 | L26: Renato Pestana de Gouveia | M26: =IF(OR(I26="",K26=""),"",IF(TRIM(I26)=TRIM(K26),"Sim","Não")) -> Sim | N26: 3.2, 4.1, 7.3 | O26: Confabulação: respostas com fontes inventadas ou com citações que não sustentam o que foi afirmado, levando os usuários a confiar em informação falsa e a tomar decisões com base nela. | P26: Procedimento de verificação documentado; registros de revisão de amostras de saídas antes da implantação e periodicamente em produção, com a taxa de citações inválidas e as correções feitas. | Q26: Médio | R26: Média | S26: Média | T26: =IF(OR(R26="",S26=""),"",CHOOSE(MATCH(R26,Listas!$X$5:$X$7,0)+MATCH(S26,Listas!$Z$5:$Z$7,0)-1,"Alta","Alta","Média","Baixa","Baixa")) -> Média | U26: NIST AI 600-1 (2024), ação MS-2.5-003, ligada à subcategoria MEASURE 2.5 do NIST AI RMF 1.0 ("The AI system to be deployed is demonstrated to be valid and reliable. Limitations of the generalizability beyond the conditions under which the technology was developed are documented"), recomenda revisar e verificar fontes e citações nas saídas, associando a ação ao risco de confabulação. A ISO/IEC 42001:2023 prevê, de forma mais geral, revisores humanos que conferem as saídas e o monitoramento da acurácia (B.9.3), sem tratar especificamente de citações; por isso a concordância foi considerada média. Custo estimado pelo grupo, pela rubrica. | V26: Concluída | X26: {=IFERROR(INDEX(Listas!$D$5:$D$17,MATCH(F26,Listas!$C$5:$C$17,0)),"")} -> nist-2024 | Y26: =IFERROR(LEFT(G26,FIND(" ",G26)-1),"") -> 3.5
A27: 26 | B27: Angelo Andrioli Netho | C27: A0506_NIST2024 | D27: Anthropomorphization Tracking | E27: Registrar antropomorfização na interface | F27: NIST AI RMF: Generative AI Profile (NIST, 2024) | G27: 3.5 Monitoramento pós-implantação | H27: Acompanhar e documentar ocorrências de antropomorfização (como imagens humanas, menções a sentimentos humanos ou motivos de ciborgue) nas interfaces do sistema. | I27: 5.1 | J27: Angelo Andrioli Netho | K27: 5.1, 6.5 | L27: Renato Pestana de Gouveia | M27: =IF(OR(I27="",K27=""),"",IF(TRIM(I27)=TRIM(K27),"Sim","Não")) -> Não | N27: 5.1, 6.5 | O27: Usuários que atribuem qualidades humanas ao sistema e passam a confiar demais nele ou a desenvolver dependência emocional, prejudicando o julgamento sobre as respostas recebidas. | P27: Registro datado das ocorrências de antropomorfização encontradas na interface e nas respostas do sistema, com a decisão tomada sobre cada uma (manter, ajustar ou remover). | Q27: Baixo | R27: Limitada | S27: Média | T27: =IF(OR(R27="",S27=""),"",CHOOSE(MATCH(R27,Listas!$X$5:$X$7,0)+MATCH(S27,Listas!$Z$5:$Z$7,0)-1,"Alta","Alta","Média","Baixa","Baixa")) -> Alta | U27: NIST AI 600-1 (2024), ação MS-2.5-004, ligada à subcategoria MEASURE 2.5 do NIST AI RMF 1.0, recomenda acompanhar e documentar ocorrências de antropomorfização nas interfaces, associando a ação ao risco de configuração humano-IA. A ISO/IEC 42001:2023 só toca o tema de forma indireta, ao exigir que os usuários saibam que estão interagindo com um sistema de IA (B.8.2). Como a ação tem uma única fonte direta, a evidência foi considerada limitada. Custo estimado pelo grupo, pela rubrica. | V27: Concluída | W27: Fonte direta só no NIST; respaldo indireto na ISO. | X27: {=IFERROR(INDEX(Listas!$D$5:$D$17,MATCH(F27,Listas!$C$5:$C$17,0)),"")} -> nist-2024 | Y27: =IFERROR(LEFT(G27,FIND(" ",G27)-1),"") -> 3.5
A28: 27 | B28: Angelo Andrioli Netho | C28: A0514_NIST2024 | D28: Inappropriate Query Handling | E28: Verificar o tratamento de pedidos maliciosos | F28: NIST AI RMF: Generative AI Profile (NIST, 2024) | G28: 2.3 Engenharia de segurança do modelo | H28: Verificar se o sistema trata adequadamente pedidos que possam levar a uso inadequado, malicioso ou ilegal, como manipulação, extorsão, falsificação de identidade direcionada, ciberataques e criação de armas. | I28: 1.2, 4.2, 4.3, 7.5, 7.6 | J28: Angelo Andrioli Netho | K28: 1.2, 4.2, 4.3, 7.5, 7.6 | L28: Renato Pestana de Gouveia | M28: =IF(OR(I28="",K28=""),"",IF(TRIM(I28)=TRIM(K28),"Sim","Não")) -> Sim | N28: 1.2, 4.2, 4.3, 7.5, 7.6 | O28: Uso do sistema por agentes mal-intencionados para manipular ou extorquir pessoas, se passar por terceiros, apoiar ciberataques ou obter informações perigosas. | P28: Conjunto documentado de testes com pedidos maliciosos por categoria; relatório com a taxa de recusa ou de tratamento correto em cada categoria; e registro das falhas encontradas e das correções aplicadas. | Q28: Médio | R28: Média | S28: Média | T28: =IF(OR(R28="",S28=""),"",CHOOSE(MATCH(R28,Listas!$X$5:$X$7,0)+MATCH(S28,Listas!$Z$5:$Z$7,0)-1,"Alta","Alta","Média","Baixa","Baixa")) -> Média | U28: NIST AI 600-1 (2024), ação MS-2.6-006, ligada à subcategoria MEASURE 2.6 do NIST AI RMF 1.0 ("The AI system is evaluated regularly for safety risks – as identified in the MAP function"), recomenda verificar se o sistema trata adequadamente pedidos que possam levar a uso inadequado, malicioso ou ilegal. De forma independente, a ISO/IEC 42001:2023 orienta analisar como agentes podem usar o sistema de forma indevida (B.5.5) e identificar ameaças de segurança específicas de IA durante a operação (B.6.2.6), mas não descreve testes com pedidos maliciosos; por isso a concordância foi considerada média. Custo estimado pelo grupo, pela rubrica. | V28: Concluída | X28: {=IFERROR(INDEX(Listas!$D$5:$D$17,MATCH(F28,Listas!$C$5:$C$17,0)),"")} -> nist-2024 | Y28: =IFERROR(LEFT(G28,FIND(" ",G28)-1),"") -> 2.3
A29: 28 | B29: Angelo Andrioli Netho | C29: A0528_NIST2024 | D29: User Instruction Adequacy | E29: Testar a adequação das instruções de uso | F29: NIST AI RMF: Generative AI Profile (NIST, 2024) | G29: 3.6 Resposta a incidentes e recuperação | H29: Verificar, por meio de testes com usuários, se as instruções de uso do sistema são adequadas. | I29: 7.3 | J29: Angelo Andrioli Netho | K29: 7.3, 7.4 | L29: Renato Pestana de Gouveia | M29: =IF(OR(I29="",K29=""),"",IF(TRIM(I29)=TRIM(K29),"Sim","Não")) -> Não | N29: 7.3, 7.4 | O29: Uso incorreto ou inseguro do sistema porque os usuários não entendem como operá-lo, quais são suas limitações e quando não confiar nas respostas. | P29: Relatório de teste com usuários representativos, informando participantes, tarefas, problemas de compreensão encontrados e as mudanças feitas nas instruções a partir dos resultados. | Q29: Médio | R29: Média | S29: Alta | T29: =IF(OR(R29="",S29=""),"",CHOOSE(MATCH(R29,Listas!$X$5:$X$7,0)+MATCH(S29,Listas!$Z$5:$Z$7,0)-1,"Alta","Alta","Média","Baixa","Baixa")) -> Baixa | U29: NIST AI 600-1 (2024), ação MS-2.8-004, ligada à subcategoria MEASURE 2.8 do NIST AI RMF 1.0 ("Risks associated with transparency and accountability – as identified in the MAP function – are examined and documented"), recomenda verificar a adequação das instruções de uso por meio de testes com usuários. De forma independente, a ISO/IEC 42001:2023 exige fornecer aos usuários as informações necessárias e validar que elas são completas, atualizadas e corretas (A.8.2 e B.8.2), e inclui testes com usuários entre os critérios de liberação para implantação (B.6.2.5). Custo estimado pelo grupo, pela rubrica. | V29: Concluída | X29: {=IFERROR(INDEX(Listas!$D$5:$D$17,MATCH(F29,Listas!$C$5:$C$17,0)),"")} -> nist-2024 | Y29: =IFERROR(LEFT(G29,FIND(" ",G29)-1),"") -> 3.6
A30: 29 | B30: Angelo Andrioli Netho | C30: A0534_NIST2024 | D30: Bias Benchmark Application | E30: Aplicar benchmarks de viés | F30: NIST AI RMF: Generative AI Profile (NIST, 2024) | G30: 3.1 Testes e auditoria | H30: Aplicar benchmarks adequados ao caso de uso (como Bias Benchmark Questions, Real Hateful or Harmful Prompts e Winogender Schemas) para quantificar viés sistêmico, estereótipos, difamação e conteúdo de ódio nas saídas, documentando as premissas e limitações dos benchmarks, inclusive possível contaminação entre dados de treino e de teste. | I30: 1.1, 4.1, 7.1, 7.3 | J30: Angelo Andrioli Netho | K30: 1.1, 4.1, 7.1, 7.3 | L30: Renato Pestana de Gouveia | M30: =IF(OR(I30="",K30=""),"",IF(TRIM(I30)=TRIM(K30),"Sim","Não")) -> Sim | N30: 1.1, 4.1, 7.1, 7.3 | O30: Saídas que reproduzem estereótipos, difamam ou discriminam grupos sociais, causando dano às pessoas afetadas e à reputação da organização. | P30: Relatório com os resultados dos benchmarks aplicados, desagregados por grupo, e a documentação das premissas, limitações e possível contaminação de cada benchmark em relação ao contexto de uso. | Q30: Médio | R30: Média | S30: Alta | T30: =IF(OR(R30="",S30=""),"",CHOOSE(MATCH(R30,Listas!$X$5:$X$7,0)+MATCH(S30,Listas!$Z$5:$Z$7,0)-1,"Alta","Alta","Média","Baixa","Baixa")) -> Baixa | U30: NIST AI 600-1 (2024), ação MS-2.11-001, ligada à subcategoria MEASURE 2.11 do NIST AI RMF 1.0 ("Fairness and bias – as identified in the MAP function – are evaluated and results are documented"), recomenda aplicar benchmarks adequados ao caso de uso para quantificar viés, estereótipos e conteúdo de ódio, documentando suas limitações. De forma independente, a ISO/IEC 42001:2023 exige definir medidas de verificação e validação com critérios de avaliação (A.6.2.4), tratar vieses nos dados (B.7.4) e considerar a equidade como objetivo (C.2.5). Custo estimado pelo grupo, pela rubrica. | V30: Concluída | X30: {=IFERROR(INDEX(Listas!$D$5:$D$17,MATCH(F30,Listas!$C$5:$C$17,0)),"")} -> nist-2024 | Y30: =IFERROR(LEFT(G30,FIND(" ",G30)-1),"") -> 3.1
A31: 30 | B31: Angelo Andrioli Netho | C31: A0712_NIST2024 | D31: Environmental Degradation Minimisation | E31: Documentar os impactos ambientais previstos | F31: NIST AI RMF: Generative AI Profile (NIST, 2024) | G31: 1.6 Gestão de impacto ambiental | H31: Documentar os impactos ambientais previstos do desenvolvimento, da manutenção e da implantação do modelo nas decisões de projeto do produto. | I31: 6.6 | J31: Angelo Andrioli Netho | K31: 6.5, 6.6 | L31: Renato Pestana de Gouveia | M31: =IF(OR(I31="",K31=""),"",IF(TRIM(I31)=TRIM(K31),"Sim","Não")) -> Não | N31: 6.5, 6.6 | O31: Consumo de energia e água e emissões de gases de efeito estufa não considerados nas decisões de projeto, gerando impacto ambiental evitável. | P31: Estimativa documentada do consumo de energia ou das emissões associadas ao sistema, registrada junto às decisões de projeto (por exemplo, na escolha do modelo, do tamanho do modelo ou da infraestrutura). | Q31: Médio | R31: Média | S31: Alta | T31: =IF(OR(R31="",S31=""),"",CHOOSE(MATCH(R31,Listas!$X$5:$X$7,0)+MATCH(S31,Listas!$Z$5:$Z$7,0)-1,"Alta","Alta","Média","Baixa","Baixa")) -> Baixa | U31: NIST AI 600-1 (2024), na subcategoria MEASURE 2.12 do NIST AI RMF 1.0 ("Environmental impact and sustainability of AI model training and management activities – as identified in the MAP function – are assessed and documented"), recomenda documentar os impactos ambientais previstos nas decisões de projeto. De forma independente, a ISO/IEC 42001:2023 inclui a sustentabilidade ambiental entre os impactos sociais a avaliar (A.5.5 e B.5.5), pede documentar o impacto ambiental do hardware utilizado (B.4.5) e lista o impacto ambiental entre os objetivos organizacionais (C.2.4). Custo estimado pelo grupo, pela rubrica. | V31: Concluída | X31: {=IFERROR(INDEX(Listas!$D$5:$D$17,MATCH(F31,Listas!$C$5:$C$17,0)),"")} -> nist-2024 | Y31: =IFERROR(LEFT(G31,FIND(" ",G31)-1),"") -> 1.6
A32: 31 | B32: Fernando Alonso Piroga da Silva | C32: A0764_UK Government2023 | D32: Rigorous Risk Assessment Processes | E32: Processos rigorosos de avaliação de riscos | F32: Emerging Processes for Frontier AI Safety (DSIT UK, 2023) | G32: 1.2 Gestão de riscos | H32: Desenvolver processos rigorosos de avaliação de risco para modelos, que: 1) Busquem abranger todos os riscos plausíveis e com consequências relevantes decorrentes de sistemas de IA, incluindo riscos de baixa probabilidade, mas que possam causar danos graves; 2) Sejam fundamentados em fatores que incluem, entre outros: avaliações de modelos e testes de estresse (*red teaming*), evidências sobre os impactos e capacidades de modelos anteriores, conhecimento das pesquisas e desenvolvimentos mais recentes na área, experiência no domínio (tanto interna quanto externa) e resultados de auditorias dos dados de entrada. Levar em consideração a dificuldade de produzir avaliações de risco confiáveis, promovendo uma cultura que leve a sério a incerteza significativa subjacente às previsões de riscos associados a modelos de fronteira. Considerar os potenciais benefícios do modelo. Incorporar aprendizados obtidos por meio de trocas de informações com o setor, a academia e o governo sobre as capacidades de modelos comparáveis. | I32: 2.2, 4.1, 6.5, 7.3 | J32: Fernando Alonso Piroga da Silva | K32: 2.2 , 4.1 , 6.5 ,7.3 | L32: Hugo Fagundes Faria Santos | M32: SIm | N32: 2.2, 4.1, 6.5, 7.3 | O32: Riscos plausíveis, inclusive de baixa probabilidade e consequência grave, não abrangidos pelo processo de avaliação por falta de fundamentação em red teaming, evidências de modelos anteriores e expertise externa, gerando danos evitáveis após a implementação. | P32: Relatório de avaliação de risco documentado, registrando os métodos utilizados (avaliações de modelos, red teaming, evidências de modelos anteriores, expertise interna e externa, auditoria dos dados de entrada), os riscos de baixa probabilidade e alta consequência considerados e os potenciais benefícios do modelo. | Q32: Médio | R32: Média | S32: Alta | T32: =IF(OR(R32="",S32=""),"",CHOOSE(MATCH(R32,Listas!$X$5:$X$7,0)+MATCH(S32,Listas!$Z$5:$Z$7,0)-1,"Alta","Alta","Média","Baixa","Baixa")) -> Baixa | U32: DSIT UK (2023, p. 8-12), perfil construído sobre o NIST AI RMF 1.0 (subcategorias MAP 1.1, MAP 1.6 e MEASURE 2.5), orienta o desenvolvimento de processos rigorosos de avaliação de risco fundamentados em testes de estresse (red teaming), evidências empíricas de modelos anteriores e consulta a especialistas internos e externos. De forma independente e complementar, a norma ISO/IEC 42001:2023 exige a definição e execução do processo de avaliação de riscos de IA (cláusulas 6.1.2 e 8.2) e a avaliação dos impactos do sistema sobre indivíduos e sociedade (cláusula 6.1.4 e controles A.5). Custo estimado pelo grupo, pela rubrica. | V32: Concluída | X32: {=IFERROR(INDEX(Listas!$D$5:$D$17,MATCH(F32,Listas!$C$5:$C$17,0)),"")} -> dsit-2023 | Y32: =IFERROR(LEFT(G32,FIND(" ",G32)-1),"") -> 1.2
A33: 32 | B33: Fernando Alonso Piroga da Silva | C33: A0766_UK Government2023 | D33: Development and Post-Deployment Monitoring | E33: Monitoramento durante o desenvolvimento e após a implementação | F33: Emerging Processes for Frontier AI Safety (DSIT UK, 2023) | G33: 1.2 Gestão de riscos | H33: Monitore os sistemas tanto durante o desenvolvimento quanto após a implementação. Novas avaliações de risco podem ser realizadas em casos de ajustes finos ou outras alterações substanciais que possam aumentar o perigo representado por um modelo — por exemplo, se o modelo passar a ter acesso a ferramentas ou plug-ins. Isso pode ocorrer paralelamente a esforços para detectar desdobramentos inesperados e novas informações que possam ter alterado os resultados da avaliação de risco existente, o que, por sua vez, poderia motivar a realização de uma nova avaliação de risco. | I33: 4.1, 6.5 | J33: Fernando Alonso Piroga da Silva | K33: 4.1, 6.5 | L33: Hugo Fagundes Faria Santos | M33: =IF(OR(I33="",K33=""),"",IF(TRIM(I33)=TRIM(K33),"Sim","Não")) -> Sim | N33: 4.1, 6.5 | O33: Ausência de monitoramento contínuo e de reavaliação após ajustes finos, acesso a ferramentas ou plug-ins ou novas informações, mantendo avaliações desatualizadas frente ao perigo real do modelo. | P33: Registro de monitoramento durante o desenvolvimento e após a implementação, com reavaliações de risco documentadas após ajustes finos, concessão de acesso a ferramentas ou plug-ins e identificação de novas informações relevantes (por exemplo, no histórico de versões do modelo). | Q33: Médio | R33: Média | S33: Alta | T33: =IF(OR(R33="",S33=""),"",CHOOSE(MATCH(R33,Listas!$X$5:$X$7,0)+MATCH(S33,Listas!$Z$5:$Z$7,0)-1,"Alta","Alta","Média","Baixa","Baixa")) -> Baixa | U33: DSIT UK (2023, p. 12-14), articulado com o NIST AI RMF 1.0 (subcategorias MEASURE 2.4, MANAGE 4.1 e GOVERN 1.5), orienta o monitoramento contínuo tanto na fase de desenvolvimento quanto pós-implantação, com reavaliações formais de risco engatilhadas por modificações substanciais (como concessão de acesso a ferramentas ou plug-ins). De forma alinhada, a ISO/IEC 42001:2023 estabelece requisitos e controles específicos para o monitoramento e operação contínua do sistema de IA (controle A.6.2.6 e seção B.6.2.6) e análise de desempenho em produção (cláusula 9.1). Custo estimado pelo grupo, pela rubrica. | V33: Concluída | X33: {=IFERROR(INDEX(Listas!$D$5:$D$17,MATCH(F33,Listas!$C$5:$C$17,0)),"")} -> dsit-2023 | Y33: =IFERROR(LEFT(G33,FIND(" ",G33)-1),"") -> 1.2
A34: 33 | B34: Fernando Alonso Piroga da Silva | C34: A0768_UK Government2023 | D34: Defining Risk Thresholds | E34: Definição de limiares de risco | F34: Emerging Processes for Frontier AI Safety (DSIT UK, 2023) | G34: 1.2 Gestão de riscos | H34: Defina limiares de risco com base nos resultados que configurariam uma violação desses limites, associando-os a capacidades perigosas que um determinado modelo — ou uma combinação de modelos — poderia apresentar. Por exemplo, uma organização que atua na fronteira da tecnologia de IA pode estabelecer, como objetivo, evitar a implementação de um sistema de IA que aumente significativamente o risco de ataques cibernéticos ou fraudes. | I34: 3.2, 4.1 | J34: Fernando Alonso Piroga da Silva | K34: 4.1, 6.5, 7.4 | L34: Hugo Fagundes Faria Santos | M34: =IF(OR(I34="",K34=""),"",IF(TRIM(I34)=TRIM(K34),"Sim","Não")) -> Não | N34: 4.1, 6.5 | O34: Limiares de risco não definidos ou não associados a capacidades perigosas do modelo, ou de combinações de modelos, impedindo a identificação do momento em que o risco se torna inaceitável. | P34: Documento de limiares de risco vinculando cada limiar às capacidades perigosas do modelo, isolado ou combinado com outros modelos, e às respostas previamente definidas em caso de violação (por exemplo, não implementar um sistema que aumente significativamente o risco de ataques cibernéticos ou fraudes). | Q34: Médio | R34: Média | S34: Alta | T34: =IF(OR(R34="",S34=""),"",CHOOSE(MATCH(R34,Listas!$X$5:$X$7,0)+MATCH(S34,Listas!$Z$5:$Z$7,0)-1,"Alta","Alta","Média","Baixa","Baixa")) -> Baixa | U34: DSIT UK (2023, p. 14-16), em alinhamento com o NIST AI RMF 1.0 (subcategorias GOVERN 1.3, MAP 1.5 e MAP 3.2), orienta a definição formal de limiares de risco (risk thresholds) associados a capacidades perigosas especificas que impediriam a liberação do sistema. De forma equivalente, a norma ISO/IEC 42001:2023 exige que a organização defina e estabeleça critérios de risco de IA claros (cláusulas 6.1.1 e 6.1.2 e) para distinguir riscos aceitáveis de inaceitáveis. Custo estimado pelo grupo, pela rubrica. | V34: Concluída | X34: {=IFERROR(INDEX(Listas!$D$5:$D$17,MATCH(F34,Listas!$C$5:$C$17,0)),"")} -> dsit-2023 | Y34: =IFERROR(LEFT(G34,FIND(" ",G34)-1),"") -> 1.2
A35: 34 | B35: Fernando Alonso Piroga da Silva | C35: A0769_UK Government2023 | D35: Operationalizing Risk Thresholds | E35: Operacionalização de limiares de risco | F35: Emerging Processes for Frontier AI Safety (DSIT UK, 2023) | G35: 1.2 Gestão de riscos | H35: Operacionalizar limiares de risco, incluindo observações específicas e passíveis de teste, de modo que diferentes observadores com acesso às mesmas informações cheguem a um consenso sobre se um determinado limiar foi atingido. Tais observações específicas permitiriam que organizações que desenvolvem IA de fronteira definissem, de forma proativa, como responderiam a situações potencialmente complexas — garantindo uma resposta imediata caso elas ocorram —, além de viabilizar a prestação de contas e a verificação externa. Contudo, dado que a ciência da avaliação de IA ainda está em estágio inicial, é pouco provável que seja possível definir um conjunto de observações passíveis de teste que detectem todos os riscos identificados com a devida confiabilidade. Em vez de depender exclusivamente desses testes predefinidos, as avaliações de risco podem levar em conta fontes de evidência mais amplas, como observações inesperadas ou preocupantes que surjam em análises exploratórias, previsões de especialistas ou informações relacionadas a riscos provenientes de outras organizações que desenvolvem IA de fronteira. Em particular, deve-se considerar eventuais riscos decorrentes da combinação de um determinado modelo com outros modelos ou ferramentas, independentemente de terem sido desenvolvidos pela mesma organização de IA de fronteira ou por terceiros. | I35: 3.2, 4.1, 5.1 | J35: Fernando Alonso Piroga da Silva | K35: 3.2 , 4.1 ,7.3 | L35: Renato Pestana de Gouveia | M35: =IF(OR(I35="",K35=""),"",IF(TRIM(I35)=TRIM(K35),"Sim","Não")) -> Não | N35: 3.2 ,7.3 | O35: Limiares de risco sem observações específicas e testáveis, ou dependentes exclusivamente de testes predefinidos, deixando riscos emergentes sem detecção e impedindo consenso entre avaliadores, prestação de contas e verificação externa. | P35: Especificação de observações testáveis para cada limiar, com protocolo de verificação por diferentes observadores, registro de fontes de evidência complementares (análises exploratórias, previsões de especialistas, informações de outras organizações) e de riscos decorrentes da combinação com outros modelos ou ferramentas. | Q35: Médio | R35: Média | S35: Alta | T35: =IF(OR(R35="",S35=""),"",CHOOSE(MATCH(R35,Listas!$X$5:$X$7,0)+MATCH(S35,Listas!$Z$5:$Z$7,0)-1,"Alta","Alta","Média","Baixa","Baixa")) -> Baixa | U35: DSIT UK (2023, p. 16-18), correlacionado ao NIST AI RMF 1.0 (subcategorias MAP 1.1, MEASURE 1.1 e MEASURE 2.3), detalha a operacionalização dos limiares em observações específicas e testáveis que permitam consenso entre avaliadores independentes, complementadas por pareceres de especialistas. De forma independente, a ISO/IEC 42001:2023 exige a especificação de medidas de verificação e validação com critérios de aceitação mensuráveis e objetivos (controle A.6.2.4 e seção B.6.2.4). Custo estimado pelo grupo, pela rubrica. | V35: Concluída | X35: {=IFERROR(INDEX(Listas!$D$5:$D$17,MATCH(F35,Listas!$C$5:$C$17,0)),"")} -> dsit-2023 | Y35: =IFERROR(LEFT(G35,FIND(" ",G35)-1),"") -> 1.2
A36: 35 | B36: Fernando Alonso Piroga da Silva | C36: A0770_UK Government2023 | D36: Refinement of Risk Evaluation Frameworks | E36: Aprimoramento de estruturas de avaliação de riscos | F36: Emerging Processes for Frontier AI Safety (DSIT UK, 2023) | G36: 1.2 Gestão de riscos | H36: Continue a refinar e redefinir as estruturas de avaliação de risco para modelos, conforme necessário, visando reduzir a lacuna entre os objetivos pretendidos para os limiares de risco e a forma como estes são operacionalizados atualmente. É natural que tais lacunas existam, dadas as limitações na ciência da avaliação e no estado atual do conhecimento sobre as capacidades existentes; portanto, o progresso rumo a uma estrutura robusta será, provavelmente, um processo iterativo. As estruturas de avaliação de risco podem empregar múltiplos métodos, incluindo estimativas de probabilidade e avaliações qualitativas das capacidades atuais. | I36: 3.1, 6.5 | J36: Fernando Alonso Piroga da Silva | K36: 3.1, 6.5, 7.4 | L36: Hugo Fagundes Faria Santos | M36: =IF(OR(I36="",K36=""),"",IF(TRIM(I36)=TRIM(K36),"Sim","Não")) -> Não | N36: 3.1, 6.5, 7.4 | O36: Estruturas de avaliação de risco não refinadas ao longo do tempo, mantendo lacuna entre os objetivos dos limiares e sua operacionalização e gerando falsa percepção de segurança. | P36: Registro de revisões periódicas da estrutura de avaliação de risco, com análise documentada da lacuna entre os objetivos dos limiares e sua operacionalização e plano de refinamento (por exemplo, no controle de versões da estrutura). | Q36: Médio | R36: Média | S36: Alta | T36: =IF(OR(R36="",S36=""),"",CHOOSE(MATCH(R36,Listas!$X$5:$X$7,0)+MATCH(S36,Listas!$Z$5:$Z$7,0)-1,"Alta","Alta","Média","Baixa","Baixa")) -> Baixa | U36: DSIT UK (2023, p. 18-20), respaldado pelo NIST AI RMF 1.0 (subcategorias GOVERN 1.5, MEASURE 1.2 e MANAGE 4.2), orienta a revisão iterativa das estruturas de avaliação de risco para reduzir lacunas na medição das capacidades emergentes dos modelos. De forma alinhada, a ISO/IEC 42001:2023 estabelece o princípio da melhoria contínua do sistema de gestão e de seus processos de avaliação de risco (cláusula 10.1) e exige revisões periódicas das políticas e controles (controle A.2.4). Custo estimado pelo grupo, pela rubrica. | V36: Concluída | X36: {=IFERROR(INDEX(Listas!$D$5:$D$17,MATCH(F36,Listas!$C$5:$C$17,0)),"")} -> dsit-2023 | Y36: =IFERROR(LEFT(G36,FIND(" ",G36)-1),"") -> 1.2
A37: 36 | B37: Fernando Alonso Piroga da Silva | C37: A0774_UK Government2023 | D37: Reassessment of Residual Risk | E37: Reavaliação do risco residual | F37: Emerging Processes for Frontier AI Safety (DSIT UK, 2023) | G37: 1.2 Gestão de riscos | H37: Após a implementação de medidas de mitigação, reavalie o risco residual existente para determinar se são necessárias medidas adicionais. Dada a imprevisibilidade dos avanços nas capacidades e as limitações da ciência de avaliação de modelos, as medidas de mitigação previamente acordadas podem se mostrar insuficientes para situar um determinado modelo dentro de um patamar de risco aceitável. Podem ser utilizados critérios de aceitação de risco — prática comum em diversos outros contextos —, os quais servem como uma ferramenta importante para conferir maior clareza. Tais critérios podem evoluir ao longo do tempo e ser de natureza quantitativa ou qualitativa. Por exemplo, um risco pode ser aceito apenas se tiver sido reduzido a um nível “tão baixo quanto razoavelmente exequível”. | I37: 3.1, 3.2 | J37: Fernando Alonso Piroga da Silva | K37: 3.1, 3.2, 7.4 | L37: Hugo Fagundes Faria Santos | M37: =IF(OR(I37="",K37=""),"",IF(TRIM(I37)=TRIM(K37),"Sim","Não")) -> Não | N37: 3.1, 3.2, 7.4 | O37: Risco residual não reavaliado após a implementação das mitigações, ou ausência de critérios de aceitação de risco claros, levando à liberação de modelos acima de um patamar de risco aceitável. | P37: Relatório de risco residual pós-mitigação, com os critérios de aceitação de risco adotados (quantitativos ou qualitativos, como “tão baixo quanto razoavelmente exequível”) e a decisão documentada sobre a suficiência das mitigações. | Q37: Médio | R37: Média | S37: Alta | T37: =IF(OR(R37="",S37=""),"",CHOOSE(MATCH(R37,Listas!$X$5:$X$7,0)+MATCH(S37,Listas!$Z$5:$Z$7,0)-1,"Alta","Alta","Média","Baixa","Baixa")) -> Baixa | U37: DSIT UK (2023, p. 20-22), fundamentado no NIST AI RMF 1.0 (subcategorias MANAGE 1.4, MANAGE 1.1 e GOVERN 1.3), orienta a reavaliação explícita do risco residual após a aplicação das mitigações para verificar se o modelo atinge critérios aceitáveis (ex.: "tão baixo quanto razoavelmente exequível"). Na norma ISO/IEC 42001:2023, a aprovação do plano de tratamento de riscos e a aceitação formal dos riscos residuais pela alta direção são exigências obrigatórias (cláusulas 6.1.3 e 8.3). Custo estimado pelo grupo, pela rubrica. | V37: Concluída | X37: {=IFERROR(INDEX(Listas!$D$5:$D$17,MATCH(F37,Listas!$C$5:$C$17,0)),"")} -> dsit-2023 | Y37: =IFERROR(LEFT(G37,FIND(" ",G37)-1),"") -> 1.2
A38: 37 | B38: Fernando Alonso Piroga da Silva | C38: A0775_UK Government2023 | D38: Disclosure of Risk Threshold to Government Authorities | E38: Divulgação de limiares de risco a autoridades governamentais | F38: Emerging Processes for Frontier AI Safety (DSIT UK, 2023) | G38: 1.2 Gestão de riscos | H38: Informe as autoridades governamentais competentes quando um limiar de risco for atingido, apresentando também as medidas de mitigação propostas. Informe novamente os governos, antes da implementação, uma vez que as medidas de mitigação tenham sido adotadas e a avaliação do risco residual tenha sido realizada. Envolva proativamente outros atores relevantes, além dos governos, conforme apropriado. | I38: 5.2, 6.5, 7.3 | J38: Fernando Alonso Piroga da Silva | K38: 5.2, 6.5, 7.4 | L38: Hugo Fagundes Faria Santos | M38: =IF(OR(I38="",K38=""),"",IF(TRIM(I38)=TRIM(K38),"Sim","Não")) -> Não | N38: 5.2, 6.5, 7.3, 7.4 | O38: Governos não informados quando um limiar de risco é atingido e antes da implementação das mitigações, comprometendo a supervisão externa e a resposta coordenada a riscos graves. | P38: Comunicações formais às autoridades governamentais competentes, registradas com data, informando a violação do limiar e as mitigações propostas, e nova comunicação antes da implementação com o resultado da avaliação de risco residual. | Q38: Médio | R38: Média | S38: Alta | T38: =IF(OR(R38="",S38=""),"",CHOOSE(MATCH(R38,Listas!$X$5:$X$7,0)+MATCH(S38,Listas!$Z$5:$Z$7,0)-1,"Alta","Alta","Média","Baixa","Baixa")) -> Baixa | U38: DSIT UK (2023, p. 22-24), em consonância com o NIST AI RMF 1.0 (subcategorias GOVERN 5.1, MAP 1.1, MEASURE 2.8 e MANAGE 4.3), orienta a notificação às autoridades governamentais competentes quando um limiar de risco for atingido e o envio de novo reporte pós-avaliação do risco residual. De forma equivalente, a ISO/IEC 42001:2023 trata do dever de reportar informações a autoridades reguladoras e partes interessadas no controle A.8.5 (Information for interested parties) e na seção B.8.5. Custo estimado pelo grupo, pela rubrica. | V38: Concluída | X38: {=IFERROR(INDEX(Listas!$D$5:$D$17,MATCH(F38,Listas!$C$5:$C$17,0)),"")} -> dsit-2023 | Y38: =IFERROR(LEFT(G38,FIND(" ",G38)-1),"") -> 1.2
A39: 38 | B39: Fernando Alonso Piroga da Silva | C39: A0777_UK Government2023 | D39: Adaptation of Mitigations for Unintended Model Use | E39: Adaptação de medidas de mitigação para usos não pretendidos do modelo | F39: Emerging Processes for Frontier AI Safety (DSIT UK, 2023) | G39: 1.2 Gestão de riscos | H39: Adapte as medidas de mitigação levando em conta os riscos decorrentes do uso não intencional de um modelo ou de sua utilização em contextos inesperados — por exemplo, um modelo que tenha suas salvaguardas removidas após ser disponibilizado como código aberto, ou um modelo que seja combinado com outro para finalidades não previstas. Assim, ao atingir um determinado patamar de risco, podem ser implementados controles de segurança da informação, mesmo antes de o modelo ser utilizado internamente por uma organização que desenvolve IA de fronteira. De modo geral, é prudente agir com cautela, dadas as limitações atuais nos controles de segurança da informação e na capacidade de prever habilidades emergentes em modelos. | I39: 2.2, 4.1 | J39: Fernando Alonso Piroga da Silva | K39: 2.2, 4.1, 6.5 | L39: Hugo Fagundes Faria Santos | M39: =IF(OR(I39="",K39=""),"",IF(TRIM(I39)=TRIM(K39),"Sim","Não")) -> Não | N39: 2.2, 4.1, 6.5 | O39: Mitigações que ignoram uso não intencional ou em contextos inesperados (remoção de salvaguardas em código aberto, combinação com outros modelos) e controles de segurança da informação ausentes, gerando danos evitáveis. | P39: Plano de mitigação que contemple uso não intencional e contextos inesperados (por exemplo, remoção de salvaguardas em código aberto, combinação com outros modelos), com registro dos controles de segurança da informação aplicados conforme o patamar de risco, inclusive antes do uso interno. | Q39: Médio | R39: Média | S39: Alta | T39: =IF(OR(R39="",S39=""),"",CHOOSE(MATCH(R39,Listas!$X$5:$X$7,0)+MATCH(S39,Listas!$Z$5:$Z$7,0)-1,"Alta","Alta","Média","Baixa","Baixa")) -> Baixa | U39: DSIT UK (2023, p. 24-26), associado ao NIST AI RMF 1.0 (subcategorias MAP 1.1, MAP 3.3, MANAGE 2.3 e GOVERN 4.1), orienta a adaptação de salvaguardas considerando o uso não pretendido, reutilização em contextos inesperados ou remoção de travas de segurança em modelos abertos. De forma correspondente, a ISO/IEC 42001:2023 exige a avaliação dos impactos decorrentes do uso pretendido e do "uso indevido razoavelmente previsível" (foreseeable misuse) (cláusulas 6.1.4 e 8.4) e a implementação de controles de uso pretendido no controle A.9.4 e seção B.9.4. Custo estimado pelo grupo, pela rubrica. | V39: Concluída | X39: {=IFERROR(INDEX(Listas!$D$5:$D$17,MATCH(F39,Listas!$C$5:$C$17,0)),"")} -> dsit-2023 | Y39: =IFERROR(LEFT(G39,FIND(" ",G39)-1),"") -> 1.2
A40: 39 | B40: Fernando Alonso Piroga da Silva | C40: A0782_UK Government2023 | D40: Risk Assessment Disclosure to Third Parties | E40: Divulgação de avaliações de risco a terceiros | F40: Emerging Processes for Frontier AI Safety (DSIT UK, 2023) | G40: 4.2 Divulgação de riscos | H40: Mantenha as partes interessadas relevantes atualizadas regularmente sobre a avaliação de riscos e as medidas de mitigação: isso permitirá avaliar se as organizações que atuam com IA possuem processos de gestão de riscos adequados, consolidar um panorama das melhores práticas e formular recomendações para suprir eventuais lacunas. Ao compartilhar essas informações com agentes externos, deve-se ter cautela quanto a dados comercialmente sensíveis. Atualizações pontuais adicionais podem ser fornecidas caso ocorram desenvolvimentos significativos. Inclua informações sobre avaliações, análise e mitigação de riscos, bem como sobre as pessoas envolvidas. Por exemplo: 1) Que tipos de testes e avaliações estão sendo realizados e em quais tipos de modelos; 2) Quais outros métodos de avaliação de riscos estão sendo empregados, que tipos de competências técnicas estão sendo mobilizados e se as partes interessadas afetadas estão sendo incluídas no processo; 3) Como as medidas de mitigação de riscos estão sendo monitoradas; 4) Quais equipes e indivíduos estão envolvidos nas diferentes etapas do processo de gestão de riscos (e de que forma, se for o caso, terceiros participam); 5) Medidas adotadas para tratar categorias específicas de risco, como, por exemplo, medidas de cibersegurança. | I40: 2.1, 5.2, 6.5, 7.3 | J40: Fernando Alonso Piroga da Silva | K40: 2.1, 6.5 | L40: Hugo Fagundes Faria Santos | M40: =IF(OR(I40="",K40=""),"",IF(TRIM(I40)=TRIM(K40),"Sim","Não")) -> Não | N40: 2.1, 6.5, 7.3 | O40: Partes interessadas sem informações regulares sobre avaliações, mitigações e responsáveis, ou com compartilhamento inadequado de dados comercialmente sensíveis, impedindo a verificação dos processos e a consolidação de melhores práticas. | P40: Relatórios periódicos às partes interessadas, descrevendo testes e avaliações realizados, métodos e competências mobilizados, monitoramento das mitigações, equipes e indivíduos envolvidos e medidas por categoria de risco (por exemplo, cibersegurança), com tratamento de dados comercialmente sensíveis. | Q40: Médio | R40: Média | S40: Alta | T40: =IF(OR(R40="",S40=""),"",CHOOSE(MATCH(R40,Listas!$X$5:$X$7,0)+MATCH(S40,Listas!$Z$5:$Z$7,0)-1,"Alta","Alta","Média","Baixa","Baixa")) -> Baixa | U40: DSIT UK (2023, p. 26-28), em sintonia com o NIST AI RMF 1.0 (subcategorias GOVERN 4.2, GOVERN 5.1, MEASURE 2.8 e MANAGE 4.3), orienta o compartilhamento periódico de informações sobre testes, avaliações e equipes envolvidas com terceiros e partes afetadas, resguardando informações proprietárias. De forma independente, a ISO/IEC 42001:2023 exige fornecer informações adequadas aos usuários e terceiros (controles A.8.2 e A.8.5; seções B.8.2 e B.8.5) e definir responsabilidades na cadeia de valor (controle A.10.2). Custo estimado pelo grupo, pela rubrica. | V40: Concluída | X40: {=IFERROR(INDEX(Listas!$D$5:$D$17,MATCH(F40,Listas!$C$5:$C$17,0)),"")} -> dsit-2023 | Y40: =IFERROR(LEFT(G40,FIND(" ",G40)-1),"") -> 4.2
A41: 40 | B41: Fernando Alonso Piroga da Silva | C41: A0784_UK Government2023 | D41: Effective Risk Governance | E41: Governança de riscos eficaz | F41: Emerging Processes for Frontier AI Safety (DSIT UK, 2023) | G41: 1.2 Gestão de riscos | H41: Estabeleça uma governança de riscos eficaz para assegurar que os riscos sejam adequadamente identificados, avaliados e tratados, e que sua natureza e dimensão sejam relatadas de forma transparente. Mais importante ainda: implemente mecanismos internos de controle e equilíbrio, o que pode incluir uma separação criteriosa de funções dentro da gestão de riscos. | I41: 4.1, 6.5 | J41: Fernando Alonso Piroga da Silva | K41: 3.1, 6.5, 7.2, 7.3 | L41: Hugo Fagundes Faria Santos | M41: =IF(OR(I41="",K41=""),"",IF(TRIM(I41)=TRIM(K41),"Sim","Não")) -> Não | N41: 3.1, 4.1, 6.5, 7.2, 7.3 | O41: Governança de riscos ineficaz, sem mecanismos internos de controle e equilíbrio nem separação de funções, gerando riscos não identificados, não tratados ou reportados sem transparência. | P41: Documento de estrutura de governança de riscos, definindo papéis, responsabilidades e separação de funções, com registros de mecanismos internos de controle e equilíbrio e de relatórios de riscos emitidos com transparência sobre sua natureza e dimensão. | Q41: Médio | R41: Média | S41: Alta | T41: =IF(OR(R41="",S41=""),"",CHOOSE(MATCH(R41,Listas!$X$5:$X$7,0)+MATCH(S41,Listas!$Z$5:$Z$7,0)-1,"Alta","Alta","Média","Baixa","Baixa")) -> Baixa | U41: DSIT UK (2023, p. 28-30), articulado com o NIST AI RMF 1.0 (subcategorias GOVERN 1.1, GOVERN 1.4, GOVERN 2.1 e GOVERN 2.3), estabelece a necessidade de uma governança de riscos eficaz com segregação de funções (checks and balances) e envolvimento da liderança executiva. De forma direta e equivalente, a norma ISO/IEC 42001:2023 estrutura a governança como pilar central no item 5 (Liderança e comprometimento, cláusula 5.1; Papéis e responsabilidades, cláusula 5.3) e no controle A.3.2 (AI roles and responsibilities) e seção B.3.2. Custo estimado pelo grupo, pela rubrica. | V41: Concluída | X41: {=IFERROR(INDEX(Listas!$D$5:$D$17,MATCH(F41,Listas!$C$5:$C$17,0)),"")} -> dsit-2023 | Y41: =IFERROR(LEFT(G41,FIND(" ",G41)-1),"") -> 1.2
A42: 41 | M42: =IF(OR(I42="",K42=""),"",IF(TRIM(I42)=TRIM(K42),"Sim","Não")) | T42: =IF(OR(R42="",S42=""),"",CHOOSE(MATCH(R42,Listas!$X$5:$X$7,0)+MATCH(S42,Listas!$Z$5:$Z$7,0)-1,"Alta","Alta","Média","Baixa","Baixa")) | X42: {=IFERROR(INDEX(Listas!$D$5:$D$17,MATCH(F42,Listas!$C$5:$C$17,0)),"")} | Y42: =IFERROR(LEFT(G42,FIND(" ",G42)-1),"")
A43: 42 | M43: =IF(OR(I43="",K43=""),"",IF(TRIM(I43)=TRIM(K43),"Sim","Não")) | T43: =IF(OR(R43="",S43=""),"",CHOOSE(MATCH(R43,Listas!$X$5:$X$7,0)+MATCH(S43,Listas!$Z$5:$Z$7,0)-1,"Alta","Alta","Média","Baixa","Baixa")) | X43: {=IFERROR(INDEX(Listas!$D$5:$D$17,MATCH(F43,Listas!$C$5:$C$17,0)),"")} | Y43: =IFERROR(LEFT(G43,FIND(" ",G43)-1),"")
A44: 43 | M44: =IF(OR(I44="",K44=""),"",IF(TRIM(I44)=TRIM(K44),"Sim","Não")) | T44: =IF(OR(R44="",S44=""),"",CHOOSE(MATCH(R44,Listas!$X$5:$X$7,0)+MATCH(S44,Listas!$Z$5:$Z$7,0)-1,"Alta","Alta","Média","Baixa","Baixa")) | X44: {=IFERROR(INDEX(Listas!$D$5:$D$17,MATCH(F44,Listas!$C$5:$C$17,0)),"")} | Y44: =IFERROR(LEFT(G44,FIND(" ",G44)-1),"")
A45: 44 | M45: =IF(OR(I45="",K45=""),"",IF(TRIM(I45)=TRIM(K45),"Sim","Não")) | T45: =IF(OR(R45="",S45=""),"",CHOOSE(MATCH(R45,Listas!$X$5:$X$7,0)+MATCH(S45,Listas!$Z$5:$Z$7,0)-1,"Alta","Alta","Média","Baixa","Baixa")) | X45: {=IFERROR(INDEX(Listas!$D$5:$D$17,MATCH(F45,Listas!$C$5:$C$17,0)),"")} | Y45: =IFERROR(LEFT(G45,FIND(" ",G45)-1),"")
A46: 45 | M46: =IF(OR(I46="",K46=""),"",IF(TRIM(I46)=TRIM(K46),"Sim","Não")) | T46: =IF(OR(R46="",S46=""),"",CHOOSE(MATCH(R46,Listas!$X$5:$X$7,0)+MATCH(S46,Listas!$Z$5:$Z$7,0)-1,"Alta","Alta","Média","Baixa","Baixa")) | X46: {=IFERROR(INDEX(Listas!$D$5:$D$17,MATCH(F46,Listas!$C$5:$C$17,0)),"")} | Y46: =IFERROR(LEFT(G46,FIND(" ",G46)-1),"")
A47: 46 | M47: =IF(OR(I47="",K47=""),"",IF(TRIM(I47)=TRIM(K47),"Sim","Não")) | T47: =IF(OR(R47="",S47=""),"",CHOOSE(MATCH(R47,Listas!$X$5:$X$7,0)+MATCH(S47,Listas!$Z$5:$Z$7,0)-1,"Alta","Alta","Média","Baixa","Baixa")) | X47: {=IFERROR(INDEX(Listas!$D$5:$D$17,MATCH(F47,Listas!$C$5:$C$17,0)),"")} | Y47: =IFERROR(LEFT(G47,FIND(" ",G47)-1),"")
A48: 47 | M48: =IF(OR(I48="",K48=""),"",IF(TRIM(I48)=TRIM(K48),"Sim","Não")) | T48: =IF(OR(R48="",S48=""),"",CHOOSE(MATCH(R48,Listas!$X$5:$X$7,0)+MATCH(S48,Listas!$Z$5:$Z$7,0)-1,"Alta","Alta","Média","Baixa","Baixa")) | X48: {=IFERROR(INDEX(Listas!$D$5:$D$17,MATCH(F48,Listas!$C$5:$C$17,0)),"")} | Y48: =IFERROR(LEFT(G48,FIND(" ",G48)-1),"")
A49: 48 | M49: =IF(OR(I49="",K49=""),"",IF(TRIM(I49)=TRIM(K49),"Sim","Não")) | T49: =IF(OR(R49="",S49=""),"",CHOOSE(MATCH(R49,Listas!$X$5:$X$7,0)+MATCH(S49,Listas!$Z$5:$Z$7,0)-1,"Alta","Alta","Média","Baixa","Baixa")) | X49: {=IFERROR(INDEX(Listas!$D$5:$D$17,MATCH(F49,Listas!$C$5:$C$17,0)),"")} | Y49: =IFERROR(LEFT(G49,FIND(" ",G49)-1),"")
A50: 49 | M50: =IF(OR(I50="",K50=""),"",IF(TRIM(I50)=TRIM(K50),"Sim","Não")) | T50: =IF(OR(R50="",S50=""),"",CHOOSE(MATCH(R50,Listas!$X$5:$X$7,0)+MATCH(S50,Listas!$Z$5:$Z$7,0)-1,"Alta","Alta","Média","Baixa","Baixa")) | X50: {=IFERROR(INDEX(Listas!$D$5:$D$17,MATCH(F50,Listas!$C$5:$C$17,0)),"")} | Y50: =IFERROR(LEFT(G50,FIND(" ",G50)-1),"")
A51: 50 | M51: =IF(OR(I51="",K51=""),"",IF(TRIM(I51)=TRIM(K51),"Sim","Não")) | T51: =IF(OR(R51="",S51=""),"",CHOOSE(MATCH(R51,Listas!$X$5:$X$7,0)+MATCH(S51,Listas!$Z$5:$Z$7,0)-1,"Alta","Alta","Média","Baixa","Baixa")) | X51: {=IFERROR(INDEX(Listas!$D$5:$D$17,MATCH(F51,Listas!$C$5:$C$17,0)),"")} | Y51: =IFERROR(LEFT(G51,FIND(" ",G51)-1),"")
A52: 51 | M52: =IF(OR(I52="",K52=""),"",IF(TRIM(I52)=TRIM(K52),"Sim","Não")) | T52: =IF(OR(R52="",S52=""),"",CHOOSE(MATCH(R52,Listas!$X$5:$X$7,0)+MATCH(S52,Listas!$Z$5:$Z$7,0)-1,"Alta","Alta","Média","Baixa","Baixa")) | X52: {=IFERROR(INDEX(Listas!$D$5:$D$17,MATCH(F52,Listas!$C$5:$C$17,0)),"")} | Y52: =IFERROR(LEFT(G52,FIND(" ",G52)-1),"")
A53: 52 | M53: =IF(OR(I53="",K53=""),"",IF(TRIM(I53)=TRIM(K53),"Sim","Não")) | T53: =IF(OR(R53="",S53=""),"",CHOOSE(MATCH(R53,Listas!$X$5:$X$7,0)+MATCH(S53,Listas!$Z$5:$Z$7,0)-1,"Alta","Alta","Média","Baixa","Baixa")) | X53: {=IFERROR(INDEX(Listas!$D$5:$D$17,MATCH(F53,Listas!$C$5:$C$17,0)),"")} | Y53: =IFERROR(LEFT(G53,FIND(" ",G53)-1),"")
... A61: 60 | M61: =IF(OR(I61="",K61=""),"",IF(TRIM(I61)=TRIM(K61),"Sim","Não")) | T61: =IF(OR(R61="",S61=""),"",CHOOSE(MATCH(R61,Listas!$X$5:$X$7,0)+MATCH(S61,Listas!$Z$5:$Z$7,0)-1,"Alta","Alta","Média","Baixa","Baixa")) | X61: {=IFERROR(INDEX(Listas!$D$5:$D$17,MATCH(F61,Listas!$C$5:$C$17,0)),"")} | Y61: =IFERROR(LEFT(G61,FIND(" ",G61)-1),"")

Sheet Listas
A1: Listas usadas nas seleções das outras folhas. Os códigos são a referência para a importação; os nomes seguem os arquivos de taxonomia do repositório.
A3: Membros do grupo | C3: Documentos de origem (Saeri et al.) | F3: Subcategorias de Saeri et al. | J3: Domínios de risco (MIT) | M3: Subdomínios de risco (MIT) | P3: Sim/Não | R3: Decisão | T3: Motivo da exclusão | V3: Custo | X3: Evidência | Z3: Concordância | AB3: Situação | AD3: Subcategorias para a triagem (inclui as não classificadas)
A4: Membro | C4: Documento | D4: Chave | F4: Opção | G4: Código | H4: Nome | J4: Código | K4: Domínio | M4: Código | N4: Subdomínio | P4: Sim/Não | R4: Decisão | T4: Motivo da exclusão | V4: Custo | X4: Evidência | Z4: Concordância | AB4: Situação | AD4: Opção
A5: Angelo Andrioli Netho | C5: International AI Safety Report 2025 (Bengio et al., 2025) | D5: bengio-2025 | F5: 1.1 Estrutura de conselho e supervisão | G5: 1.1 | H5: Estrutura de conselho e supervisão | J5: 1 | K5: Discriminação e toxicidade | M5: 1.1 | N5: Discriminação injusta e representação distorcida | P5: Sim | R5: Incluir | T5: Ator | V5: Baixo | X5: Limitada | Z5: Baixa | AB5: Rascunho | AD5: 1.1 Estrutura de conselho e supervisão
A6: Fernando Alonso Piroga da Silva | C6: A Frontier AI Risk Management Framework (Campos et al., 2025) | D6: campos-2025 | F6: 1.2 Gestão de riscos | G6: 1.2 | H6: Gestão de riscos | J6: 2 | K6: Privacidade e segurança | M6: 1.2 | N6: Exposição a conteúdo tóxico | P6: Não | R6: Excluir | T6: Acionável | V6: Médio | X6: Média | Z6: Média | AB6: Em revisão | AD6: 1.2 Gestão de riscos
A7: Hugo Fagundes Faria Santos | C7: The Unified Control Framework (Eisenberg et al., 2025) | D7: eisenberg-2025 | F7: 1.3 Proteção contra conflitos de interesse | G7: 1.3 | H7: Proteção contra conflitos de interesse | J7: 3 | K7: Informação incorreta | M7: 1.3 | N7: Desempenho desigual entre grupos | T7: Verificável | V7: Alto | X7: Robusta | Z7: Alta | AB7: Concluída | AD7: 1.3 Proteção contra conflitos de interesse
A8: Renato Pestana de Gouveia | C8: Risk Sources and Risk Management Measures (Gipiškis et al., 2024) | D8: gipiskis-2024 | F8: 1.4 Canal de denúncia e proteção ao denunciante | G8: 1.4 | H8: Canal de denúncia e proteção ao denunciante | J8: 4 | K8: Agentes maliciosos e uso indevido | M8: 2.1 | N8: Comprometimento da privacidade por obtenção, vazamento ou inferência de informações sensíveis | T8: Classificada | AD8: 1.4 Canal de denúncia e proteção ao denunciante
C9: Effective Mitigations for Systemic Risks from GPAI (Uuk et al., 2024) | D9: uuk-2024 | F9: 1.5 Estruturas de decisão de segurança | G9: 1.5 | H9: Estruturas de decisão de segurança | J9: 5 | K9: Interação humano-computador | M9: 2.2 | N9: Vulnerabilidades de segurança e ataques a sistemas de IA | T9: Redundante | AD9: 1.5 Estruturas de decisão de segurança
C10: FLI AI Safety Index 2024 (Future of Life Institute) | D10: fli-2024 | F10: 1.6 Gestão de impacto ambiental | G10: 1.6 | H10: Gestão de impacto ambiental | J10: 6 | K10: Socioeconômico e ambiental | M10: 3.1 | N10: Informação falsa ou enganosa | T10: Fora da seleção de cobertura | AD10: 1.6 Gestão de impacto ambiental
C11: Towards Best Practices in AGI Safety and Governance (Schuett et al., 2023) | D11: schuett-2023 | F11: 1.7 Avaliação de impacto social | G11: 1.7 | H11: Avaliação de impacto social | J11: 7 | K11: Segurança, falhas e limitações de sistemas de IA | M11: 3.2 | N11: Poluição do ecossistema de informação e perda de uma realidade comum | AD11: 1.7 Avaliação de impacto social
C12: Pitfalls of Evidence-Based AI Policy (Casper et al., 2025) | D12: casper-2025 | F12: 2.1 Segurança do modelo e da infraestrutura | G12: 2.1 | H12: Segurança do modelo e da infraestrutura | M12: 4.1 | N12: Desinformação, vigilância e influência em larga escala | AD12: 2.1 Segurança do modelo e da infraestrutura
C13: EU AI Act: GPAI Code of Practice, Draft 3 (EU AI Office, 2025) | D13: eu-ai-office-2025 | F13: 2.2 Alinhamento do modelo | G13: 2.2 | H13: Alinhamento do modelo | M13: 4.2 | N13: Ciberataques, desenvolvimento ou uso de armas e danos em massa | AD13: 2.2 Alinhamento do modelo
C14: Emerging Processes for Frontier AI Safety (DSIT UK, 2023) | D14: dsit-2023 | F14: 2.3 Engenharia de segurança do modelo | G14: 2.3 | H14: Engenharia de segurança do modelo | M14: 4.3 | N14: Fraudes, golpes e manipulação direcionada | AD14: 2.3 Engenharia de segurança do modelo
C15: NIST AI RMF: Generative AI Profile (NIST, 2024) | D15: nist-2024 | F15: 2.4 Controles de segurança de conteúdo | G15: 2.4 | H15: Controles de segurança de conteúdo | M15: 5.1 | N15: Dependência excessiva e uso inseguro | AD15: 2.4 Controles de segurança de conteúdo
C16: AI Risk Management Standards Profile for GPAIS (Barrett et al., 2024) | D16: barrett-2024 | F16: 3.1 Testes e auditoria | G16: 3.1 | H16: Testes e auditoria | M16: 5.2 | N16: Perda de agência e autonomia humanas | AD16: 3.1 Testes e auditoria
C17: California Senate Bill 1047 (2024) | D17: ca-sb1047-2024 | F17: 3.2 Governança de dados | G17: 3.2 | H17: Governança de dados | M17: 6.1 | N17: Centralização de poder e distribuição injusta de benefícios | AD17: 3.2 Governança de dados
F18: 3.3 Gestão de acesso | G18: 3.3 | H18: Gestão de acesso | M18: 6.2 | N18: Aumento da desigualdade e piora na qualidade do emprego | AD18: 3.3 Gestão de acesso
F19: 3.4 Implantação em etapas | G19: 3.4 | H19: Implantação em etapas | M19: 6.3 | N19: Desvalorização econômica e cultural do esforço humano | AD19: 3.4 Implantação em etapas
F20: 3.5 Monitoramento pós-implantação | G20: 3.5 | H20: Monitoramento pós-implantação | M20: 6.4 | N20: Dinâmicas competitivas | AD20: 3.5 Monitoramento pós-implantação
F21: 3.6 Resposta a incidentes e recuperação | G21: 3.6 | H21: Resposta a incidentes e recuperação | M21: 6.5 | N21: Falha de governança | AD21: 3.6 Resposta a incidentes e recuperação
F22: 4.1 Documentação do sistema | G22: 4.1 | H22: Documentação do sistema | M22: 6.6 | N22: Danos ambientais | AD22: 4.1 Documentação do sistema
F23: 4.2 Divulgação de riscos | G23: 4.2 | H23: Divulgação de riscos | M23: 7.1 | N23: IA perseguindo objetivos próprios em conflito com objetivos ou valores humanos | AD23: 4.2 Divulgação de riscos
F24: 4.3 Relato de incidentes | G24: 4.3 | H24: Relato de incidentes | M24: 7.2 | N24: IA com capacidades perigosas | AD24: 4.3 Relato de incidentes
F25: 4.4 Divulgação da governança | G25: 4.4 | H25: Divulgação da governança | M25: 7.3 | N25: Falta de capacidade ou robustez | AD25: 4.4 Divulgação da governança
F26: 4.5 Acesso de terceiros ao sistema | G26: 4.5 | H26: Acesso de terceiros ao sistema | M26: 7.4 | N26: Falta de transparência ou interpretabilidade | AD26: 4.5 Acesso de terceiros ao sistema
F27: 4.6 Direitos e recursos dos usuários | G27: 4.6 | H27: Direitos e recursos dos usuários | M27: 7.5 | N27: Bem-estar e direitos da IA | AD27: 4.6 Direitos e recursos dos usuários
M28: 7.6 | N28: Riscos multiagentes | AD28: X.X Controle não categorizado
AD29: 1.X Controle de governança e supervisão não categorizado
AD30: 2.X Controle técnico e de segurança não categorizado
AD31: 3.X Controle de processo operacional não categorizado

Sheet Rubrica
A1: Rubrica de custo e incerteza
A2: Escalas qualitativas, com cada nível definido por critérios explícitos, para que dois anotadores cheguem ao mesmo nível pela mesma mitigação. Uma avaliação qualitativa usa categorias ou níveis não numéricos (NIST SP 800-30 Rev. 1); definir o que cada nível significa é o que a torna repetível.
A4: 1. Custo sugerido
A5: Esforço típico para uma organização que implanta ou opera um sistema de IA colocar a mitigação em prática pela primeira vez. Avalie as quatro dimensões; se elas apontarem níveis diferentes, use o mais alto.
A6: Dimensão | B6: Baixo | C6: Médio | D6: Alto
A7: Tempo para implantar | B7: Até cerca de duas semanas. | C7: De algumas semanas a cerca de três meses. | D7: Mais de três meses.
A8: Pessoas e competências | B8: A própria equipe do sistema, sem competência nova. | C8: Envolve outra área ou competência específica (jurídico, segurança, dados). | D8: Exige equipe dedicada, contratação ou especialista externo.
A9: Ferramentas e serviços | B9: Nenhuma ferramenta ou serviço novo pago. | C9: Ferramenta ou serviço de custo moderado, ou ampliação de um existente. | D9: Infraestrutura, ferramenta ou serviço dedicado, ou auditoria externa.
A10: Impacto na operação | B10: Não altera processos de outras áreas. | C10: Altera um processo existente. | D10: Muda a arquitetura do sistema ou processos de várias áreas.
A11: Exemplos | B11: Checklist de revisão antes da implantação; política de uso documentada. | C11: Monitoramento contínuo com ferramenta já disponível; treinamento das equipes. | D11: Auditoria independente; red teaming externo; retreinamento do modelo.
A13: 2. Incerteza da estimativa
A14: A incerteza se refere às estimativas do grupo para a mitigação (risco-alvo, evidência esperada e custo), e não à mitigação em si. Segue a abordagem do IPCC (Mastrandrea et al., 2010): avalia-se o tipo, a quantidade e a qualidade da evidência e o grau de concordância entre as fontes, e a combinação dos dois define o nível. A coluna 'Fonte da estimativa' registra essa avaliação, como o relato rastreável que o IPCC recomenda.
A15: Evidência | B15: Limitada | C15: Média | D15: Robusta
A16: Descrição | B16: Fonte única, opinião ou proposta sem aplicação relatada. | C16: Mais de uma fonte, ou norma ou guia reconhecido, mas sem dado empírico. | D16: Várias fontes independentes, com estudo empírico, avaliação publicada ou norma aplicada.
A18: Concordância | B18: Baixa | C18: Média | D18: Alta
A19: Descrição | B19: As fontes divergem sobre o risco tratado, o custo ou a evidência. | C19: As fontes convergem em parte, com divergências relevantes. | D19: As fontes convergem sobre o que a mitigação trata, custa e produz.
A21: Matriz de incerteza (calculada na folha Catálogo)
A22: Evidência \ Concordância | B22: Baixa | C22: Média | D22: Alta
A23: Robusta | B23: Média | C23: Baixa | D23: Baixa
A24: Média | B24: Alta | C24: Média | D24: Baixa
A25: Limitada | B25: Alta | C25: Alta | D25: Média
A27: Referências
A28: MASTRANDREA, M. D. et al. Guidance Note for Lead Authors of the IPCC Fifth Assessment Report on Consistent Treatment of Uncertainties. IPCC, 2010.
A29: MASTRANDREA, M. D. et al. The IPCC AR5 guidance note on consistent treatment of uncertainties: a common approach across the working groups. Climatic Change, v. 108, p. 675-691, 2011. DOI: 10.1007/s10584-011-0178-6.
A30: NATIONAL INSTITUTE OF STANDARDS AND TECHNOLOGY. Guide for Conducting Risk Assessments. NIST SP 800-30 Rev. 1. Gaithersburg: NIST, 2012. DOI: 10.6028/NIST.SP.800-30r1.

Sheet Acompanhamento
A1: Acompanhamento (tudo calculado, não editar)
A3: Catálogo | B3: Valor | C3: Meta | D3: Situação
A4: Mitigações no catálogo | B4: =COUNTA('Catálogo'!C2:C61) -> 40 | C4: 40 | D4: =IF(B4=C4,"OK",IF(B4<C4,"Faltam "&(C4-B4),"Excede em "&(B4-C4))) -> OK
A5: Entradas incluídas na triagem | B5: =COUNTIF(Triagem!M2:M1001,"Incluir") -> 40 | C5: =C4 -> 40 | D5: =IF(B5=B4,"OK","Diferente do catálogo") -> OK
A6: Entradas analisadas na triagem | B6: =COUNTA(Triagem!M2:M1001) -> 40
A7: Entradas da triagem com assistência de IA | B7: =COUNTIF(Triagem!O2:O1001,"Sim") -> 831
A8: Concordância exata entre anotadores (indicador) | B8: =IFERROR(COUNTIF('Catálogo'!M2:M61,"Sim")/(COUNTIF('Catálogo'!M2:M61,"Sim")+COUNTIF('Catálogo'!M2:M61,"Não")),"") -> 0.4
A10: Por membro | B10: Triagem: bloco | C10: Triagem: conferidas | D10: Triagem: progresso | E10: Catálogo | F10: Situação do catálogo
A11: Angelo Andrioli Netho | B11: =COUNTIF(Triagem!$F$2:$F$1001,A11) -> 213 | C11: =COUNTIFS(Triagem!$F$2:$F$1001,A11,Triagem!$G$2:$G$1001,"<>",Triagem!$H$2:$H$1001,"<>",Triagem!$I$2:$I$1001,"<>") -> 213 | D11: =IFERROR(C11/B11,0) -> 1 | E11: =COUNTIF('Catálogo'!$B$2:$B$61,A11) -> 10 | F11: =IF(E11=10,"OK",IF(E11<10,"Faltam "&(10-E11),"Excede em "&(E11-10))) -> OK
A12: Fernando Alonso Piroga da Silva | B12: =COUNTIF(Triagem!$F$2:$F$1001,A12) -> 201 | C12: =COUNTIFS(Triagem!$F$2:$F$1001,A12,Triagem!$G$2:$G$1001,"<>",Triagem!$H$2:$H$1001,"<>",Triagem!$I$2:$I$1001,"<>") -> 201 | D12: =IFERROR(C12/B12,0) -> 1 | E12: =COUNTIF('Catálogo'!$B$2:$B$61,A12) -> 10 | F12: =IF(E12=10,"OK",IF(E12<10,"Faltam "&(10-E12),"Excede em "&(E12-10))) -> OK
A13: Hugo Fagundes Faria Santos | B13: =COUNTIF(Triagem!$F$2:$F$1001,A13) -> 216 | C13: =COUNTIFS(Triagem!$F$2:$F$1001,A13,Triagem!$G$2:$G$1001,"<>",Triagem!$H$2:$H$1001,"<>",Triagem!$I$2:$I$1001,"<>") -> 215 | D13: =IFERROR(C13/B13,0) -> 0.99537037 | E13: =COUNTIF('Catálogo'!$B$2:$B$61,A13) -> 10 | F13: =IF(E13=10,"OK",IF(E13<10,"Faltam "&(10-E13),"Excede em "&(E13-10))) -> OK
A14: Renato Pestana de Gouveia | B14: =COUNTIF(Triagem!$F$2:$F$1001,A14) -> 201 | C14: =COUNTIFS(Triagem!$F$2:$F$1001,A14,Triagem!$G$2:$G$1001,"<>",Triagem!$H$2:$H$1001,"<>",Triagem!$I$2:$I$1001,"<>") -> 201 | D14: =IFERROR(C14/B14,0) -> 1 | E14: =COUNTIF('Catálogo'!$B$2:$B$61,A14) -> 10 | F14: =IF(E14=10,"OK",IF(E14<10,"Faltam "&(10-E14),"Excede em "&(E14-10))) -> OK
A16: Domínio de risco do MIT (meta: 3 mitigações ou mais) | B16: Mitigações | C16: Meta | D16: Situação
A17: 1. Discriminação e toxicidade | B17: =COUNTIF('Catálogo'!N2:N61,"1.*")+COUNTIF('Catálogo'!N2:N61,"*, 1.*") -> 6 | C17: 3 | D17: =IF(B17>=C17,"OK","Faltam "&(C17-B17)) -> OK
A18: 2. Privacidade e segurança | B18: =COUNTIF('Catálogo'!N2:N61,"2.*")+COUNTIF('Catálogo'!N2:N61,"*, 2.*") -> 17 | C18: 3 | D18: =IF(B18>=C18,"OK","Faltam "&(C18-B18)) -> OK
A19: 3. Informação incorreta | B19: =COUNTIF('Catálogo'!N2:N61,"3.*")+COUNTIF('Catálogo'!N2:N61,"*, 3.*") -> 12 | C19: 3 | D19: =IF(B19>=C19,"OK","Faltam "&(C19-B19)) -> OK
A20: 4. Agentes maliciosos e uso indevido | B20: =COUNTIF('Catálogo'!N2:N61,"4.*")+COUNTIF('Catálogo'!N2:N61,"*, 4.*") -> 15 | C20: 3 | D20: =IF(B20>=C20,"OK","Faltam "&(C20-B20)) -> OK
A21: 5. Interação humano-computador | B21: =COUNTIF('Catálogo'!N2:N61,"5.*")+COUNTIF('Catálogo'!N2:N61,"*, 5.*") -> 6 | C21: 3 | D21: =IF(B21>=C21,"OK","Faltam "&(C21-B21)) -> OK
A22: 6. Socioeconômico e ambiental | B22: =COUNTIF('Catálogo'!N2:N61,"6.*")+COUNTIF('Catálogo'!N2:N61,"*, 6.*") -> 30 | C22: 3 | D22: =IF(B22>=C22,"OK","Faltam "&(C22-B22)) -> OK
A23: 7. Segurança, falhas e limitações de sistemas de IA | B23: =COUNTIF('Catálogo'!N2:N61,"7.*")+COUNTIF('Catálogo'!N2:N61,"*, 7.*") -> 33 | C23: 3 | D23: =IF(B23>=C23,"OK","Faltam "&(C23-B23)) -> OK
A25: Subcategoria de Saeri et al. (cobertura) | B25: Mitigações | D25: Situação
A26: 1.1 Estrutura de conselho e supervisão | B26: =COUNTIF('Catálogo'!G2:G61,"1.1 *") -> 0 | D26: =IF(B26>0,"Coberta","Sem mitigação") -> Sem mitigação
A27: 1.2 Gestão de riscos | B27: =COUNTIF('Catálogo'!G2:G61,"1.2 *") -> 12 | D27: =IF(B27>0,"Coberta","Sem mitigação") -> Coberta
A28: 1.3 Proteção contra conflitos de interesse | B28: =COUNTIF('Catálogo'!G2:G61,"1.3 *") -> 0 | D28: =IF(B28>0,"Coberta","Sem mitigação") -> Sem mitigação
A29: 1.4 Canal de denúncia e proteção ao denunciante | B29: =COUNTIF('Catálogo'!G2:G61,"1.4 *") -> 0 | D29: =IF(B29>0,"Coberta","Sem mitigação") -> Sem mitigação
A30: 1.5 Estruturas de decisão de segurança | B30: =COUNTIF('Catálogo'!G2:G61,"1.5 *") -> 1 | D30: =IF(B30>0,"Coberta","Sem mitigação") -> Coberta
A31: 1.6 Gestão de impacto ambiental | B31: =COUNTIF('Catálogo'!G2:G61,"1.6 *") -> 1 | D31: =IF(B31>0,"Coberta","Sem mitigação") -> Coberta
A32: 1.7 Avaliação de impacto social | B32: =COUNTIF('Catálogo'!G2:G61,"1.7 *") -> 0 | D32: =IF(B32>0,"Coberta","Sem mitigação") -> Sem mitigação
A33: 2.1 Segurança do modelo e da infraestrutura | B33: =COUNTIF('Catálogo'!G2:G61,"2.1 *") -> 0 | D33: =IF(B33>0,"Coberta","Sem mitigação") -> Sem mitigação
A34: 2.2 Alinhamento do modelo | B34: =COUNTIF('Catálogo'!G2:G61,"2.2 *") -> 0 | D34: =IF(B34>0,"Coberta","Sem mitigação") -> Sem mitigação
A35: 2.3 Engenharia de segurança do modelo | B35: =COUNTIF('Catálogo'!G2:G61,"2.3 *") -> 2 | D35: =IF(B35>0,"Coberta","Sem mitigação") -> Coberta
A36: 2.4 Controles de segurança de conteúdo | B36: =COUNTIF('Catálogo'!G2:G61,"2.4 *") -> 3 | D36: =IF(B36>0,"Coberta","Sem mitigação") -> Coberta
A37: 3.1 Testes e auditoria | B37: =COUNTIF('Catálogo'!G2:G61,"3.1 *") -> 6 | D37: =IF(B37>0,"Coberta","Sem mitigação") -> Coberta
A38: 3.2 Governança de dados | B38: =COUNTIF('Catálogo'!G2:G61,"3.2 *") -> 1 | D38: =IF(B38>0,"Coberta","Sem mitigação") -> Coberta
A39: 3.3 Gestão de acesso | B39: =COUNTIF('Catálogo'!G2:G61,"3.3 *") -> 1 | D39: =IF(B39>0,"Coberta","Sem mitigação") -> Coberta
A40: 3.4 Implantação em etapas | B40: =COUNTIF('Catálogo'!G2:G61,"3.4 *") -> 1 | D40: =IF(B40>0,"Coberta","Sem mitigação") -> Coberta
A41: 3.5 Monitoramento pós-implantação | B41: =COUNTIF('Catálogo'!G2:G61,"3.5 *") -> 4 | D41: =IF(B41>0,"Coberta","Sem mitigação") -> Coberta
A42: 3.6 Resposta a incidentes e recuperação | B42: =COUNTIF('Catálogo'!G2:G61,"3.6 *") -> 2 | D42: =IF(B42>0,"Coberta","Sem mitigação") -> Coberta
A43: 4.1 Documentação do sistema | B43: =COUNTIF('Catálogo'!G2:G61,"4.1 *") -> 1 | D43: =IF(B43>0,"Coberta","Sem mitigação") -> Coberta
A44: 4.2 Divulgação de riscos | B44: =COUNTIF('Catálogo'!G2:G61,"4.2 *") -> 1 | D44: =IF(B44>0,"Coberta","Sem mitigação") -> Coberta
A45: 4.3 Relato de incidentes | B45: =COUNTIF('Catálogo'!G2:G61,"4.3 *") -> 2 | D45: =IF(B45>0,"Coberta","Sem mitigação") -> Coberta
A46: 4.4 Divulgação da governança | B46: =COUNTIF('Catálogo'!G2:G61,"4.4 *") -> 0 | D46: =IF(B46>0,"Coberta","Sem mitigação") -> Sem mitigação
A47: 4.5 Acesso de terceiros ao sistema | B47: =COUNTIF('Catálogo'!G2:G61,"4.5 *") -> 1 | D47: =IF(B47>0,"Coberta","Sem mitigação") -> Coberta
A48: 4.6 Direitos e recursos dos usuários | B48: =COUNTIF('Catálogo'!G2:G61,"4.6 *") -> 1 | D48: =IF(B48>0,"Coberta","Sem mitigação") -> Coberta
A50: Subcategorias sem mitigação não são necessariamente um problema: algumas podem não ter entradas aplicáveis ao ator do catálogo (por exemplo, segurança de pesos de modelo). Nesses casos, registre o motivo na folha Instruções ou no relato do método.
A52: Pré-triagem por IA | B52: Valor | D52: Situação
A53: Sugeridas como elegíveis pela IA | B53: =COUNTIF(Triagem!U2:U1001,"Sim") -> 558
A54: Já conferidas pelo grupo (com Decisão) | B54: =COUNTA(Triagem!M2:M1001) -> 40
A55: Divergências: grupo disse Não ao Ator e a IA disse Sim, ou o contrário | B55: =SUMPRODUCT((Triagem!G2:G1001<>"")*(Triagem!G2:G1001<>Triagem!Q2:Q1001)) -> 26
